Workbook
Name SILVERBASE: #REF!
Name SILVERBASE: #REF!

Sheet Customs Invoice
A1: PT. VERONIQUE INDONESIA
A2: Jl. Raya Purwonegoro Rt. 007/003, Purwonegoro, Banjarnegara, Jawa Tengah, Zip Code : 53472, INDONESIA
A3: INVOICE
A4: Seller: | B4: PT. VERONIQUE INDONESIA | I4: Invoice No. & Date :
B5: Jl. Raya Purwonegoro Rt. 007/003 Purwonegoro Banjarnegara | I5: L/C No. & Date) :
B6: Jawa Tengah Zip Code : 53472 INDONESIA | I6: BILL TO : | M6: NEW MERCHANDISE
B7: NPWP : 0315202689-529000
B8: Tel : 62-286-598-8594 Fax : 62-286-598-8650
A9: Consignee:
I12: "GSP eligible Article"
I13: Other References: | K13: Country of Origin : | L13: INDONESIA
K14: B/L No. :
A15: Departure Date: | D15: COUNTRY OF ORIGIN: INDONESIA | K15: A/C No. :
A16: Vessel/Flight : | D16: From : INDONESIA | K16: C/T No. : | L16: 1
A17: To : | I17: Terms of Payment: | K17: 30 Day's Net
B19: BOX 1 = GOLD JEWELRY
B20: No | C20: ID Code | D20: USA harmonized code | E20: Item | F20: ID | G20: Qty/Pcs,Pair | I20: N.Weight | J20: G.Weight | K20: Unit Value (material & manufacturing cost) | L20: Total Value (material & manufacturing cost) | M20: Manufacturing Cost (nilai maklon) | N20: Dia Value | O20: Gold Value | P20: Manufacturing + Dia + Gold for US | R20: Total Value | S20: N.Weight
B21: 1 | C21: =CONCATENATE("MFGG-",MID(E21,1,3),MID(E21,10,1),"-IDD") -> #N/A | D21: =VLOOKUP(F21,Sheet2!$A$2:$D$31,4,0) -> #N/A | E21: =VLOOKUP(F21,Sheet2!$A$2:$D$31,2,0) -> #N/A | H21: =VLOOKUP(F21,Sheet2!$A$2:$D$31,3,0) -> #N/A | J21: =ROUND((I21/$I$164)*$J$164,2) -> #DIV/0! | K21: =L21/G21 -> #DIV/0! | R21: =L21 -> 0 | S21: =I21 -> 0
B22: 2 | C22: =CONCATENATE("MFGG-",MID(E22,1,3),MID(E22,10,1),"-IDD") -> #N/A | D22: =VLOOKUP(F22,Sheet2!$A$2:$D$31,4,0) -> #N/A | E22: =VLOOKUP(F22,Sheet2!$A$2:$D$31,2,0) -> #N/A | H22: =VLOOKUP(F22,Sheet2!$A$2:$D$31,3,0) -> #N/A | K22: =L22/G22 -> #DIV/0! | R22: =L22 -> 0 | S22: =I22 -> 0
B23: 3 | C23: =CONCATENATE("MFGG-",MID(E23,1,3),MID(E23,10,1),"-IDD") -> #N/A | D23: =VLOOKUP(F23,Sheet2!$A$2:$D$31,4,0) -> #N/A | E23: =VLOOKUP(F23,Sheet2!$A$2:$D$31,2,0) -> #N/A | H23: =VLOOKUP(F23,Sheet2!$A$2:$D$31,3,0) -> #N/A | K23: =L23/G23 -> #DIV/0! | R23: =L23 -> 0 | S23: =I23 -> 0
B24: 4 | C24: =CONCATENATE("MFGG-",MID(E24,1,3),MID(E24,10,1),"-IDD") -> #N/A | D24: =VLOOKUP(F24,Sheet2!$A$2:$D$31,4,0) -> #N/A | E24: =VLOOKUP(F24,Sheet2!$A$2:$D$31,2,0) -> #N/A | H24: =VLOOKUP(F24,Sheet2!$A$2:$D$31,3,0) -> #N/A | K24: =L24/G24 -> #DIV/0! | R24: =L24 -> 0 | S24: =I24 -> 0
B25: 5 | C25: =CONCATENATE("MFGG-",MID(E25,1,3),MID(E25,10,1),"-IDD") -> #N/A | D25: =VLOOKUP(F25,Sheet2!$A$2:$D$31,4,0) -> #N/A | E25: =VLOOKUP(F25,Sheet2!$A$2:$D$31,2,0) -> #N/A | H25: =VLOOKUP(F25,Sheet2!$A$2:$D$31,3,0) -> #N/A | K25: =L25/G25 -> #DIV/0! | R25: =L25 -> 0 | S25: =I25 -> 0
B26: 6 | C26: =CONCATENATE("MFGG-",MID(E26,1,3),MID(E26,10,1),"-IDD") -> #N/A | D26: =VLOOKUP(F26,Sheet2!$A$2:$D$31,4,0) -> #N/A | E26: =VLOOKUP(F26,Sheet2!$A$2:$D$31,2,0) -> #N/A | H26: =VLOOKUP(F26,Sheet2!$A$2:$D$31,3,0) -> #N/A | K26: =L26/G26 -> #DIV/0! | R26: =L26 -> 0 | S26: =I26 -> 0
B27: 7 | C27: =CONCATENATE("MFGG-",MID(E27,1,3),MID(E27,10,1),"-IDD") -> #N/A | D27: =VLOOKUP(F27,Sheet2!$A$2:$D$31,4,0) -> #N/A | E27: =VLOOKUP(F27,Sheet2!$A$2:$D$31,2,0) -> #N/A | H27: =VLOOKUP(F27,Sheet2!$A$2:$D$31,3,0) -> #N/A | K27: =L27/G27 -> #DIV/0! | R27: =L27 -> 0 | S27: =I27 -> 0
B28: 8 | C28: =CONCATENATE("MFGG-",MID(E28,1,3),MID(E28,10,1),"-IDD") -> #N/A | D28: =VLOOKUP(F28,Sheet2!$A$2:$D$31,4,0) -> #N/A | E28: =VLOOKUP(F28,Sheet2!$A$2:$D$31,2,0) -> #N/A | H28: =VLOOKUP(F28,Sheet2!$A$2:$D$31,3,0) -> #N/A | K28: =L28/G28 -> #DIV/0! | R28: =L28 -> 0 | S28: =I28 -> 0
B29: 9 | C29: =CONCATENATE("MFGG-",MID(E29,1,3),MID(E29,10,1),"-IDD") -> #N/A | D29: =VLOOKUP(F29,Sheet2!$A$2:$D$31,4,0) -> #N/A | E29: =VLOOKUP(F29,Sheet2!$A$2:$D$31,2,0) -> #N/A | H29: =VLOOKUP(F29,Sheet2!$A$2:$D$31,3,0) -> #N/A | K29: =L29/G29 -> #DIV/0! | R29: =L29 -> 0 | S29: =I29 -> 0
B30: 10 | C30: =CONCATENATE("MFGG-",MID(E30,1,3),MID(E30,10,1),"-IDD") -> #N/A | D30: =VLOOKUP(F30,Sheet2!$A$2:$D$31,4,0) -> #N/A | E30: =VLOOKUP(F30,Sheet2!$A$2:$D$31,2,0) -> #N/A | F30: - | H30: =VLOOKUP(F30,Sheet2!$A$2:$D$31,3,0) -> #N/A | K30: =L30/G30 -> #DIV/0! | R30: =L30 -> 0 | S30: =I30 -> 0
B31: 11 | C31: =CONCATENATE("MFGG-",MID(E31,1,3),MID(E31,10,1),"-IDD") -> #N/A | D31: =VLOOKUP(F31,Sheet2!$A$2:$D$31,4,0) -> #N/A | E31: =VLOOKUP(F31,Sheet2!$A$2:$D$31,2,0) -> #N/A | F31: - | H31: =VLOOKUP(F31,Sheet2!$A$2:$D$31,3,0) -> #N/A | K31: =L31/G31 -> #DIV/0! | R31: =L31 -> 0 | S31: =I31 -> 0
B32: 12 | C32: =CONCATENATE("MFGG-",MID(E32,1,3),MID(E32,10,1),"-IDD") -> #N/A | D32: =VLOOKUP(F32,Sheet2!$A$2:$D$31,4,0) -> #N/A | E32: =VLOOKUP(F32,Sheet2!$A$2:$D$31,2,0) -> #N/A | F32: - | H32: =VLOOKUP(F32,Sheet2!$A$2:$D$31,3,0) -> #N/A | K32: =L32/G32 -> #DIV/0! | R32: =L32 -> 0 | S32: =I32 -> 0
B33: 13 | C33: =CONCATENATE("MFGG-",MID(E33,1,3),MID(E33,10,1),"-IDD") -> #N/A | D33: =VLOOKUP(F33,Sheet2!$A$2:$D$31,4,0) -> #N/A | E33: =VLOOKUP(F33,Sheet2!$A$2:$D$31,2,0) -> #N/A | F33: - | H33: =VLOOKUP(F33,Sheet2!$A$2:$D$31,3,0) -> #N/A | K33: =L33/G33 -> #DIV/0! | R33: =L33 -> 0 | S33: =I33 -> 0
B34: 14 | C34: =CONCATENATE("MFGG-",MID(E34,1,3),MID(E34,10,1),"-IDD") -> #N/A | D34: =VLOOKUP(F34,Sheet2!$A$2:$D$31,4,0) -> #N/A | E34: =VLOOKUP(F34,Sheet2!$A$2:$D$31,2,0) -> #N/A | F34: - | H34: =VLOOKUP(F34,Sheet2!$A$2:$D$31,3,0) -> #N/A | K34: =L34/G34 -> #DIV/0! | R34: =L34 -> 0 | S34: =I34 -> 0
B35: 15 | C35: =CONCATENATE("MFGG-",MID(E35,1,3),MID(E35,10,1),"-IDD") -> #N/A | D35: =VLOOKUP(F35,Sheet2!$A$2:$D$31,4,0) -> #N/A | E35: =VLOOKUP(F35,Sheet2!$A$2:$D$31,2,0) -> #N/A | F35: - | H35: =VLOOKUP(F35,Sheet2!$A$2:$D$31,3,0) -> #N/A | K35: =L35/G35 -> #DIV/0! | R35: =L35 -> 0 | S35: =I35 -> 0
B36: 16 | C36: =CONCATENATE("MFGG-",MID(E36,1,3),MID(E36,10,1),"-IDD") -> #N/A | D36: =VLOOKUP(F36,Sheet2!$A$2:$D$31,4,0) -> #N/A | E36: =VLOOKUP(F36,Sheet2!$A$2:$D$31,2,0) -> #N/A | F36: - | H36: =VLOOKUP(F36,Sheet2!$A$2:$D$31,3,0) -> #N/A | K36: =L36/G36 -> #DIV/0! | R36: =L36 -> 0 | S36: =I36 -> 0
B37: 17 | C37: =CONCATENATE("MFGG-",MID(E37,1,3),MID(E37,10,1),"-IDD") -> #N/A | D37: =VLOOKUP(F37,Sheet2!$A$2:$D$31,4,0) -> #N/A | E37: =VLOOKUP(F37,Sheet2!$A$2:$D$31,2,0) -> #N/A | F37: - | H37: =VLOOKUP(F37,Sheet2!$A$2:$D$31,3,0) -> #N/A | K37: =L37/G37 -> #DIV/0! | R37: =L37 -> 0 | S37: =I37 -> 0
B38: 18 | C38: =CONCATENATE("MFGG-",MID(E38,1,3),MID(E38,10,1),"-IDD") -> #N/A | D38: =VLOOKUP(F38,Sheet2!$A$2:$D$31,4,0) -> #N/A | E38: =VLOOKUP(F38,Sheet2!$A$2:$D$31,2,0) -> #N/A | F38: - | H38: =VLOOKUP(F38,Sheet2!$A$2:$D$31,3,0) -> #N/A | K38: =L38/G38 -> #DIV/0! | R38: =L38 -> 0 | S38: =I38 -> 0
B39: 19 | C39: =CONCATENATE("MFGG-",MID(E39,1,3),MID(E39,10,1),"-IDD") -> #N/A | D39: =VLOOKUP(F39,Sheet2!$A$2:$D$31,4,0) -> #N/A | E39: =VLOOKUP(F39,Sheet2!$A$2:$D$31,2,0) -> #N/A | F39: - | H39: =VLOOKUP(F39,Sheet2!$A$2:$D$31,3,0) -> #N/A | K39: =L39/G39 -> #DIV/0! | R39: =L39 -> 0 | S39: =I39 -> 0
B40: 20 | C40: =CONCATENATE("MFGG-",MID(E40,1,3),MID(E40,10,1),"-IDD") -> #N/A | D40: =VLOOKUP(F40,Sheet2!$A$2:$D$31,4,0) -> #N/A | E40: =VLOOKUP(F40,Sheet2!$A$2:$D$31,2,0) -> #N/A | F40: - | H40: =VLOOKUP(F40,Sheet2!$A$2:$D$31,3,0) -> #N/A | K40: =L40/G40 -> #DIV/0! | R40: =L40 -> 0 | S40: =I40 -> 0
E41: TOTAL | G41: =SUM(G21:G40) -> 0 | I41: =SUM(I21:I40) -> 0 | J41: =SUM(J21:J40) -> #DIV/0! | L41: =SUM(L21:L40) -> 0 | M41: =SUM(M21:M40) -> 0 | N41: =SUM(N21:N40) -> 0 | O41: =SUM(O21:O40) -> 0 | P41: =SUM(P21:P40) -> 0
B43: BOX 2 = GOLD JEWELRY
B44: No | C44: ID Code | D44: USA harmonized code | E44: Item | F44: ID | G44: Qty/Pcs,Pair | I44: N.Weight | J44: G.Weight | K44: Unit Value (material & manufacturing cost) | L44: Total Value (material & manufacturing cost) | M44: Manufacturing Cost (nilai maklon) | P44: Manufacturing + Dia + Gold for US
C45: =CONCATENATE("MFGG","-",MID(E45,1,3),MID(E45,10,1),"-","IDD") -> #N/A | D45: =VLOOKUP(F45,Sheet2!$A$2:$D$31,4,0) -> #N/A | E45: =VLOOKUP(F45,Sheet2!$A$2:$D$31,2,0) -> #N/A | H45: =VLOOKUP(F45,Sheet2!$A$2:$D$31,3,0) -> #N/A | K45: =L45/G45 -> #DIV/0!
C46: =CONCATENATE("MFGG","-",MID(E46,1,3),MID(E46,10,1),"-","IDD") -> #N/A | D46: =VLOOKUP(F46,Sheet2!$A$2:$D$31,4,0) -> #N/A | E46: =VLOOKUP(F46,Sheet2!$A$2:$D$31,2,0) -> #N/A | H46: =VLOOKUP(F46,Sheet2!$A$2:$D$31,3,0) -> #N/A | K46: =L46/G46 -> #DIV/0!
C47: =CONCATENATE("MFGG","-",MID(E47,1,3),MID(E47,10,1),"-","IDD") -> #N/A | D47: =VLOOKUP(F47,Sheet2!$A$2:$D$31,4,0) -> #N/A | E47: =VLOOKUP(F47,Sheet2!$A$2:$D$31,2,0) -> #N/A | H47: =VLOOKUP(F47,Sheet2!$A$2:$D$31,3,0) -> #N/A | K47: =L47/G47 -> #DIV/0!
C48: =CONCATENATE("MFGG","-",MID(E48,1,3),MID(E48,10,1),"-","IDD") -> #N/A | D48: =VLOOKUP(F48,Sheet2!$A$2:$D$31,4,0) -> #N/A | E48: =VLOOKUP(F48,Sheet2!$A$2:$D$31,2,0) -> #N/A | H48: =VLOOKUP(F48,Sheet2!$A$2:$D$31,3,0) -> #N/A | K48: =L48/G48 -> #DIV/0!
C49: =CONCATENATE("MFGG","-",MID(E49,1,3),MID(E49,10,1),"-","IDD") -> #N/A | D49: =VLOOKUP(F49,Sheet2!$A$2:$D$31,4,0) -> #N/A | E49: =VLOOKUP(F49,Sheet2!$A$2:$D$31,2,0) -> #N/A | H49: =VLOOKUP(F49,Sheet2!$A$2:$D$31,3,0) -> #N/A | K49: =L49/G49 -> #DIV/0!
C50: =CONCATENATE("MFGG","-",MID(E50,1,3),MID(E50,10,1),"-","IDD") -> #N/A | D50: =VLOOKUP(F50,Sheet2!$A$2:$D$31,4,0) -> #N/A | E50: =VLOOKUP(F50,Sheet2!$A$2:$D$31,2,0) -> #N/A | H50: =VLOOKUP(F50,Sheet2!$A$2:$D$31,3,0) -> #N/A | K50: =L50/G50 -> #DIV/0!
C51: =CONCATENATE("MFGG","-",MID(E51,1,3),MID(E51,10,1),"-","IDD") -> #N/A | D51: =VLOOKUP(F51,Sheet2!$A$2:$D$31,4,0) -> #N/A | E51: =VLOOKUP(F51,Sheet2!$A$2:$D$31,2,0) -> #N/A | H51: =VLOOKUP(F51,Sheet2!$A$2:$D$31,3,0) -> #N/A | K51: =L51/G51 -> #DIV/0!
C52: =CONCATENATE("MFGG","-",MID(E52,1,3),MID(E52,10,1),"-","IDD") -> #N/A | D52: =VLOOKUP(F52,Sheet2!$A$2:$D$31,4,0) -> #N/A | E52: =VLOOKUP(F52,Sheet2!$A$2:$D$31,2,0) -> #N/A | H52: =VLOOKUP(F52,Sheet2!$A$2:$D$31,3,0) -> #N/A | K52: =L52/G52 -> #DIV/0!
C53: =CONCATENATE("MFGG","-",MID(E53,1,3),MID(E53,10,1),"-","IDD") -> #N/A | D53: =VLOOKUP(F53,Sheet2!$A$2:$D$31,4,0) -> #N/A | E53: =VLOOKUP(F53,Sheet2!$A$2:$D$31,2,0) -> #N/A | H53: =VLOOKUP(F53,Sheet2!$A$2:$D$31,3,0) -> #N/A | K53: =L53/G53 -> #DIV/0!
C54: =CONCATENATE("MFGG","-",MID(E54,1,3),MID(E54,10,1),"-","IDD") -> #N/A | D54: =VLOOKUP(F54,Sheet2!$A$2:$D$31,4,0) -> #N/A | E54: =VLOOKUP(F54,Sheet2!$A$2:$D$31,2,0) -> #N/A | H54: =VLOOKUP(F54,Sheet2!$A$2:$D$31,3,0) -> #N/A | K54: =L54/G54 -> #DIV/0!
C55: =CONCATENATE("MFGG","-",MID(E55,1,3),MID(E55,10,1),"-","IDD") -> #N/A | D55: =VLOOKUP(F55,Sheet2!$A$2:$D$31,4,0) -> #N/A | E55: =VLOOKUP(F55,Sheet2!$A$2:$D$31,2,0) -> #N/A | H55: =VLOOKUP(F55,Sheet2!$A$2:$D$31,3,0) -> #N/A | K55: =L55/G55 -> #DIV/0!
C56: =CONCATENATE("MFGG","-",MID(E56,1,3),MID(E56,10,1),"-","IDD") -> #N/A | D56: =VLOOKUP(F56,Sheet2!$A$2:$D$31,4,0) -> #N/A | E56: =VLOOKUP(F56,Sheet2!$A$2:$D$31,2,0) -> #N/A | H56: =VLOOKUP(F56,Sheet2!$A$2:$D$31,3,0) -> #N/A | K56: =L56/G56 -> #DIV/0!
... C64: =CONCATENATE("MFGG","-",MID(E64,1,3),MID(E64,10,1),"-","IDD") -> #N/A | D64: =VLOOKUP(F64,Sheet2!$A$2:$D$31,4,0) -> #N/A | E64: =VLOOKUP(F64,Sheet2!$A$2:$D$31,2,0) -> #N/A | H64: =VLOOKUP(F64,Sheet2!$A$2:$D$31,3,0) -> #N/A | K64: =L64/G64 -> #DIV/0!
E65: TOTAL | G65: =SUM(G45:G64) -> 0 | I65: =SUM(I45:I64) -> 0 | J65: =SUM(J45:J64) -> 0 | L65: =SUM(L45:L64) -> 0 | M65: =SUM(M45:M64) -> 0 | P65: =SUM(P45:P64) -> 0
B67: BOX 3 = GOLD JEWELRY
B68: No | C68: ID Code | D68: USA harmonized code | E68: Item | F68: ID | G68: Qty/Pcs,Pair | I68: N.Weight | J68: G.Weight | K68: Unit Value (material & manufacturing cost) | L68: Total Value (material & manufacturing cost) | M68: Manufacturing Cost (nilai maklon) | P68: Manufacturing + Dia + Gold for US
C69: =CONCATENATE("MFGG","-",MID(E69,1,3),MID(E69,10,1),"-","IDD") -> #N/A | D69: =VLOOKUP(F69,Sheet2!$A$2:$D$31,4,0) -> #N/A | E69: =VLOOKUP(F69,Sheet2!$A$2:$D$31,2,0) -> #N/A | H69: =VLOOKUP(F69,Sheet2!$A$2:$D$31,3,0) -> #N/A | K69: =L69/G69 -> #DIV/0!
C70: =CONCATENATE("MFGG","-",MID(E70,1,3),MID(E70,10,1),"-","IDD") -> #N/A | D70: =VLOOKUP(F70,Sheet2!$A$2:$D$31,4,0) -> #N/A | E70: =VLOOKUP(F70,Sheet2!$A$2:$D$31,2,0) -> #N/A | H70: =VLOOKUP(F70,Sheet2!$A$2:$D$31,3,0) -> #N/A | K70: =L70/G70 -> #DIV/0!
C71: =CONCATENATE("MFGG","-",MID(E71,1,3),MID(E71,10,1),"-","IDD") -> #N/A | D71: =VLOOKUP(F71,Sheet2!$A$2:$D$31,4,0) -> #N/A | E71: =VLOOKUP(F71,Sheet2!$A$2:$D$31,2,0) -> #N/A | H71: =VLOOKUP(F71,Sheet2!$A$2:$D$31,3,0) -> #N/A | K71: =L71/G71 -> #DIV/0!
C72: =CONCATENATE("MFGG","-",MID(E72,1,3),MID(E72,10,1),"-","IDD") -> #N/A | D72: =VLOOKUP(F72,Sheet2!$A$2:$D$31,4,0) -> #N/A | E72: =VLOOKUP(F72,Sheet2!$A$2:$D$31,2,0) -> #N/A | H72: =VLOOKUP(F72,Sheet2!$A$2:$D$31,3,0) -> #N/A | K72: =L72/G72 -> #DIV/0!
C73: =CONCATENATE("MFGG","-",MID(E73,1,3),MID(E73,10,1),"-","IDD") -> #N/A | D73: =VLOOKUP(F73,Sheet2!$A$2:$D$31,4,0) -> #N/A | E73: =VLOOKUP(F73,Sheet2!$A$2:$D$31,2,0) -> #N/A | H73: =VLOOKUP(F73,Sheet2!$A$2:$D$31,3,0) -> #N/A | K73: =L73/G73 -> #DIV/0!
C74: =CONCATENATE("MFGG","-",MID(E74,1,3),MID(E74,10,1),"-","IDD") -> #N/A | D74: =VLOOKUP(F74,Sheet2!$A$2:$D$31,4,0) -> #N/A | E74: =VLOOKUP(F74,Sheet2!$A$2:$D$31,2,0) -> #N/A | H74: =VLOOKUP(F74,Sheet2!$A$2:$D$31,3,0) -> #N/A | K74: =L74/G74 -> #DIV/0!
C75: =CONCATENATE("MFGG","-",MID(E75,1,3),MID(E75,10,1),"-","IDD") -> #N/A | D75: =VLOOKUP(F75,Sheet2!$A$2:$D$31,4,0) -> #N/A | E75: =VLOOKUP(F75,Sheet2!$A$2:$D$31,2,0) -> #N/A | H75: =VLOOKUP(F75,Sheet2!$A$2:$D$31,3,0) -> #N/A | K75: =L75/G75 -> #DIV/0!
C76: =CONCATENATE("MFGG","-",MID(E76,1,3),MID(E76,10,1),"-","IDD") -> #N/A | D76: =VLOOKUP(F76,Sheet2!$A$2:$D$31,4,0) -> #N/A | E76: =VLOOKUP(F76,Sheet2!$A$2:$D$31,2,0) -> #N/A | H76: =VLOOKUP(F76,Sheet2!$A$2:$D$31,3,0) -> #N/A | K76: =L76/G76 -> #DIV/0!
C77: =CONCATENATE("MFGG","-",MID(E77,1,3),MID(E77,10,1),"-","IDD") -> #N/A | D77: =VLOOKUP(F77,Sheet2!$A$2:$D$31,4,0) -> #N/A | E77: =VLOOKUP(F77,Sheet2!$A$2:$D$31,2,0) -> #N/A | H77: =VLOOKUP(F77,Sheet2!$A$2:$D$31,3,0) -> #N/A | K77: =L77/G77 -> #DIV/0!
C78: =CONCATENATE("MFGG","-",MID(E78,1,3),MID(E78,10,1),"-","IDD") -> #N/A | D78: =VLOOKUP(F78,Sheet2!$A$2:$D$31,4,0) -> #N/A | E78: =VLOOKUP(F78,Sheet2!$A$2:$D$31,2,0) -> #N/A | H78: =VLOOKUP(F78,Sheet2!$A$2:$D$31,3,0) -> #N/A | K78: =L78/G78 -> #DIV/0!
C79: =CONCATENATE("MFGG","-",MID(E79,1,3),MID(E79,10,1),"-","IDD") -> #N/A | D79: =VLOOKUP(F79,Sheet2!$A$2:$D$31,4,0) -> #N/A | E79: =VLOOKUP(F79,Sheet2!$A$2:$D$31,2,0) -> #N/A | H79: =VLOOKUP(F79,Sheet2!$A$2:$D$31,3,0) -> #N/A | K79: =L79/G79 -> #DIV/0!
C80: =CONCATENATE("MFGG","-",MID(E80,1,3),MID(E80,10,1),"-","IDD") -> #N/A | D80: =VLOOKUP(F80,Sheet2!$A$2:$D$31,4,0) -> #N/A | E80: =VLOOKUP(F80,Sheet2!$A$2:$D$31,2,0) -> #N/A | H80: =VLOOKUP(F80,Sheet2!$A$2:$D$31,3,0) -> #N/A | K80: =L80/G80 -> #DIV/0!
... C88: =CONCATENATE("MFGG","-",MID(E88,1,3),MID(E88,10,1),"-","IDD") -> #N/A | D88: =VLOOKUP(F88,Sheet2!$A$2:$D$31,4,0) -> #N/A | E88: =VLOOKUP(F88,Sheet2!$A$2:$D$31,2,0) -> #N/A | H88: =VLOOKUP(F88,Sheet2!$A$2:$D$31,3,0) -> #N/A | K88: =L88/G88 -> #DIV/0!
E89: TOTAL | G89: =SUM(G69:G88) -> 0 | I89: =SUM(I69:I88) -> 0 | J89: =SUM(J69:J88) -> 0 | L89: =SUM(L69:L88) -> 0 | M89: =SUM(M69:M88) -> 0 | P89: =SUM(P69:P88) -> 0
B91: BOX 4 = GOLD JEWELRY
B92: No | C92: ID Code | D92: USA harmonized code | E92: Item | F92: ID | G92: Qty/Pcs,Pair | I92: N.Weight | J92: G.Weight | K92: Unit Value (material & manufacturing cost) | L92: Total Value (material & manufacturing cost) | M92: Manufacturing Cost (nilai maklon) | P92: Manufacturing + Dia + Gold for US
C93: =CONCATENATE("MFGG","-",MID(E93,1,3),MID(E93,10,1),"-","IDD") -> #N/A | D93: =VLOOKUP(F93,Sheet2!$A$2:$D$31,4,0) -> #N/A | E93: =VLOOKUP(F93,Sheet2!$A$2:$D$31,2,0) -> #N/A | H93: =VLOOKUP(F93,Sheet2!$A$2:$D$31,3,0) -> #N/A | K93: =L93/G93 -> #DIV/0!
C94: =CONCATENATE("MFGG","-",MID(E94,1,3),MID(E94,10,1),"-","IDD") -> #N/A | D94: =VLOOKUP(F94,Sheet2!$A$2:$D$31,4,0) -> #N/A | E94: =VLOOKUP(F94,Sheet2!$A$2:$D$31,2,0) -> #N/A | H94: =VLOOKUP(F94,Sheet2!$A$2:$D$31,3,0) -> #N/A | K94: =L94/G94 -> #DIV/0!
C95: =CONCATENATE("MFGG","-",MID(E95,1,3),MID(E95,10,1),"-","IDD") -> #N/A | D95: =VLOOKUP(F95,Sheet2!$A$2:$D$31,4,0) -> #N/A | E95: =VLOOKUP(F95,Sheet2!$A$2:$D$31,2,0) -> #N/A | H95: =VLOOKUP(F95,Sheet2!$A$2:$D$31,3,0) -> #N/A | K95: =L95/G95 -> #DIV/0!
C96: =CONCATENATE("MFGG","-",MID(E96,1,3),MID(E96,10,1),"-","IDD") -> #N/A | D96: =VLOOKUP(F96,Sheet2!$A$2:$D$31,4,0) -> #N/A | E96: =VLOOKUP(F96,Sheet2!$A$2:$D$31,2,0) -> #N/A | H96: =VLOOKUP(F96,Sheet2!$A$2:$D$31,3,0) -> #N/A | K96: =L96/G96 -> #DIV/0!
C97: =CONCATENATE("MFGG","-",MID(E97,1,3),MID(E97,10,1),"-","IDD") -> #N/A | D97: =VLOOKUP(F97,Sheet2!$A$2:$D$31,4,0) -> #N/A | E97: =VLOOKUP(F97,Sheet2!$A$2:$D$31,2,0) -> #N/A | H97: =VLOOKUP(F97,Sheet2!$A$2:$D$31,3,0) -> #N/A | K97: =L97/G97 -> #DIV/0!
C98: =CONCATENATE("MFGG","-",MID(E98,1,3),MID(E98,10,1),"-","IDD") -> #N/A | D98: =VLOOKUP(F98,Sheet2!$A$2:$D$31,4,0) -> #N/A | E98: =VLOOKUP(F98,Sheet2!$A$2:$D$31,2,0) -> #N/A | H98: =VLOOKUP(F98,Sheet2!$A$2:$D$31,3,0) -> #N/A | K98: =L98/G98 -> #DIV/0!
C99: =CONCATENATE("MFGG","-",MID(E99,1,3),MID(E99,10,1),"-","IDD") -> #N/A | D99: =VLOOKUP(F99,Sheet2!$A$2:$D$31,4,0) -> #N/A | E99: =VLOOKUP(F99,Sheet2!$A$2:$D$31,2,0) -> #N/A | H99: =VLOOKUP(F99,Sheet2!$A$2:$D$31,3,0) -> #N/A | K99: =L99/G99 -> #DIV/0!
C100: =CONCATENATE("MFGG","-",MID(E100,1,3),MID(E100,10,1),"-","IDD") -> #N/A | D100: =VLOOKUP(F100,Sheet2!$A$2:$D$31,4,0) -> #N/A | E100: =VLOOKUP(F100,Sheet2!$A$2:$D$31,2,0) -> #N/A | H100: =VLOOKUP(F100,Sheet2!$A$2:$D$31,3,0) -> #N/A | K100: =L100/G100 -> #DIV/0!
C101: =CONCATENATE("MFGG","-",MID(E101,1,3),MID(E101,10,1),"-","IDD") -> #N/A | D101: =VLOOKUP(F101,Sheet2!$A$2:$D$31,4,0) -> #N/A | E101: =VLOOKUP(F101,Sheet2!$A$2:$D$31,2,0) -> #N/A | H101: =VLOOKUP(F101,Sheet2!$A$2:$D$31,3,0) -> #N/A | K101: =L101/G101 -> #DIV/0!
C102: =CONCATENATE("MFGG","-",MID(E102,1,3),MID(E102,10,1),"-","IDD") -> #N/A | D102: =VLOOKUP(F102,Sheet2!$A$2:$D$31,4,0) -> #N/A | E102: =VLOOKUP(F102,Sheet2!$A$2:$D$31,2,0) -> #N/A | H102: =VLOOKUP(F102,Sheet2!$A$2:$D$31,3,0) -> #N/A | K102: =L102/G102 -> #DIV/0!
C103: =CONCATENATE("MFGG","-",MID(E103,1,3),MID(E103,10,1),"-","IDD") -> #N/A | D103: =VLOOKUP(F103,Sheet2!$A$2:$D$31,4,0) -> #N/A | E103: =VLOOKUP(F103,Sheet2!$A$2:$D$31,2,0) -> #N/A | H103: =VLOOKUP(F103,Sheet2!$A$2:$D$31,3,0) -> #N/A | K103: =L103/G103 -> #DIV/0!
C104: =CONCATENATE("MFGG","-",MID(E104,1,3),MID(E104,10,1),"-","IDD") -> #N/A | D104: =VLOOKUP(F104,Sheet2!$A$2:$D$31,4,0) -> #N/A | E104: =VLOOKUP(F104,Sheet2!$A$2:$D$31,2,0) -> #N/A | H104: =VLOOKUP(F104,Sheet2!$A$2:$D$31,3,0) -> #N/A | K104: =L104/G104 -> #DIV/0!
... C112: =CONCATENATE("MFGG","-",MID(E112,1,3),MID(E112,10,1),"-","IDD") -> #N/A | D112: =VLOOKUP(F112,Sheet2!$A$2:$D$31,4,0) -> #N/A | E112: =VLOOKUP(F112,Sheet2!$A$2:$D$31,2,0) -> #N/A | H112: =VLOOKUP(F112,Sheet2!$A$2:$D$31,3,0) -> #N/A | K112: =L112/G112 -> #DIV/0!
E113: TOTAL | G113: =SUM(G93:G112) -> 0 | I113: =SUM(I93:I112) -> 0 | J113: =SUM(J93:J112) -> 0 | L113: =SUM(L93:L112) -> 0 | M113: =SUM(M93:M112) -> 0 | P113: =SUM(P93:P112) -> 0
B115: BOX 5 = GOLD JEWELRY
B116: No | C116: ID Code | D116: USA harmonized code | E116: Item | F116: ID | G116: Qty/Pcs,Pair | I116: N.Weight | J116: G.Weight | K116: Unit Value (material & manufacturing cost) | L116: Total Value (material & manufacturing cost) | M116: Manufacturing Cost (nilai maklon) | P116: Manufacturing + Dia + Gold for US
C117: =CONCATENATE("MFGG","-",MID(E117,1,3),MID(E117,10,1),"-","IDD") -> #N/A | D117: =VLOOKUP(F117,Sheet2!$A$2:$D$31,4,0) -> #N/A | E117: =VLOOKUP(F117,Sheet2!$A$2:$D$31,2,0) -> #N/A | H117: =VLOOKUP(F117,Sheet2!$A$2:$D$31,3,0) -> #N/A | K117: =L117/G117 -> #DIV/0!
C118: =CONCATENATE("MFGG","-",MID(E118,1,3),MID(E118,10,1),"-","IDD") -> #N/A | D118: =VLOOKUP(F118,Sheet2!$A$2:$D$31,4,0) -> #N/A | E118: =VLOOKUP(F118,Sheet2!$A$2:$D$31,2,0) -> #N/A | H118: =VLOOKUP(F118,Sheet2!$A$2:$D$31,3,0) -> #N/A | K118: =L118/G118 -> #DIV/0!
C119: =CONCATENATE("MFGG","-",MID(E119,1,3),MID(E119,10,1),"-","IDD") -> #N/A | D119: =VLOOKUP(F119,Sheet2!$A$2:$D$31,4,0) -> #N/A | E119: =VLOOKUP(F119,Sheet2!$A$2:$D$31,2,0) -> #N/A | H119: =VLOOKUP(F119,Sheet2!$A$2:$D$31,3,0) -> #N/A | K119: =L119/G119 -> #DIV/0!
C120: =CONCATENATE("MFGG","-",MID(E120,1,3),MID(E120,10,1),"-","IDD") -> #N/A | D120: =VLOOKUP(F120,Sheet2!$A$2:$D$31,4,0) -> #N/A | E120: =VLOOKUP(F120,Sheet2!$A$2:$D$31,2,0) -> #N/A | H120: =VLOOKUP(F120,Sheet2!$A$2:$D$31,3,0) -> #N/A | K120: =L120/G120 -> #DIV/0!
C121: =CONCATENATE("MFGG","-",MID(E121,1,3),MID(E121,10,1),"-","IDD") -> #N/A | D121: =VLOOKUP(F121,Sheet2!$A$2:$D$31,4,0) -> #N/A | E121: =VLOOKUP(F121,Sheet2!$A$2:$D$31,2,0) -> #N/A | H121: =VLOOKUP(F121,Sheet2!$A$2:$D$31,3,0) -> #N/A | K121: =L121/G121 -> #DIV/0!
C122: =CONCATENATE("MFGG","-",MID(E122,1,3),MID(E122,10,1),"-","IDD") -> #N/A | D122: =VLOOKUP(F122,Sheet2!$A$2:$D$31,4,0) -> #N/A | E122: =VLOOKUP(F122,Sheet2!$A$2:$D$31,2,0) -> #N/A | H122: =VLOOKUP(F122,Sheet2!$A$2:$D$31,3,0) -> #N/A | K122: =L122/G122 -> #DIV/0!
C123: =CONCATENATE("MFGG","-",MID(E123,1,3),MID(E123,10,1),"-","IDD") -> #N/A | D123: =VLOOKUP(F123,Sheet2!$A$2:$D$31,4,0) -> #N/A | E123: =VLOOKUP(F123,Sheet2!$A$2:$D$31,2,0) -> #N/A | H123: =VLOOKUP(F123,Sheet2!$A$2:$D$31,3,0) -> #N/A | K123: =L123/G123 -> #DIV/0!
C124: =CONCATENATE("MFGG","-",MID(E124,1,3),MID(E124,10,1),"-","IDD") -> #N/A | D124: =VLOOKUP(F124,Sheet2!$A$2:$D$31,4,0) -> #N/A | E124: =VLOOKUP(F124,Sheet2!$A$2:$D$31,2,0) -> #N/A | H124: =VLOOKUP(F124,Sheet2!$A$2:$D$31,3,0) -> #N/A | K124: =L124/G124 -> #DIV/0!
C125: =CONCATENATE("MFGG","-",MID(E125,1,3),MID(E125,10,1),"-","IDD") -> #N/A | D125: =VLOOKUP(F125,Sheet2!$A$2:$D$31,4,0) -> #N/A | E125: =VLOOKUP(F125,Sheet2!$A$2:$D$31,2,0) -> #N/A | H125: =VLOOKUP(F125,Sheet2!$A$2:$D$31,3,0) -> #N/A | K125: =L125/G125 -> #DIV/0!
C126: =CONCATENATE("MFGG","-",MID(E126,1,3),MID(E126,10,1),"-","IDD") -> #N/A | D126: =VLOOKUP(F126,Sheet2!$A$2:$D$31,4,0) -> #N/A | E126: =VLOOKUP(F126,Sheet2!$A$2:$D$31,2,0) -> #N/A | H126: =VLOOKUP(F126,Sheet2!$A$2:$D$31,3,0) -> #N/A | K126: =L126/G126 -> #DIV/0!
C127: =CONCATENATE("MFGG","-",MID(E127,1,3),MID(E127,10,1),"-","IDD") -> #N/A | D127: =VLOOKUP(F127,Sheet2!$A$2:$D$31,4,0) -> #N/A | E127: =VLOOKUP(F127,Sheet2!$A$2:$D$31,2,0) -> #N/A | H127: =VLOOKUP(F127,Sheet2!$A$2:$D$31,3,0) -> #N/A | K127: =L127/G127 -> #DIV/0!
C128: =CONCATENATE("MFGG","-",MID(E128,1,3),MID(E128,10,1),"-","IDD") -> #N/A | D128: =VLOOKUP(F128,Sheet2!$A$2:$D$31,4,0) -> #N/A | E128: =VLOOKUP(F128,Sheet2!$A$2:$D$31,2,0) -> #N/A | H128: =VLOOKUP(F128,Sheet2!$A$2:$D$31,3,0) -> #N/A | K128: =L128/G128 -> #DIV/0!
...

Sheet PL
A1: PT. VERONIQUE INDONESIA
A2: Jl. Raya Purwonegoro Rt. 007/003, Purwonegoro, Banjarnegara, Jawa Tengah, Zip Code : 53472, INDONESIA
A3: PACKING LIST
A4: Seller: | B4: PT. VERONIQUE INDONESIA | I4: Invoice No. & Date : | K4: ='Customs Invoice'!K4 -> 0 | L4: ='Customs Invoice'!L4 -> 0
B5: Jl. Raya Purwonegoro Rt. 007/003 Purwonegoro Banjarnegara | I5: L/C No. & Date) :
B6: Jawa Tengah Zip Code : 53472 INDONESIA | I6: ='Customs Invoice'!I6 -> BILL TO : | K6: ='Customs Invoice'!K6 -> 0 | M6: NEW MERCHANDISE
B7: NPWP : 0315202689-529000 | K7: ='Customs Invoice'!K7 -> 0
B8: Tel : 62-286-598-8594 Fax : 62-286-598-8650 | K8: ='Customs Invoice'!K8 -> 0
A9: Consignee: | B9: ='Customs Invoice'!B9 -> 0 | K9: ='Customs Invoice'!K9 -> 0
B10: ='Customs Invoice'!B10 -> 0 | K10: ='Customs Invoice'!K10 -> 0
B11: ='Customs Invoice'!B11 -> 0 | K11: ='Customs Invoice'!K11 -> 0
B12: ='Customs Invoice'!B12 -> 0 | I12: "GSP eligible Article"
B13: ='Customs Invoice'!B13 -> 0 | I13: Other References: | K13: Country of Origin : | L13: INDONESIA
B14: ='Customs Invoice'!B14 -> 0 | K14: B/L No. :
A15: Departure Date: | B15: ='Customs Invoice'!B15 -> 0 | D15: COUNTRY OF ORIGIN: INDONESIA | K15: A/C No. :
A16: Vessel/Flight : | B16: ='Customs Invoice'!B16 -> 0 | D16: From : INDONESIA | K16: C/T No. : | L16: ='Customs Invoice'!L16 -> 1
A17: To : USA | I17: Terms of Payment: | K17: 30 Day's Net
B19: BOX 1 = GOLD JEWELRY
B20: No | C20: ID Code | D20: USA harmonized code | E20: Item | F20: ID | G20: Qty/Pcs,Pair | I20: N.Weight | J20: G.Weight | K20: Jumlah Carton
B21: ='Customs Invoice'!B21 -> 1 | C21: ='Customs Invoice'!C21 -> #N/A | D21: ='Customs Invoice'!D21 -> #N/A | E21: ='Customs Invoice'!E21 -> #N/A | G21: ='Customs Invoice'!G21 -> 0 | H21: ='Customs Invoice'!H21 -> #N/A | I21: ='Customs Invoice'!I21 -> 0 | J21: ='Customs Invoice'!J21 -> #DIV/0! | K21: 1
B22: ='Customs Invoice'!B22 -> 2 | C22: ='Customs Invoice'!C22 -> #N/A | D22: ='Customs Invoice'!D22 -> #N/A | E22: ='Customs Invoice'!E22 -> #N/A | G22: ='Customs Invoice'!G22 -> 0 | H22: ='Customs Invoice'!H22 -> #N/A | I22: ='Customs Invoice'!I22 -> 0 | J22: ='Customs Invoice'!J22 -> 0
B23: ='Customs Invoice'!B23 -> 3 | C23: ='Customs Invoice'!C23 -> #N/A | D23: ='Customs Invoice'!D23 -> #N/A | E23: ='Customs Invoice'!E23 -> #N/A | G23: ='Customs Invoice'!G23 -> 0 | H23: ='Customs Invoice'!H23 -> #N/A | I23: ='Customs Invoice'!I23 -> 0 | J23: ='Customs Invoice'!J23 -> 0
B24: ='Customs Invoice'!B24 -> 4 | C24: ='Customs Invoice'!C24 -> #N/A | D24: ='Customs Invoice'!D24 -> #N/A | E24: ='Customs Invoice'!E24 -> #N/A | G24: ='Customs Invoice'!G24 -> 0 | H24: ='Customs Invoice'!H24 -> #N/A | I24: ='Customs Invoice'!I24 -> 0 | J24: ='Customs Invoice'!J24 -> 0
B25: ='Customs Invoice'!B25 -> 5 | C25: ='Customs Invoice'!C25 -> #N/A | D25: ='Customs Invoice'!D25 -> #N/A | E25: ='Customs Invoice'!E25 -> #N/A | G25: ='Customs Invoice'!G25 -> 0 | H25: ='Customs Invoice'!H25 -> #N/A | I25: ='Customs Invoice'!I25 -> 0 | J25: ='Customs Invoice'!J25 -> 0
B26: ='Customs Invoice'!B26 -> 6 | C26: ='Customs Invoice'!C26 -> #N/A | D26: ='Customs Invoice'!D26 -> #N/A | E26: ='Customs Invoice'!E26 -> #N/A | G26: ='Customs Invoice'!G26 -> 0 | H26: ='Customs Invoice'!H26 -> #N/A | I26: ='Customs Invoice'!I26 -> 0 | J26: ='Customs Invoice'!J26 -> 0
B27: ='Customs Invoice'!B27 -> 7 | C27: ='Customs Invoice'!C27 -> #N/A | D27: ='Customs Invoice'!D27 -> #N/A | E27: ='Customs Invoice'!E27 -> #N/A | G27: ='Customs Invoice'!G27 -> 0 | H27: ='Customs Invoice'!H27 -> #N/A | I27: ='Customs Invoice'!I27 -> 0 | J27: ='Customs Invoice'!J27 -> 0
B28: ='Customs Invoice'!B28 -> 8 | C28: ='Customs Invoice'!C28 -> #N/A | D28: ='Customs Invoice'!D28 -> #N/A | E28: ='Customs Invoice'!E28 -> #N/A | G28: ='Customs Invoice'!G28 -> 0 | H28: ='Customs Invoice'!H28 -> #N/A | I28: ='Customs Invoice'!I28 -> 0 | J28: ='Customs Invoice'!J28 -> 0
B29: ='Customs Invoice'!B29 -> 9 | C29: ='Customs Invoice'!C29 -> #N/A | D29: ='Customs Invoice'!D29 -> #N/A | E29: ='Customs Invoice'!E29 -> #N/A | G29: ='Customs Invoice'!G29 -> 0 | H29: ='Customs Invoice'!H29 -> #N/A | I29: ='Customs Invoice'!I29 -> 0 | J29: ='Customs Invoice'!J29 -> 0
B30: ='Customs Invoice'!B30 -> 10 | C30: ='Customs Invoice'!C30 -> #N/A | D30: ='Customs Invoice'!D30 -> #N/A | E30: ='Customs Invoice'!E30 -> #N/A | G30: ='Customs Invoice'!G30 -> 0 | H30: ='Customs Invoice'!H30 -> #N/A | I30: ='Customs Invoice'!I30 -> 0 | J30: ='Customs Invoice'!J30 -> 0
B31: ='Customs Invoice'!B31 -> 11 | C31: ='Customs Invoice'!C31 -> #N/A | D31: ='Customs Invoice'!D31 -> #N/A | E31: ='Customs Invoice'!E31 -> #N/A | G31: ='Customs Invoice'!G31 -> 0 | H31: ='Customs Invoice'!H31 -> #N/A | I31: ='Customs Invoice'!I31 -> 0 | J31: ='Customs Invoice'!J31 -> 0
B32: ='Customs Invoice'!B32 -> 12 | C32: ='Customs Invoice'!C32 -> #N/A | D32: ='Customs Invoice'!D32 -> #N/A | E32: ='Customs Invoice'!E32 -> #N/A | G32: ='Customs Invoice'!G32 -> 0 | H32: ='Customs Invoice'!H32 -> #N/A | I32: ='Customs Invoice'!I32 -> 0 | J32: ='Customs Invoice'!J32 -> 0
B33: ='Customs Invoice'!B33 -> 13 | C33: ='Customs Invoice'!C33 -> #N/A | D33: ='Customs Invoice'!D33 -> #N/A | E33: ='Customs Invoice'!E33 -> #N/A | G33: ='Customs Invoice'!G33 -> 0 | H33: ='Customs Invoice'!H33 -> #N/A | I33: ='Customs Invoice'!I33 -> 0 | J33: ='Customs Invoice'!J33 -> 0
... B40: ='Customs Invoice'!B40 -> 20 | C40: ='Customs Invoice'!C40 -> #N/A | D40: ='Customs Invoice'!D40 -> #N/A | E40: ='Customs Invoice'!E40 -> #N/A | G40: ='Customs Invoice'!G40 -> 0 | H40: ='Customs Invoice'!H40 -> #N/A | I40: ='Customs Invoice'!I40 -> 0 | J40: ='Customs Invoice'!J40 -> 0
E41: TOTAL | G41: =SUM(G21:G40) -> 0 | I41: =SUM(I21:I40) -> 0 | J41: =SUM(J21:J40) -> #DIV/0! | K41: =SUM(K21) -> 1
B43: BOX 2 = GOLD JEWELRY
B44: No | C44: ID Code | D44: USA harmonized code | E44: Item | F44: ID | G44: Qty/Pcs,Pair | I44: N.Weight | J44: G.Weight | K44: Jumlah Carton
B45: ='Customs Invoice'!B45 -> 0 | C45: ='Customs Invoice'!C45 -> #N/A | D45: ='Customs Invoice'!D45 -> #N/A | E45: ='Customs Invoice'!E45 -> #N/A | G45: ='Customs Invoice'!G45 -> 0 | H45: ='Customs Invoice'!H45 -> #N/A | I45: ='Customs Invoice'!I45 -> 0 | J45: ='Customs Invoice'!J45 -> 0 | K45: 1
B46: ='Customs Invoice'!B46 -> 0 | C46: ='Customs Invoice'!C46 -> #N/A | D46: ='Customs Invoice'!D46 -> #N/A | E46: ='Customs Invoice'!E46 -> #N/A | G46: ='Customs Invoice'!G46 -> 0 | H46: ='Customs Invoice'!H46 -> #N/A | I46: ='Customs Invoice'!I46 -> 0 | J46: ='Customs Invoice'!J46 -> 0
B47: ='Customs Invoice'!B47 -> 0 | C47: ='Customs Invoice'!C47 -> #N/A | D47: ='Customs Invoice'!D47 -> #N/A | E47: ='Customs Invoice'!E47 -> #N/A | G47: ='Customs Invoice'!G47 -> 0 | H47: ='Customs Invoice'!H47 -> #N/A | I47: ='Customs Invoice'!I47 -> 0 | J47: ='Customs Invoice'!J47 -> 0
B48: ='Customs Invoice'!B48 -> 0 | C48: ='Customs Invoice'!C48 -> #N/A | D48: ='Customs Invoice'!D48 -> #N/A | E48: ='Customs Invoice'!E48 -> #N/A | G48: ='Customs Invoice'!G48 -> 0 | H48: ='Customs Invoice'!H48 -> #N/A | I48: ='Customs Invoice'!I48 -> 0 | J48: ='Customs Invoice'!J48 -> 0
B49: ='Customs Invoice'!B49 -> 0 | C49: ='Customs Invoice'!C49 -> #N/A | D49: ='Customs Invoice'!D49 -> #N/A | E49: ='Customs Invoice'!E49 -> #N/A | G49: ='Customs Invoice'!G49 -> 0 | H49: ='Customs Invoice'!H49 -> #N/A | I49: ='Customs Invoice'!I49 -> 0 | J49: ='Customs Invoice'!J49 -> 0
B50: ='Customs Invoice'!B50 -> 0 | C50: ='Customs Invoice'!C50 -> #N/A | D50: ='Customs Invoice'!D50 -> #N/A | E50: ='Customs Invoice'!E50 -> #N/A | G50: ='Customs Invoice'!G50 -> 0 | H50: ='Customs Invoice'!H50 -> #N/A | I50: ='Customs Invoice'!I50 -> 0 | J50: ='Customs Invoice'!J50 -> 0
B51: ='Customs Invoice'!B51 -> 0 | C51: ='Customs Invoice'!C51 -> #N/A | D51: ='Customs Invoice'!D51 -> #N/A | E51: ='Customs Invoice'!E51 -> #N/A | G51: ='Customs Invoice'!G51 -> 0 | H51: ='Customs Invoice'!H51 -> #N/A | I51: ='Customs Invoice'!I51 -> 0 | J51: ='Customs Invoice'!J51 -> 0
B52: ='Customs Invoice'!B52 -> 0 | C52: ='Customs Invoice'!C52 -> #N/A | D52: ='Customs Invoice'!D52 -> #N/A | E52: ='Customs Invoice'!E52 -> #N/A | G52: ='Customs Invoice'!G52 -> 0 | H52: ='Customs Invoice'!H52 -> #N/A | I52: ='Customs Invoice'!I52 -> 0 | J52: ='Customs Invoice'!J52 -> 0
B53: ='Customs Invoice'!B53 -> 0 | C53: ='Customs Invoice'!C53 -> #N/A | D53: ='Customs Invoice'!D53 -> #N/A | E53: ='Customs Invoice'!E53 -> #N/A | G53: ='Customs Invoice'!G53 -> 0 | H53: ='Customs Invoice'!H53 -> #N/A | I53: ='Customs Invoice'!I53 -> 0 | J53: ='Customs Invoice'!J53 -> 0
B54: ='Customs Invoice'!B54 -> 0 | C54: ='Customs Invoice'!C54 -> #N/A | D54: ='Customs Invoice'!D54 -> #N/A | E54: ='Customs Invoice'!E54 -> #N/A | G54: ='Customs Invoice'!G54 -> 0 | H54: ='Customs Invoice'!H54 -> #N/A | I54: ='Customs Invoice'!I54 -> 0 | J54: ='Customs Invoice'!J54 -> 0
B55: ='Customs Invoice'!B55 -> 0 | C55: ='Customs Invoice'!C55 -> #N/A | D55: ='Customs Invoice'!D55 -> #N/A | E55: ='Customs Invoice'!E55 -> #N/A | G55: ='Customs Invoice'!G55 -> 0 | H55: ='Customs Invoice'!H55 -> #N/A | I55: ='Customs Invoice'!I55 -> 0 | J55: ='Customs Invoice'!J55 -> 0
B56: ='Customs Invoice'!B56 -> 0 | C56: ='Customs Invoice'!C56 -> #N/A | D56: ='Customs Invoice'!D56 -> #N/A | E56: ='Customs Invoice'!E56 -> #N/A | G56: ='Customs Invoice'!G56 -> 0 | H56: ='Customs Invoice'!H56 -> #N/A | I56: ='Customs Invoice'!I56 -> 0 | J56: ='Customs Invoice'!J56 -> 0
B57: ='Customs Invoice'!B57 -> 0 | C57: ='Customs Invoice'!C57 -> #N/A | D57: ='Customs Invoice'!D57 -> #N/A | E57: ='Customs Invoice'!E57 -> #N/A | G57: ='Customs Invoice'!G57 -> 0 | H57: ='Customs Invoice'!H57 -> #N/A | I57: ='Customs Invoice'!I57 -> 0 | J57: ='Customs Invoice'!J57 -> 0
... B64: ='Customs Invoice'!B64 -> 0 | C64: ='Customs Invoice'!C64 -> #N/A | D64: ='Customs Invoice'!D64 -> #N/A | E64: ='Customs Invoice'!E64 -> #N/A | G64: ='Customs Invoice'!G64 -> 0 | H64: ='Customs Invoice'!H64 -> #N/A | I64: ='Customs Invoice'!I64 -> 0 | J64: ='Customs Invoice'!J64 -> 0
E65: TOTAL | G65: =SUM(G45:G64) -> 0 | I65: =SUM(I45:I64) -> 0 | J65: =SUM(J45:J64) -> 0 | K65: =SUM(K45) -> 1
B69: BOX 3 = GOLD JEWELRY
B70: No | C70: ID Code | D70: USA harmonized code | E70: Item | F70: ID | G70: Qty/Pcs,Pair | I70: N.Weight | J70: G.Weight | K70: Jumlah Carton
B71: ='Customs Invoice'!B69 -> 0 | C71: ='Customs Invoice'!C69 -> #N/A | D71: ='Customs Invoice'!D69 -> #N/A | E71: ='Customs Invoice'!E69 -> #N/A | G71: ='Customs Invoice'!G69 -> 0 | H71: ='Customs Invoice'!H69 -> #N/A | I71: ='Customs Invoice'!I69 -> 0 | J71: ='Customs Invoice'!J69 -> 0 | K71: 1
B72: ='Customs Invoice'!B70 -> 0 | C72: ='Customs Invoice'!C70 -> #N/A | D72: ='Customs Invoice'!D70 -> #N/A | E72: ='Customs Invoice'!E70 -> #N/A | G72: ='Customs Invoice'!G70 -> 0 | H72: ='Customs Invoice'!H70 -> #N/A | I72: ='Customs Invoice'!I70 -> 0 | J72: ='Customs Invoice'!J70 -> 0
B73: ='Customs Invoice'!B71 -> 0 | C73: ='Customs Invoice'!C71 -> #N/A | D73: ='Customs Invoice'!D71 -> #N/A | E73: ='Customs Invoice'!E71 -> #N/A | G73: ='Customs Invoice'!G71 -> 0 | H73: ='Customs Invoice'!H71 -> #N/A | I73: ='Customs Invoice'!I71 -> 0 | J73: ='Customs Invoice'!J71 -> 0
B74: ='Customs Invoice'!B72 -> 0 | C74: ='Customs Invoice'!C72 -> #N/A | D74: ='Customs Invoice'!D72 -> #N/A | E74: ='Customs Invoice'!E72 -> #N/A | G74: ='Customs Invoice'!G72 -> 0 | H74: ='Customs Invoice'!H72 -> #N/A | I74: ='Customs Invoice'!I72 -> 0 | J74: ='Customs Invoice'!J72 -> 0
B75: ='Customs Invoice'!B73 -> 0 | C75: ='Customs Invoice'!C73 -> #N/A | D75: ='Customs Invoice'!D73 -> #N/A | E75: ='Customs Invoice'!E73 -> #N/A | G75: ='Customs Invoice'!G73 -> 0 | H75: ='Customs Invoice'!H73 -> #N/A | I75: ='Customs Invoice'!I73 -> 0 | J75: ='Customs Invoice'!J73 -> 0
B76: ='Customs Invoice'!B74 -> 0 | C76: ='Customs Invoice'!C74 -> #N/A | D76: ='Customs Invoice'!D74 -> #N/A | E76: ='Customs Invoice'!E74 -> #N/A | G76: ='Customs Invoice'!G74 -> 0 | H76: ='Customs Invoice'!H74 -> #N/A | I76: ='Customs Invoice'!I74 -> 0 | J76: ='Customs Invoice'!J74 -> 0
B77: ='Customs Invoice'!B75 -> 0 | C77: ='Customs Invoice'!C75 -> #N/A | D77: ='Customs Invoice'!D75 -> #N/A | E77: ='Customs Invoice'!E75 -> #N/A | G77: ='Customs Invoice'!G75 -> 0 | H77: ='Customs Invoice'!H75 -> #N/A | I77: ='Customs Invoice'!I75 -> 0 | J77: ='Customs Invoice'!J75 -> 0
B78: ='Customs Invoice'!B76 -> 0 | C78: ='Customs Invoice'!C76 -> #N/A | D78: ='Customs Invoice'!D76 -> #N/A | E78: ='Customs Invoice'!E76 -> #N/A | G78: ='Customs Invoice'!G76 -> 0 | H78: ='Customs Invoice'!H76 -> #N/A | I78: ='Customs Invoice'!I76 -> 0 | J78: ='Customs Invoice'!J76 -> 0
B79: ='Customs Invoice'!B77 -> 0 | C79: ='Customs Invoice'!C77 -> #N/A | D79: ='Customs Invoice'!D77 -> #N/A | E79: ='Customs Invoice'!E77 -> #N/A | G79: ='Customs Invoice'!G77 -> 0 | H79: ='Customs Invoice'!H77 -> #N/A | I79: ='Customs Invoice'!I77 -> 0 | J79: ='Customs Invoice'!J77 -> 0
B80: ='Customs Invoice'!B78 -> 0 | C80: ='Customs Invoice'!C78 -> #N/A | D80: ='Customs Invoice'!D78 -> #N/A | E80: ='Customs Invoice'!E78 -> #N/A | G80: ='Customs Invoice'!G78 -> 0 | H80: ='Customs Invoice'!H78 -> #N/A | I80: ='Customs Invoice'!I78 -> 0 | J80: ='Customs Invoice'!J78 -> 0
B81: ='Customs Invoice'!B79 -> 0 | C81: ='Customs Invoice'!C79 -> #N/A | D81: ='Customs Invoice'!D79 -> #N/A | E81: ='Customs Invoice'!E79 -> #N/A | G81: ='Customs Invoice'!G79 -> 0 | H81: ='Customs Invoice'!H79 -> #N/A | I81: ='Customs Invoice'!I79 -> 0 | J81: ='Customs Invoice'!J79 -> 0
B82: ='Customs Invoice'!B80 -> 0 | C82: ='Customs Invoice'!C80 -> #N/A | D82: ='Customs Invoice'!D80 -> #N/A | E82: ='Customs Invoice'!E80 -> #N/A | G82: ='Customs Invoice'!G80 -> 0 | H82: ='Customs Invoice'!H80 -> #N/A | I82: ='Customs Invoice'!I80 -> 0 | J82: ='Customs Invoice'!J80 -> 0
B83: ='Customs Invoice'!B81 -> 0 | C83: ='Customs Invoice'!C81 -> #N/A | D83: ='Customs Invoice'!D81 -> #N/A | E83: ='Customs Invoice'!E81 -> #N/A | G83: ='Customs Invoice'!G81 -> 0 | H83: ='Customs Invoice'!H81 -> #N/A | I83: ='Customs Invoice'!I81 -> 0 | J83: ='Customs Invoice'!J81 -> 0
... B90: ='Customs Invoice'!B88 -> 0 | C90: ='Customs Invoice'!C88 -> #N/A | D90: ='Customs Invoice'!D88 -> #N/A | E90: ='Customs Invoice'!E88 -> #N/A | G90: ='Customs Invoice'!G88 -> 0 | H90: ='Customs Invoice'!H88 -> #N/A | I90: ='Customs Invoice'!I88 -> 0 | J90: ='Customs Invoice'!J88 -> 0
E91: TOTAL | G91: =SUM(G71:G90) -> 0 | I91: =SUM(I71:I90) -> 0 | J91: =SUM(J71:J90) -> 0 | K91: =SUM(K71) -> 1
B93: BOX 4 = GOLD JEWELRY
B94: No | C94: ID Code | D94: USA harmonized code | E94: Item | F94: ID | G94: Qty/Pcs,Pair | I94: N.Weight | J94: G.Weight | K94: Jumlah Carton
B95: ='Customs Invoice'!B93 -> 0 | C95: ='Customs Invoice'!C93 -> #N/A | D95: ='Customs Invoice'!D93 -> #N/A | E95: ='Customs Invoice'!E93 -> #N/A | G95: ='Customs Invoice'!G93 -> 0 | H95: ='Customs Invoice'!H93 -> #N/A | I95: ='Customs Invoice'!I93 -> 0 | J95: ='Customs Invoice'!J93 -> 0 | K95: 1
B96: ='Customs Invoice'!B94 -> 0 | C96: ='Customs Invoice'!C94 -> #N/A | D96: ='Customs Invoice'!D94 -> #N/A | E96: ='Customs Invoice'!E94 -> #N/A | G96: ='Customs Invoice'!G94 -> 0 | H96: ='Customs Invoice'!H94 -> #N/A | I96: ='Customs Invoice'!I94 -> 0 | J96: ='Customs Invoice'!J94 -> 0
B97: ='Customs Invoice'!B95 -> 0 | C97: ='Customs Invoice'!C95 -> #N/A | D97: ='Customs Invoice'!D95 -> #N/A | E97: ='Customs Invoice'!E95 -> #N/A | G97: ='Customs Invoice'!G95 -> 0 | H97: ='Customs Invoice'!H95 -> #N/A | I97: ='Customs Invoice'!I95 -> 0 | J97: ='Customs Invoice'!J95 -> 0
B98: ='Customs Invoice'!B96 -> 0 | C98: ='Customs Invoice'!C96 -> #N/A | D98: ='Customs Invoice'!D96 -> #N/A | E98: ='Customs Invoice'!E96 -> #N/A | G98: ='Customs Invoice'!G96 -> 0 | H98: ='Customs Invoice'!H96 -> #N/A | I98: ='Customs Invoice'!I96 -> 0 | J98: ='Customs Invoice'!J96 -> 0
B99: ='Customs Invoice'!B97 -> 0 | C99: ='Customs Invoice'!C97 -> #N/A | D99: ='Customs Invoice'!D97 -> #N/A | E99: ='Customs Invoice'!E97 -> #N/A | G99: ='Customs Invoice'!G97 -> 0 | H99: ='Customs Invoice'!H97 -> #N/A | I99: ='Customs Invoice'!I97 -> 0 | J99: ='Customs Invoice'!J97 -> 0
B100: ='Customs Invoice'!B98 -> 0 | C100: ='Customs Invoice'!C98 -> #N/A | D100: ='Customs Invoice'!D98 -> #N/A | E100: ='Customs Invoice'!E98 -> #N/A | G100: ='Customs Invoice'!G98 -> 0 | H100: ='Customs Invoice'!H98 -> #N/A | I100: ='Customs Invoice'!I98 -> 0 | J100: ='Customs Invoice'!J98 -> 0
B101: ='Customs Invoice'!B99 -> 0 | C101: ='Customs Invoice'!C99 -> #N/A | D101: ='Customs Invoice'!D99 -> #N/A | E101: ='Customs Invoice'!E99 -> #N/A | G101: ='Customs Invoice'!G99 -> 0 | H101: ='Customs Invoice'!H99 -> #N/A | I101: ='Customs Invoice'!I99 -> 0 | J101: ='Customs Invoice'!J99 -> 0
B102: ='Customs Invoice'!B100 -> 0 | C102: ='Customs Invoice'!C100 -> #N/A | D102: ='Customs Invoice'!D100 -> #N/A | E102: ='Customs Invoice'!E100 -> #N/A | G102: ='Customs Invoice'!G100 -> 0 | H102: ='Customs Invoice'!H100 -> #N/A | I102: ='Customs Invoice'!I100 -> 0 | J102: ='Customs Invoice'!J100 -> 0
B103: ='Customs Invoice'!B101 -> 0 | C103: ='Customs Invoice'!C101 -> #N/A | D103: ='Customs Invoice'!D101 -> #N/A | E103: ='Customs Invoice'!E101 -> #N/A | G103: ='Customs Invoice'!G101 -> 0 | H103: ='Customs Invoice'!H101 -> #N/A | I103: ='Customs Invoice'!I101 -> 0 | J103: ='Customs Invoice'!J101 -> 0
B104: ='Customs Invoice'!B102 -> 0 | C104: ='Customs Invoice'!C102 -> #N/A | D104: ='Customs Invoice'!D102 -> #N/A | E104: ='Customs Invoice'!E102 -> #N/A | G104: ='Customs Invoice'!G102 -> 0 | H104: ='Customs Invoice'!H102 -> #N/A | I104: ='Customs Invoice'!I102 -> 0 | J104: ='Customs Invoice'!J102 -> 0
B105: ='Customs Invoice'!B103 -> 0 | C105: ='Customs Invoice'!C103 -> #N/A | D105: ='Customs Invoice'!D103 -> #N/A | E105: ='Customs Invoice'!E103 -> #N/A | G105: ='Customs Invoice'!G103 -> 0 | H105: ='Customs Invoice'!H103 -> #N/A | I105: ='Customs Invoice'!I103 -> 0 | J105: ='Customs Invoice'!J103 -> 0
B106: ='Customs Invoice'!B104 -> 0 | C106: ='Customs Invoice'!C104 -> #N/A | D106: ='Customs Invoice'!D104 -> #N/A | E106: ='Customs Invoice'!E104 -> #N/A | G106: ='Customs Invoice'!G104 -> 0 | H106: ='Customs Invoice'!H104 -> #N/A | I106: ='Customs Invoice'!I104 -> 0 | J106: ='Customs Invoice'!J104 -> 0
B107: ='Customs Invoice'!B105 -> 0 | C107: ='Customs Invoice'!C105 -> #N/A | D107: ='Customs Invoice'!D105 -> #N/A | E107: ='Customs Invoice'!E105 -> #N/A | G107: ='Customs Invoice'!G105 -> 0 | H107: ='Customs Invoice'!H105 -> #N/A | I107: ='Customs Invoice'!I105 -> 0 | J107: ='Customs Invoice'!J105 -> 0
... B114: ='Customs Invoice'!B112 -> 0 | C114: ='Customs Invoice'!C112 -> #N/A | D114: ='Customs Invoice'!D112 -> #N/A | E114: ='Customs Invoice'!E112 -> #N/A | G114: ='Customs Invoice'!G112 -> 0 | H114: ='Customs Invoice'!H112 -> #N/A | I114: ='Customs Invoice'!I112 -> 0 | J114: ='Customs Invoice'!J112 -> 0
E115: TOTAL | G115: =SUM(G95:G114) -> 0 | I115: =SUM(I95:I114) -> 0 | J115: =SUM(J95:J114) -> 0 | K115: =SUM(K95) -> 1
B117: BOX 5 = GOLD JEWELRY
B118: No | C118: ID Code | D118: USA harmonized code | E118: Item | F118: ID | G118: Qty/Pcs,Pair | I118: N.Weight | J118: G.Weight | K118: Jumlah Carton
B119: ='Customs Invoice'!B117 -> 0 | C119: ='Customs Invoice'!C117 -> #N/A | D119: ='Customs Invoice'!D117 -> #N/A | E119: ='Customs Invoice'!E117 -> #N/A | G119: ='Customs Invoice'!G117 -> 0 | H119: ='Customs Invoice'!H117 -> #N/A | I119: ='Customs Invoice'!I117 -> 0 | J119: ='Customs Invoice'!J117 -> 0 | K119: 1
B120: ='Customs Invoice'!B118 -> 0 | C120: ='Customs Invoice'!C118 -> #N/A | D120: ='Customs Invoice'!D118 -> #N/A | E120: ='Customs Invoice'!E118 -> #N/A | G120: ='Customs Invoice'!G118 -> 0 | H120: ='Customs Invoice'!H118 -> #N/A | I120: ='Customs Invoice'!I118 -> 0 | J120: ='Customs Invoice'!J118 -> 0
B121: ='Customs Invoice'!B119 -> 0 | C121: ='Customs Invoice'!C119 -> #N/A | D121: ='Customs Invoice'!D119 -> #N/A | E121: ='Customs Invoice'!E119 -> #N/A | G121: ='Customs Invoice'!G119 -> 0 | H121: ='Customs Invoice'!H119 -> #N/A | I121: ='Customs Invoice'!I119 -> 0 | J121: ='Customs Invoice'!J119 -> 0
B122: ='Customs Invoice'!B120 -> 0 | C122: ='Customs Invoice'!C120 -> #N/A | D122: ='Customs Invoice'!D120 -> #N/A | E122: ='Customs Invoice'!E120 -> #N/A | G122: ='Customs Invoice'!G120 -> 0 | H122: ='Customs Invoice'!H120 -> #N/A | I122: ='Customs Invoice'!I120 -> 0 | J122: ='Customs Invoice'!J120 -> 0
B123: ='Customs Invoice'!B121 -> 0 | C123: ='Customs Invoice'!C121 -> #N/A | D123: ='Customs Invoice'!D121 -> #N/A | E123: ='Customs Invoice'!E121 -> #N/A | G123: ='Customs Invoice'!G121 -> 0 | H123: ='Customs Invoice'!H121 -> #N/A | I123: ='Customs Invoice'!I121 -> 0 | J123: ='Customs Invoice'!J121 -> 0
B124: ='Customs Invoice'!B122 -> 0 | C124: ='Customs Invoice'!C122 -> #N/A | D124: ='Customs Invoice'!D122 -> #N/A | E124: ='Customs Invoice'!E122 -> #N/A | G124: ='Customs Invoice'!G122 -> 0 | H124: ='Customs Invoice'!H122 -> #N/A | I124: ='Customs Invoice'!I122 -> 0 | J124: ='Customs Invoice'!J122 -> 0
B125: ='Customs Invoice'!B123 -> 0 | C125: ='Customs Invoice'!C123 -> #N/A | D125: ='Customs Invoice'!D123 -> #N/A | E125: ='Customs Invoice'!E123 -> #N/A | G125: ='Customs Invoice'!G123 -> 0 | H125: ='Customs Invoice'!H123 -> #N/A | I125: ='Customs Invoice'!I123 -> 0 | J125: ='Customs Invoice'!J123 -> 0
B126: ='Customs Invoice'!B124 -> 0 | C126: ='Customs Invoice'!C124 -> #N/A | D126: ='Customs Invoice'!D124 -> #N/A | E126: ='Customs Invoice'!E124 -> #N/A | G126: ='Customs Invoice'!G124 -> 0 | H126: ='Customs Invoice'!H124 -> #N/A | I126: ='Customs Invoice'!I124 -> 0 | J126: ='Customs Invoice'!J124 -> 0
B127: ='Customs Invoice'!B125 -> 0 | C127: ='Customs Invoice'!C125 -> #N/A | D127: ='Customs Invoice'!D125 -> #N/A | E127: ='Customs Invoice'!E125 -> #N/A | G127: ='Customs Invoice'!G125 -> 0 | H127: ='Customs Invoice'!H125 -> #N/A | I127: ='Customs Invoice'!I125 -> 0 | J127: ='Customs Invoice'!J125 -> 0
B128: ='Customs Invoice'!B126 -> 0 | C128: ='Customs Invoice'!C126 -> #N/A | D128: ='Customs Invoice'!D126 -> #N/A | E128: ='Customs Invoice'!E126 -> #N/A | G128: ='Customs Invoice'!G126 -> 0 | H128: ='Customs Invoice'!H126 -> #N/A | I128: ='Customs Invoice'!I126 -> 0 | J128: ='Customs Invoice'!J126 -> 0
B129: ='Customs Invoice'!B127 -> 0 | C129: ='Customs Invoice'!C127 -> #N/A | D129: ='Customs Invoice'!D127 -> #N/A | E129: ='Customs Invoice'!E127 -> #N/A | G129: ='Customs Invoice'!G127 -> 0 | H129: ='Customs Invoice'!H127 -> #N/A | I129: ='Customs Invoice'!I127 -> 0 | J129: ='Customs Invoice'!J127 -> 0
B130: ='Customs Invoice'!B128 -> 0 | C130: ='Customs Invoice'!C128 -> #N/A | D130: ='Customs Invoice'!D128 -> #N/A | E130: ='Customs Invoice'!E128 -> #N/A | G130: ='Customs Invoice'!G128 -> 0 | H130: ='Customs Invoice'!H128 -> #N/A | I130: ='Customs Invoice'!I128 -> 0 | J130: ='Customs Invoice'!J128 -> 0
B131: ='Customs Invoice'!B129 -> 0 | C131: ='Customs Invoice'!C129 -> #N/A | D131: ='Customs Invoice'!D129 -> #N/A | E131: ='Customs Invoice'!E129 -> #N/A | G131: ='Customs Invoice'!G129 -> 0 | H131: ='Customs Invoice'!H129 -> #N/A | I131: ='Customs Invoice'!I129 -> 0 | J131: ='Customs Invoice'!J129 -> 0
...

Sheet US Customs Invoice
A1: PT. VERONIQUE INDONESIA
A2: Jl. Raya Purwonegoro Rt. 007/003, Purwonegoro, Banjarnegara, Jawa Tengah, Zip Code : 53472, INDONESIA
A3: INVOICE
A4: Seller: | B4: PT. VERONIQUE INDONESIA | I4: Invoice No. & Date : | J4: ='Customs Invoice'!K4 -> 0 | K4: ='Customs Invoice'!L4 -> 0
B5: Jl. Raya Purwonegoro Rt. 007/003 Purwonegoro Banjarnegara | I5: L/C No. & Date) :
B6: Jawa Tengah Zip Code : 53472 INDONESIA | I6: ='Customs Invoice'!I6 -> BILL TO : | J6: ='Customs Invoice'!K6 -> 0 | L6: NEW MERCHANDISE
B7: NPWP : 0315202689-529000 | J7: ='Customs Invoice'!K7 -> 0
B8: Tel : 62-286-598-8594 Fax : 62-286-598-8650 | J8: ='Customs Invoice'!K8 -> 0
A9: Consignee: | B9: ='Customs Invoice'!B9 -> 0 | J9: ='Customs Invoice'!K9 -> 0
B10: ='Customs Invoice'!B10 -> 0 | J10: ='Customs Invoice'!K10 -> 0
B11: ='Customs Invoice'!B11 -> 0 | J11: ='Customs Invoice'!K11 -> 0
B12: ='Customs Invoice'!B12 -> 0 | I12: "GSP eligible Article"
B13: ='Customs Invoice'!B13 -> 0 | I13: Other References: | J13: Country of Origin : | K13: INDONESIA
B14: ='Customs Invoice'!B14 -> 0 | J14: B/L No. :
A15: Departure Date: | B15: ='Customs Invoice'!B15 -> 0 | D15: COUNTRY OF ORIGIN: INDONESIA | J15: A/C No. :
A16: Vessel/Flight : | B16: ='Customs Invoice'!B16 -> 0 | D16: From : INDONESIA | J16: C/T No. : | K16: ='Customs Invoice'!L16 -> 1
A17: ='Customs Invoice'!A17 -> To : | I17: Terms of Payment: | J17: 30 Day's Net
B18: =CONCATENATE("PT Veronique to US_",LEFT('Customs Invoice'!K4,13)," Customs Invoice_New Merchandise") -> PT Veronique to US_ Customs Invoice_New Merchandise
B19: BOX 1 = GOLD JEWELRY
B20: No | C20: Manufacturer ID code | D20: USA HTS code | E20: Item description | F20: ID | G20: QTY (Pcs, pairs) | I20: N.Weight | J20: G.Weight | K20: Total value
B21: ='Customs Invoice'!B21 -> 1 | C21: ='Customs Invoice'!C21 -> #N/A | D21: =VLOOKUP(F21,Sheet2!$A$2:$D$31,4,0) -> #N/A | E21: ='Customs Invoice'!E21 -> #N/A | F21: ='Customs Invoice'!F21 -> 0 | G21: ='Customs Invoice'!G21 -> 0 | H21: ='Customs Invoice'!H21 -> #N/A | I21: ='Customs Invoice'!I21 -> 0 | J21: ='Customs Invoice'!J21 -> #DIV/0! | K21: ='Customs Invoice'!P21 -> 0
D22: =VLOOKUP(F22,Sheet2!$A$2:$D$31,4,0) -> #N/A | F22: =F21&1 -> 01
B23: ='Customs Invoice'!B22 -> 2 | C23: ='Customs Invoice'!C22 -> #N/A | D23: =VLOOKUP(F23,Sheet2!$A$2:$D$31,4,0) -> #N/A | E23: ='Customs Invoice'!E22 -> #N/A | F23: ='Customs Invoice'!F22 -> 0 | G23: ='Customs Invoice'!G22 -> 0 | H23: ='Customs Invoice'!H22 -> #N/A | I23: ='Customs Invoice'!I22 -> 0 | J23: ='Customs Invoice'!J22 -> 0 | K23: ='Customs Invoice'!P22 -> 0
D24: =VLOOKUP(F24,Sheet2!$A$2:$D$31,4,0) -> #N/A | F24: =F23&1 -> 01
B25: ='Customs Invoice'!B23 -> 3 | C25: ='Customs Invoice'!C23 -> #N/A | D25: =VLOOKUP(F25,Sheet2!$A$2:$D$31,4,0) -> #N/A | E25: ='Customs Invoice'!E23 -> #N/A | F25: ='Customs Invoice'!F23 -> 0 | G25: ='Customs Invoice'!G23 -> 0 | H25: ='Customs Invoice'!H23 -> #N/A | I25: ='Customs Invoice'!I23 -> 0 | J25: ='Customs Invoice'!J23 -> 0 | K25: ='Customs Invoice'!P23 -> 0
D26: =VLOOKUP(F26,Sheet2!$A$2:$D$31,4,0) -> #N/A | F26: =F25&1 -> 01
B27: ='Customs Invoice'!B24 -> 4 | C27: ='Customs Invoice'!C24 -> #N/A | D27: =VLOOKUP(F27,Sheet2!$A$2:$D$31,4,0) -> #N/A | E27: ='Customs Invoice'!E24 -> #N/A | F27: ='Customs Invoice'!F24 -> 0 | G27: ='Customs Invoice'!G24 -> 0 | H27: ='Customs Invoice'!H24 -> #N/A | I27: ='Customs Invoice'!I24 -> 0 | J27: ='Customs Invoice'!J24 -> 0 | K27: ='Customs Invoice'!P24 -> 0
D28: =VLOOKUP(F28,Sheet2!$A$2:$D$31,4,0) -> #N/A | F28: =F27&1 -> 01
B29: ='Customs Invoice'!B25 -> 5 | C29: ='Customs Invoice'!C25 -> #N/A | D29: =VLOOKUP(F29,Sheet2!$A$2:$D$31,4,0) -> #N/A | E29: ='Customs Invoice'!E25 -> #N/A | F29: ='Customs Invoice'!F25 -> 0 | G29: ='Customs Invoice'!G25 -> 0 | H29: ='Customs Invoice'!H25 -> #N/A | I29: ='Customs Invoice'!I25 -> 0 | J29: ='Customs Invoice'!J25 -> 0 | K29: ='Customs Invoice'!P25 -> 0
D30: =VLOOKUP(F30,Sheet2!$A$2:$D$31,4,0) -> #N/A | F30: =F29&1 -> 01
B31: ='Customs Invoice'!B26 -> 6 | C31: ='Customs Invoice'!C26 -> #N/A | D31: =VLOOKUP(F31,Sheet2!$A$2:$D$31,4,0) -> #N/A | E31: ='Customs Invoice'!E26 -> #N/A | F31: ='Customs Invoice'!F26 -> 0 | G31: ='Customs Invoice'!G26 -> 0 | H31: ='Customs Invoice'!H26 -> #N/A | I31: ='Customs Invoice'!I26 -> 0 | J31: ='Customs Invoice'!J26 -> 0 | K31: ='Customs Invoice'!P26 -> 0
D32: =VLOOKUP(F32,Sheet2!$A$2:$D$31,4,0) -> #N/A | F32: =F31&1 -> 01
B33: ='Customs Invoice'!B27 -> 7 | C33: ='Customs Invoice'!C27 -> #N/A | D33: =VLOOKUP(F33,Sheet2!$A$2:$D$31,4,0) -> #N/A | E33: ='Customs Invoice'!E27 -> #N/A | F33: ='Customs Invoice'!F27 -> 0 | G33: ='Customs Invoice'!G27 -> 0 | H33: ='Customs Invoice'!H27 -> #N/A | I33: ='Customs Invoice'!I27 -> 0 | J33: ='Customs Invoice'!J27 -> 0 | K33: ='Customs Invoice'!P27 -> 0
D34: =VLOOKUP(F34,Sheet2!$A$2:$D$31,4,0) -> #N/A | F34: =F33&1 -> 01
B35: ='Customs Invoice'!B28 -> 8 | C35: ='Customs Invoice'!C28 -> #N/A | D35: =VLOOKUP(F35,Sheet2!$A$2:$D$31,4,0) -> #N/A | E35: ='Customs Invoice'!E28 -> #N/A | F35: ='Customs Invoice'!F28 -> 0 | G35: ='Customs Invoice'!G28 -> 0 | H35: ='Customs Invoice'!H28 -> #N/A | I35: ='Customs Invoice'!I28 -> 0 | J35: ='Customs Invoice'!J28 -> 0 | K35: ='Customs Invoice'!P28 -> 0
D36: =VLOOKUP(F36,Sheet2!$A$2:$D$31,4,0) -> #N/A | F36: =F35&1 -> 01
B37: ='Customs Invoice'!B29 -> 9 | C37: ='Customs Invoice'!C29 -> #N/A | D37: =VLOOKUP(F37,Sheet2!$A$2:$D$31,4,0) -> #N/A | E37: ='Customs Invoice'!E29 -> #N/A | F37: ='Customs Invoice'!F29 -> 0 | G37: ='Customs Invoice'!G29 -> 0 | H37: ='Customs Invoice'!H29 -> #N/A | I37: ='Customs Invoice'!I29 -> 0 | J37: ='Customs Invoice'!J29 -> 0 | K37: ='Customs Invoice'!P29 -> 0
D38: =VLOOKUP(F38,Sheet2!$A$2:$D$31,4,0) -> #N/A | F38: =F37&1 -> 01
B39: ='Customs Invoice'!B30 -> 10 | C39: ='Customs Invoice'!C30 -> #N/A | D39: =VLOOKUP(F39,Sheet2!$A$2:$D$31,4,0) -> #N/A | E39: ='Customs Invoice'!E30 -> #N/A | F39: ='Customs Invoice'!F30 -> - | G39: ='Customs Invoice'!G30 -> 0 | H39: ='Customs Invoice'!H30 -> #N/A | I39: ='Customs Invoice'!I30 -> 0 | J39: ='Customs Invoice'!J30 -> 0 | K39: ='Customs Invoice'!P30 -> 0
D40: =VLOOKUP(F40,Sheet2!$A$2:$D$31,4,0) -> #N/A | F40: =F39&1 -> -1
B41: TOTAL | G41: =SUM(G21:G40) -> 0 | I41: =SUM(I21:I40) -> 0 | J41: =SUM(J21:J40) -> #DIV/0! | K41: =SUM(K21:K40) -> 0
B43: BOX 2 = GOLD JEWELRY
B44: No | C44: Manufacturer ID code | D44: USA HTS code | E44: Item description | F44: ID | G44: QTY (Pcs, pairs) | I44: N.Weight | J44: G.Weight | K44: Unit value | L44: Total value
B45: ='Customs Invoice'!B45 -> 0 | C45: ='Customs Invoice'!C45 -> #N/A | D45: =VLOOKUP(F45,Sheet2!$A$2:$D$31,4,0) -> #N/A | E45: ='Customs Invoice'!E45 -> #N/A | F45: ='Customs Invoice'!F45 -> 0 | G45: ='Customs Invoice'!G45 -> 0 | H45: ='Customs Invoice'!H45 -> #N/A | I45: ='Customs Invoice'!I45 -> 0 | J45: ='Customs Invoice'!J45 -> 0 | K45: =L45/G45 -> #DIV/0! | L45: ='Customs Invoice'!P45 -> 0
D46: =VLOOKUP(F46,Sheet2!$A$2:$D$31,4,0) -> #N/A | F46: =F45&1 -> 01
B47: ='Customs Invoice'!B46 -> 0 | C47: ='Customs Invoice'!C46 -> #N/A | D47: =VLOOKUP(F47,Sheet2!$A$2:$D$31,4,0) -> #N/A | E47: ='Customs Invoice'!E46 -> #N/A | F47: ='Customs Invoice'!F46 -> 0 | G47: ='Customs Invoice'!G46 -> 0 | H47: ='Customs Invoice'!H46 -> #N/A | I47: ='Customs Invoice'!I46 -> 0 | J47: ='Customs Invoice'!J46 -> 0 | K47: =L47/G47 -> #DIV/0! | L47: ='Customs Invoice'!P46 -> 0
D48: =VLOOKUP(F48,Sheet2!$A$2:$D$31,4,0) -> #N/A | F48: =F47&1 -> 01
B49: ='Customs Invoice'!B47 -> 0 | C49: ='Customs Invoice'!C47 -> #N/A | D49: =VLOOKUP(F49,Sheet2!$A$2:$D$31,4,0) -> #N/A | E49: ='Customs Invoice'!E47 -> #N/A | F49: ='Customs Invoice'!F47 -> 0 | G49: ='Customs Invoice'!G47 -> 0 | H49: ='Customs Invoice'!H47 -> #N/A | I49: ='Customs Invoice'!I47 -> 0 | J49: ='Customs Invoice'!J47 -> 0 | K49: =L49/G49 -> #DIV/0! | L49: ='Customs Invoice'!P47 -> 0
D50: =VLOOKUP(F50,Sheet2!$A$2:$D$31,4,0) -> #N/A | F50: =F49&1 -> 01
B51: ='Customs Invoice'!B48 -> 0 | C51: ='Customs Invoice'!C48 -> #N/A | D51: =VLOOKUP(F51,Sheet2!$A$2:$D$31,4,0) -> #N/A | E51: ='Customs Invoice'!E48 -> #N/A | F51: ='Customs Invoice'!F48 -> 0 | G51: ='Customs Invoice'!G48 -> 0 | H51: ='Customs Invoice'!H48 -> #N/A | I51: ='Customs Invoice'!I48 -> 0 | J51: ='Customs Invoice'!J48 -> 0 | K51: =L51/G51 -> #DIV/0! | L51: ='Customs Invoice'!P48 -> 0
D52: =VLOOKUP(F52,Sheet2!$A$2:$D$31,4,0) -> #N/A | F52: =F51&1 -> 01
B53: ='Customs Invoice'!B49 -> 0 | C53: ='Customs Invoice'!C49 -> #N/A | D53: =VLOOKUP(F53,Sheet2!$A$2:$D$31,4,0) -> #N/A | E53: ='Customs Invoice'!E49 -> #N/A | F53: ='Customs Invoice'!F49 -> 0 | G53: ='Customs Invoice'!G49 -> 0 | H53: ='Customs Invoice'!H49 -> #N/A | I53: ='Customs Invoice'!I49 -> 0 | J53: ='Customs Invoice'!J49 -> 0 | K53: =L53/G53 -> #DIV/0! | L53: ='Customs Invoice'!P49 -> 0
D54: =VLOOKUP(F54,Sheet2!$A$2:$D$31,4,0) -> #N/A | F54: =F53&1 -> 01
B55: ='Customs Invoice'!B50 -> 0 | C55: ='Customs Invoice'!C50 -> #N/A | D55: =VLOOKUP(F55,Sheet2!$A$2:$D$31,4,0) -> #N/A | E55: ='Customs Invoice'!E50 -> #N/A | F55: ='Customs Invoice'!F50 -> 0 | G55: ='Customs Invoice'!G50 -> 0 | H55: ='Customs Invoice'!H50 -> #N/A | I55: ='Customs Invoice'!I50 -> 0 | J55: ='Customs Invoice'!J50 -> 0 | K55: =L55/G55 -> #DIV/0! | L55: ='Customs Invoice'!P50 -> 0
D56: =VLOOKUP(F56,Sheet2!$A$2:$D$31,4,0) -> #N/A | F56: =F55&1 -> 01
B57: ='Customs Invoice'!B51 -> 0 | C57: ='Customs Invoice'!C51 -> #N/A | D57: =VLOOKUP(F57,Sheet2!$A$2:$D$31,4,0) -> #N/A | E57: ='Customs Invoice'!E51 -> #N/A | F57: ='Customs Invoice'!F51 -> 0 | G57: ='Customs Invoice'!G51 -> 0 | H57: ='Customs Invoice'!H51 -> #N/A | I57: ='Customs Invoice'!I51 -> 0 | J57: ='Customs Invoice'!J51 -> 0 | K57: =L57/G57 -> #DIV/0! | L57: ='Customs Invoice'!P51 -> 0
D58: =VLOOKUP(F58,Sheet2!$A$2:$D$31,4,0) -> #N/A | F58: =F57&1 -> 01
B59: ='Customs Invoice'!B52 -> 0 | C59: ='Customs Invoice'!C52 -> #N/A | D59: =VLOOKUP(F59,Sheet2!$A$2:$D$31,4,0) -> #N/A | E59: ='Customs Invoice'!E52 -> #N/A | F59: ='Customs Invoice'!F52 -> 0 | G59: ='Customs Invoice'!G52 -> 0 | H59: ='Customs Invoice'!H52 -> #N/A | I59: ='Customs Invoice'!I52 -> 0 | J59: ='Customs Invoice'!J52 -> 0 | K59: =L59/G59 -> #DIV/0! | L59: ='Customs Invoice'!P52 -> 0
D60: =VLOOKUP(F60,Sheet2!$A$2:$D$31,4,0) -> #N/A | F60: =F59&1 -> 01
B61: ='Customs Invoice'!B53 -> 0 | C61: ='Customs Invoice'!C53 -> #N/A | D61: =VLOOKUP(F61,Sheet2!$A$2:$D$31,4,0) -> #N/A | E61: ='Customs Invoice'!E53 -> #N/A | F61: ='Customs Invoice'!F53 -> 0 | G61: ='Customs Invoice'!G53 -> 0 | H61: ='Customs Invoice'!H53 -> #N/A | I61: ='Customs Invoice'!I53 -> 0 | J61: ='Customs Invoice'!J53 -> 0 | K61: =L61/G61 -> #DIV/0! | L61: ='Customs Invoice'!P53 -> 0
D62: =VLOOKUP(F62,Sheet2!$A$2:$D$31,4,0) -> #N/A | F62: =F61&1 -> 01
B63: ='Customs Invoice'!B54 -> 0 | C63: ='Customs Invoice'!C54 -> #N/A | D63: =VLOOKUP(F63,Sheet2!$A$2:$D$31,4,0) -> #N/A | E63: ='Customs Invoice'!E54 -> #N/A | F63: ='Customs Invoice'!F54 -> 0 | G63: ='Customs Invoice'!G54 -> 0 | H63: ='Customs Invoice'!H54 -> #N/A | I63: ='Customs Invoice'!I54 -> 0 | J63: ='Customs Invoice'!J54 -> 0 | K63: =L63/G63 -> #DIV/0! | L63: ='Customs Invoice'!P54 -> 0
D64: =VLOOKUP(F64,Sheet2!$A$2:$D$31,4,0) -> #N/A | F64: =F63&1 -> 01
B65: TOTAL | G65: =SUM(G45:G64) -> 0 | I65: =SUM(I45:I64) -> 0 | J65: =SUM(J45:J64) -> 0 | L65: =SUM(L45:L64) -> 0
B67: BOX 3 = GOLD JEWELRY
B68: No | C68: Manufacturer ID code | D68: USA HTS code | E68: Item description | F68: ID | G68: QTY (Pcs, pairs) | I68: N.Weight | J68: G.Weight | K68: Unit value | L68: Total value
B69: ='Customs Invoice'!B69 -> 0 | C69: ='Customs Invoice'!C69 -> #N/A | D69: =VLOOKUP(F69,Sheet2!$A$2:$D$31,4,0) -> #N/A | E69: ='Customs Invoice'!E69 -> #N/A | F69: ='Customs Invoice'!F69 -> 0 | G69: ='Customs Invoice'!G69 -> 0 | H69: ='Customs Invoice'!H69 -> #N/A | I69: ='Customs Invoice'!I69 -> 0 | J69: ='Customs Invoice'!J69 -> 0 | K69: =L69/G69 -> #DIV/0! | L69: ='Customs Invoice'!P69 -> 0
D70: =VLOOKUP(F70,Sheet2!$A$2:$D$31,4,0) -> #N/A | F70: =F69&1 -> 01
B71: ='Customs Invoice'!B70 -> 0 | C71: ='Customs Invoice'!C70 -> #N/A | D71: =VLOOKUP(F71,Sheet2!$A$2:$D$31,4,0) -> #N/A | E71: ='Customs Invoice'!E70 -> #N/A | F71: ='Customs Invoice'!F70 -> 0 | G71: ='Customs Invoice'!G70 -> 0 | H71: ='Customs Invoice'!H70 -> #N/A | I71: ='Customs Invoice'!I70 -> 0 | J71: ='Customs Invoice'!J70 -> 0 | K71: =L71/G71 -> #DIV/0! | L71: ='Customs Invoice'!P70 -> 0
D72: =VLOOKUP(F72,Sheet2!$A$2:$D$31,4,0) -> #N/A | F72: =F71&1 -> 01
B73: ='Customs Invoice'!B71 -> 0 | C73: ='Customs Invoice'!C71 -> #N/A | D73: =VLOOKUP(F73,Sheet2!$A$2:$D$31,4,0) -> #N/A | E73: ='Customs Invoice'!E71 -> #N/A | F73: ='Customs Invoice'!F71 -> 0 | G73: ='Customs Invoice'!G71 -> 0 | H73: ='Customs Invoice'!H71 -> #N/A | I73: ='Customs Invoice'!I71 -> 0 | J73: ='Customs Invoice'!J71 -> 0 | K73: =L73/G73 -> #DIV/0! | L73: ='Customs Invoice'!P71 -> 0
D74: =VLOOKUP(F74,Sheet2!$A$2:$D$31,4,0) -> #N/A | F74: =F73&1 -> 01
B75: ='Customs Invoice'!B72 -> 0 | C75: ='Customs Invoice'!C72 -> #N/A | D75: =VLOOKUP(F75,Sheet2!$A$2:$D$31,4,0) -> #N/A | E75: ='Customs Invoice'!E72 -> #N/A | F75: ='Customs Invoice'!F72 -> 0 | G75: ='Customs Invoice'!G72 -> 0 | H75: ='Customs Invoice'!H72 -> #N/A | I75: ='Customs Invoice'!I72 -> 0 | J75: ='Customs Invoice'!J72 -> 0 | K75: =L75/G75 -> #DIV/0! | L75: ='Customs Invoice'!P72 -> 0
D76: =VLOOKUP(F76,Sheet2!$A$2:$D$31,4,0) -> #N/A | F76: =F75&1 -> 01
B77: ='Customs Invoice'!B73 -> 0 | C77: ='Customs Invoice'!C73 -> #N/A | D77: =VLOOKUP(F77,Sheet2!$A$2:$D$31,4,0) -> #N/A | E77: ='Customs Invoice'!E73 -> #N/A | F77: ='Customs Invoice'!F73 -> 0 | G77: ='Customs Invoice'!G73 -> 0 | H77: ='Customs Invoice'!H73 -> #N/A | I77: ='Customs Invoice'!I73 -> 0 | J77: ='Customs Invoice'!J73 -> 0 | K77: =L77/G77 -> #DIV/0! | L77: ='Customs Invoice'!P73 -> 0
D78: =VLOOKUP(F78,Sheet2!$A$2:$D$31,4,0) -> #N/A | F78: =F77&1 -> 01
B79: ='Customs Invoice'!B74 -> 0 | C79: ='Customs Invoice'!C74 -> #N/A | D79: =VLOOKUP(F79,Sheet2!$A$2:$D$31,4,0) -> #N/A | E79: ='Customs Invoice'!E74 -> #N/A | F79: ='Customs Invoice'!F74 -> 0 | G79: ='Customs Invoice'!G74 -> 0 | H79: ='Customs Invoice'!H74 -> #N/A | I79: ='Customs Invoice'!I74 -> 0 | J79: ='Customs Invoice'!J74 -> 0 | K79: =L79/G79 -> #DIV/0! | L79: ='Customs Invoice'!P74 -> 0
D80: =VLOOKUP(F80,Sheet2!$A$2:$D$31,4,0) -> #N/A | F80: =F79&1 -> 01
B81: ='Customs Invoice'!B75 -> 0 | C81: ='Customs Invoice'!C75 -> #N/A | D81: =VLOOKUP(F81,Sheet2!$A$2:$D$31,4,0) -> #N/A | E81: ='Customs Invoice'!E75 -> #N/A | F81: ='Customs Invoice'!F75 -> 0 | G81: ='Customs Invoice'!G75 -> 0 | H81: ='Customs Invoice'!H75 -> #N/A | I81: ='Customs Invoice'!I75 -> 0 | J81: ='Customs Invoice'!J75 -> 0 | K81: =L81/G81 -> #DIV/0! | L81: ='Customs Invoice'!P75 -> 0
D82: =VLOOKUP(F82,Sheet2!$A$2:$D$31,4,0) -> #N/A | F82: =F81&1 -> 01
B83: ='Customs Invoice'!B76 -> 0 | C83: ='Customs Invoice'!C76 -> #N/A | D83: =VLOOKUP(F83,Sheet2!$A$2:$D$31,4,0) -> #N/A | E83: ='Customs Invoice'!E76 -> #N/A | F83: ='Customs Invoice'!F76 -> 0 | G83: ='Customs Invoice'!G76 -> 0 | H83: ='Customs Invoice'!H76 -> #N/A | I83: ='Customs Invoice'!I76 -> 0 | J83: ='Customs Invoice'!J76 -> 0 | K83: =L83/G83 -> #DIV/0! | L83: ='Customs Invoice'!P76 -> 0
D84: =VLOOKUP(F84,Sheet2!$A$2:$D$31,4,0) -> #N/A | F84: =F83&1 -> 01
B85: ='Customs Invoice'!B77 -> 0 | C85: ='Customs Invoice'!C77 -> #N/A | D85: =VLOOKUP(F85,Sheet2!$A$2:$D$31,4,0) -> #N/A | E85: ='Customs Invoice'!E77 -> #N/A | F85: ='Customs Invoice'!F77 -> 0 | G85: ='Customs Invoice'!G77 -> 0 | H85: ='Customs Invoice'!H77 -> #N/A | I85: ='Customs Invoice'!I77 -> 0 | J85: ='Customs Invoice'!J77 -> 0 | K85: =L85/G85 -> #DIV/0! | L85: ='Customs Invoice'!P77 -> 0
D86: =VLOOKUP(F86,Sheet2!$A$2:$D$31,4,0) -> #N/A | F86: =F85&1 -> 01
B87: ='Customs Invoice'!B78 -> 0 | C87: ='Customs Invoice'!C78 -> #N/A | D87: =VLOOKUP(F87,Sheet2!$A$2:$D$31,4,0) -> #N/A | E87: ='Customs Invoice'!E78 -> #N/A | F87: ='Customs Invoice'!F78 -> 0 | G87: ='Customs Invoice'!G78 -> 0 | H87: ='Customs Invoice'!H78 -> #N/A | I87: ='Customs Invoice'!I78 -> 0 | J87: ='Customs Invoice'!J78 -> 0 | K87: =L87/G87 -> #DIV/0! | L87: ='Customs Invoice'!P78 -> 0
D88: =VLOOKUP(F88,Sheet2!$A$2:$D$31,4,0) -> #N/A | F88: =F87&1 -> 01
B89: TOTAL | G89: =SUM(G69:G88) -> 0 | I89: =SUM(I69:I88) -> 0 | J89: =SUM(J69:J88) -> 0 | L89: =SUM(L69:L88) -> 0
B91: BOX 4 = GOLD JEWELRY
B92: No | C92: Manufacturer ID code | D92: USA HTS code | E92: Item description | F92: ID | G92: QTY (Pcs, pairs) | I92: N.Weight | J92: G.Weight | K92: Unit value | L92: Total value
B93: ='Customs Invoice'!B93 -> 0 | C93: ='Customs Invoice'!C93 -> #N/A | D93: =VLOOKUP(F93,Sheet2!$A$2:$D$31,4,0) -> #N/A | E93: ='Customs Invoice'!E93 -> #N/A | F93: ='Customs Invoice'!F93 -> 0 | G93: ='Customs Invoice'!G93 -> 0 | H93: ='Customs Invoice'!H93 -> #N/A | I93: ='Customs Invoice'!I93 -> 0 | J93: ='Customs Invoice'!J93 -> 0 | K93: =L93/G93 -> #DIV/0! | L93: ='Customs Invoice'!P93 -> 0
D94: =VLOOKUP(F94,Sheet2!$A$2:$D$31,4,0) -> #N/A | F94: =F93&1 -> 01
B95: ='Customs Invoice'!B94 -> 0 | C95: ='Customs Invoice'!C94 -> #N/A | D95: =VLOOKUP(F95,Sheet2!$A$2:$D$31,4,0) -> #N/A | E95: ='Customs Invoice'!E94 -> #N/A | F95: ='Customs Invoice'!F94 -> 0 | G95: ='Customs Invoice'!G94 -> 0 | H95: ='Customs Invoice'!H94 -> #N/A | I95: ='Customs Invoice'!I94 -> 0 | J95: ='Customs Invoice'!J94 -> 0 | K95: =L95/G95 -> #DIV/0! | L95: ='Customs Invoice'!P94 -> 0
D96: =VLOOKUP(F96,Sheet2!$A$2:$D$31,4,0) -> #N/A | F96: =F95&1 -> 01
B97: ='Customs Invoice'!B95 -> 0 | C97: ='Customs Invoice'!C95 -> #N/A | D97: =VLOOKUP(F97,Sheet2!$A$2:$D$31,4,0) -> #N/A | E97: ='Customs Invoice'!E95 -> #N/A | F97: ='Customs Invoice'!F95 -> 0 | G97: ='Customs Invoice'!G95 -> 0 | H97: ='Customs Invoice'!H95 -> #N/A | I97: ='Customs Invoice'!I95 -> 0 | J97: ='Customs Invoice'!J95 -> 0 | K97: =L97/G97 -> #DIV/0! | L97: ='Customs Invoice'!P95 -> 0
D98: =VLOOKUP(F98,Sheet2!$A$2:$D$31,4,0) -> #N/A | F98: =F97&1 -> 01
B99: ='Customs Invoice'!B96 -> 0 | C99: ='Customs Invoice'!C96 -> #N/A | D99: =VLOOKUP(F99,Sheet2!$A$2:$D$31,4,0) -> #N/A | E99: ='Customs Invoice'!E96 -> #N/A | F99: ='Customs Invoice'!F96 -> 0 | G99: ='Customs Invoice'!G96 -> 0 | H99: ='Customs Invoice'!H96 -> #N/A | I99: ='Customs Invoice'!I96 -> 0 | J99: ='Customs Invoice'!J96 -> 0 | K99: =L99/G99 -> #DIV/0! | L99: ='Customs Invoice'!P96 -> 0
D100: =VLOOKUP(F100,Sheet2!$A$2:$D$31,4,0) -> #N/A | F100: =F99&1 -> 01
B101: ='Customs Invoice'!B97 -> 0 | C101: ='Customs Invoice'!C97 -> #N/A | D101: =VLOOKUP(F101,Sheet2!$A$2:$D$31,4,0) -> #N/A | E101: ='Customs Invoice'!E97 -> #N/A | F101: ='Customs Invoice'!F97 -> 0 | G101: ='Customs Invoice'!G97 -> 0 | H101: ='Customs Invoice'!H97 -> #N/A | I101: ='Customs Invoice'!I97 -> 0 | J101: ='Customs Invoice'!J97 -> 0 | K101: =L101/G101 -> #DIV/0! | L101: ='Customs Invoice'!P97 -> 0
D102: =VLOOKUP(F102,Sheet2!$A$2:$D$31,4,0) -> #N/A | F102: =F101&1 -> 01
B103: ='Customs Invoice'!B98 -> 0 | C103: ='Customs Invoice'!C98 -> #N/A | D103: =VLOOKUP(F103,Sheet2!$A$2:$D$31,4,0) -> #N/A | E103: ='Customs Invoice'!E98 -> #N/A | F103: ='Customs Invoice'!F98 -> 0 | G103: ='Customs Invoice'!G98 -> 0 | H103: ='Customs Invoice'!H98 -> #N/A | I103: ='Customs Invoice'!I98 -> 0 | J103: ='Customs Invoice'!J98 -> 0 | K103: =L103/G103 -> #DIV/0! | L103: ='Customs Invoice'!P98 -> 0
...

Sheet US Customs Invoice GOLD
A1: PT. VERONIQUE INDONESIA
A2: Jl. Raya Purwonegoro Rt. 007/003, Purwonegoro, Banjarnegara, Jawa Tengah, Zip Code : 53472, INDONESIA
A3: INVOICE
A4: Seller: | B4: PT. VERONIQUE INDONESIA | I4: Invoice No. & Date : | J4: ='Customs Invoice'!K4 -> 0 | K4: ='Customs Invoice'!L4 -> 0
B5: Jl. Raya Purwonegoro Rt. 007/003 Purwonegoro Banjarnegara | I5: L/C No. & Date) :
B6: Jawa Tengah Zip Code : 53472 INDONESIA | I6: ='Customs Invoice'!I6 -> BILL TO : | J6: ='Customs Invoice'!K6 -> 0 | L6: NEW MERCHANDISE
B7: NPWP : 0315202689-529000 | J7: ='Customs Invoice'!K7 -> 0
B8: Tel : 62-286-598-8594 Fax : 62-286-598-8650 | J8: ='Customs Invoice'!K8 -> 0
A9: Consignee: | B9: ='Customs Invoice'!B9 -> 0 | J9: ='Customs Invoice'!K9 -> 0
B10: ='Customs Invoice'!B10 -> 0 | J10: ='Customs Invoice'!K10 -> 0
B11: ='Customs Invoice'!B11 -> 0 | J11: ='Customs Invoice'!K11 -> 0
B12: ='Customs Invoice'!B12 -> 0 | I12: "GSP eligible Article"
B13: ='Customs Invoice'!B13 -> 0 | I13: Other References: | J13: Country of Origin : | K13: INDONESIA
B14: ='Customs Invoice'!B14 -> 0 | J14: B/L No. :
A15: Departure Date: | B15: ='Customs Invoice'!B15 -> 0 | D15: COUNTRY OF ORIGIN: INDONESIA | J15: A/C No. :
A16: Vessel/Flight : | B16: ='Customs Invoice'!B16 -> 0 | D16: From : INDONESIA | J16: C/T No. : | K16: ='Customs Invoice'!L16 -> 1
A17: ='Customs Invoice'!A17 -> To : | I17: Terms of Payment: | J17: 30 Day's Net
B18: =CONCATENATE("PT Veronique to US_",LEFT('Customs Invoice'!K4,13)," Customs Invoice_New Merchandise") -> PT Veronique to US_ Customs Invoice_New Merchandise
B19: BOX 1 = GOLD JEWELRY
B20: No | C20: Manufacturer ID code | D20: USA HTS code | E20: Item description | F20: ID | G20: QTY (Pcs, pairs) | I20: N.Weight | J20: G.Weight | K20: Gold Value
B21: ='Customs Invoice'!B21 -> 1 | C21: ='Customs Invoice'!C21 -> #N/A | D21: =VLOOKUP(F21,Sheet2!$A$2:$D$31,4,0) -> #N/A | E21: ='Customs Invoice'!E21 -> #N/A | F21: ='Customs Invoice'!F21 -> 0 | G21: ='Customs Invoice'!G21 -> 0 | H21: ='Customs Invoice'!H21 -> #N/A | I21: ='Customs Invoice'!I21 -> 0 | J21: ='Customs Invoice'!J21 -> #DIV/0! | K21: ='Customs Invoice'!O21 -> 0
D22: =VLOOKUP(F22,Sheet2!$A$2:$D$31,4,0) -> #N/A | F22: =F21&1 -> 01
B23: ='Customs Invoice'!B22 -> 2 | C23: ='Customs Invoice'!C22 -> #N/A | D23: =VLOOKUP(F23,Sheet2!$A$2:$D$31,4,0) -> #N/A | E23: ='Customs Invoice'!E22 -> #N/A | F23: ='Customs Invoice'!F22 -> 0 | G23: ='Customs Invoice'!G22 -> 0 | H23: ='Customs Invoice'!H22 -> #N/A | I23: ='Customs Invoice'!I22 -> 0 | J23: ='Customs Invoice'!J22 -> 0 | K23: ='Customs Invoice'!O22 -> 0
D24: =VLOOKUP(F24,Sheet2!$A$2:$D$31,4,0) -> #N/A | F24: =F23&1 -> 01
B25: ='Customs Invoice'!B23 -> 3 | C25: ='Customs Invoice'!C23 -> #N/A | D25: =VLOOKUP(F25,Sheet2!$A$2:$D$31,4,0) -> #N/A | E25: ='Customs Invoice'!E23 -> #N/A | F25: ='Customs Invoice'!F23 -> 0 | G25: ='Customs Invoice'!G23 -> 0 | H25: ='Customs Invoice'!H23 -> #N/A | I25: ='Customs Invoice'!I23 -> 0 | J25: ='Customs Invoice'!J23 -> 0 | K25: ='Customs Invoice'!O23 -> 0
D26: =VLOOKUP(F26,Sheet2!$A$2:$D$31,4,0) -> #N/A | F26: =F25&1 -> 01
B27: ='Customs Invoice'!B24 -> 4 | C27: ='Customs Invoice'!C24 -> #N/A | D27: =VLOOKUP(F27,Sheet2!$A$2:$D$31,4,0) -> #N/A | E27: ='Customs Invoice'!E24 -> #N/A | F27: ='Customs Invoice'!F24 -> 0 | G27: ='Customs Invoice'!G24 -> 0 | H27: ='Customs Invoice'!H24 -> #N/A | I27: ='Customs Invoice'!I24 -> 0 | J27: ='Customs Invoice'!J24 -> 0 | K27: ='Customs Invoice'!O24 -> 0
D28: =VLOOKUP(F28,Sheet2!$A$2:$D$31,4,0) -> #N/A | F28: =F27&1 -> 01
B29: ='Customs Invoice'!B25 -> 5 | C29: ='Customs Invoice'!C25 -> #N/A | D29: =VLOOKUP(F29,Sheet2!$A$2:$D$31,4,0) -> #N/A | E29: ='Customs Invoice'!E25 -> #N/A | F29: ='Customs Invoice'!F25 -> 0 | G29: ='Customs Invoice'!G25 -> 0 | H29: ='Customs Invoice'!H25 -> #N/A | I29: ='Customs Invoice'!I25 -> 0 | J29: ='Customs Invoice'!J25 -> 0 | K29: ='Customs Invoice'!O25 -> 0
D30: =VLOOKUP(F30,Sheet2!$A$2:$D$31,4,0) -> #N/A | F30: =F29&1 -> 01
B31: ='Customs Invoice'!B26 -> 6 | C31: ='Customs Invoice'!C26 -> #N/A | D31: =VLOOKUP(F31,Sheet2!$A$2:$D$31,4,0) -> #N/A | E31: ='Customs Invoice'!E26 -> #N/A | F31: ='Customs Invoice'!F26 -> 0 | G31: ='Customs Invoice'!G26 -> 0 | H31: ='Customs Invoice'!H26 -> #N/A | I31: ='Customs Invoice'!I26 -> 0 | J31: ='Customs Invoice'!J26 -> 0 | K31: ='Customs Invoice'!O26 -> 0
D32: =VLOOKUP(F32,Sheet2!$A$2:$D$31,4,0) -> #N/A | F32: =F31&1 -> 01
B33: ='Customs Invoice'!B27 -> 7 | C33: ='Customs Invoice'!C27 -> #N/A | D33: =VLOOKUP(F33,Sheet2!$A$2:$D$31,4,0) -> #N/A | E33: ='Customs Invoice'!E27 -> #N/A | F33: ='Customs Invoice'!F27 -> 0 | G33: ='Customs Invoice'!G27 -> 0 | H33: ='Customs Invoice'!H27 -> #N/A | I33: ='Customs Invoice'!I27 -> 0 | J33: ='Customs Invoice'!J27 -> 0 | K33: ='Customs Invoice'!O27 -> 0
D34: =VLOOKUP(F34,Sheet2!$A$2:$D$31,4,0) -> #N/A | F34: =F33&1 -> 01
B35: ='Customs Invoice'!B28 -> 8 | C35: ='Customs Invoice'!C28 -> #N/A | D35: =VLOOKUP(F35,Sheet2!$A$2:$D$31,4,0) -> #N/A | E35: ='Customs Invoice'!E28 -> #N/A | F35: ='Customs Invoice'!F28 -> 0 | G35: ='Customs Invoice'!G28 -> 0 | H35: ='Customs Invoice'!H28 -> #N/A | I35: ='Customs Invoice'!I28 -> 0 | J35: ='Customs Invoice'!J28 -> 0 | K35: ='Customs Invoice'!O28 -> 0
D36: =VLOOKUP(F36,Sheet2!$A$2:$D$31,4,0) -> #N/A | F36: =F35&1 -> 01
B37: ='Customs Invoice'!B29 -> 9 | C37: ='Customs Invoice'!C29 -> #N/A | D37: =VLOOKUP(F37,Sheet2!$A$2:$D$31,4,0) -> #N/A | E37: ='Customs Invoice'!E29 -> #N/A | F37: ='Customs Invoice'!F29 -> 0 | G37: ='Customs Invoice'!G29 -> 0 | H37: ='Customs Invoice'!H29 -> #N/A | I37: ='Customs Invoice'!I29 -> 0 | J37: ='Customs Invoice'!J29 -> 0 | K37: ='Customs Invoice'!O29 -> 0
D38: =VLOOKUP(F38,Sheet2!$A$2:$D$31,4,0) -> #N/A | F38: =F37&1 -> 01
B39: ='Customs Invoice'!B30 -> 10 | C39: ='Customs Invoice'!C30 -> #N/A | D39: =VLOOKUP(F39,Sheet2!$A$2:$D$31,4,0) -> #N/A | E39: ='Customs Invoice'!E30 -> #N/A | F39: ='Customs Invoice'!F30 -> - | G39: ='Customs Invoice'!G30 -> 0 | H39: ='Customs Invoice'!H30 -> #N/A | I39: ='Customs Invoice'!I30 -> 0 | J39: ='Customs Invoice'!J30 -> 0 | K39: ='Customs Invoice'!O30 -> 0
D40: =VLOOKUP(F40,Sheet2!$A$2:$D$31,4,0) -> #N/A | F40: =F39&1 -> -1
B41: TOTAL | G41: =SUM(G21:G40) -> 0 | I41: =SUM(I21:I40) -> 0 | J41: =SUM(J21:J40) -> #DIV/0! | K41: =SUM(K21:K40) -> 0
B43: BOX 2 = GOLD JEWELRY
B44: No | C44: Manufacturer ID code | D44: USA HTS code | E44: Item description | F44: ID | G44: QTY (Pcs, pairs) | I44: N.Weight | J44: G.Weight | K44: Unit value | L44: Total value
B45: ='Customs Invoice'!B45 -> 0 | C45: ='Customs Invoice'!C45 -> #N/A | D45: =VLOOKUP(F45,Sheet2!$A$2:$D$31,4,0) -> #N/A | E45: ='Customs Invoice'!E45 -> #N/A | F45: ='Customs Invoice'!F45 -> 0 | G45: ='Customs Invoice'!G45 -> 0 | H45: ='Customs Invoice'!H45 -> #N/A | I45: ='Customs Invoice'!I45 -> 0 | J45: ='Customs Invoice'!J45 -> 0 | K45: =L45/G45 -> #DIV/0! | L45: ='Customs Invoice'!P45 -> 0
D46: =VLOOKUP(F46,Sheet2!$A$2:$D$31,4,0) -> #N/A | F46: =F45&1 -> 01
B47: ='Customs Invoice'!B46 -> 0 | C47: ='Customs Invoice'!C46 -> #N/A | D47: =VLOOKUP(F47,Sheet2!$A$2:$D$31,4,0) -> #N/A | E47: ='Customs Invoice'!E46 -> #N/A | F47: ='Customs Invoice'!F46 -> 0 | G47: ='Customs Invoice'!G46 -> 0 | H47: ='Customs Invoice'!H46 -> #N/A | I47: ='Customs Invoice'!I46 -> 0 | J47: ='Customs Invoice'!J46 -> 0 | K47: =L47/G47 -> #DIV/0! | L47: ='Customs Invoice'!P46 -> 0
D48: =VLOOKUP(F48,Sheet2!$A$2:$D$31,4,0) -> #N/A | F48: =F47&1 -> 01
B49: ='Customs Invoice'!B47 -> 0 | C49: ='Customs Invoice'!C47 -> #N/A | D49: =VLOOKUP(F49,Sheet2!$A$2:$D$31,4,0) -> #N/A | E49: ='Customs Invoice'!E47 -> #N/A | F49: ='Customs Invoice'!F47 -> 0 | G49: ='Customs Invoice'!G47 -> 0 | H49: ='Customs Invoice'!H47 -> #N/A | I49: ='Customs Invoice'!I47 -> 0 | J49: ='Customs Invoice'!J47 -> 0 | K49: =L49/G49 -> #DIV/0! | L49: ='Customs Invoice'!P47 -> 0
D50: =VLOOKUP(F50,Sheet2!$A$2:$D$31,4,0) -> #N/A | F50: =F49&1 -> 01
B51: ='Customs Invoice'!B48 -> 0 | C51: ='Customs Invoice'!C48 -> #N/A | D51: =VLOOKUP(F51,Sheet2!$A$2:$D$31,4,0) -> #N/A | E51: ='Customs Invoice'!E48 -> #N/A | F51: ='Customs Invoice'!F48 -> 0 | G51: ='Customs Invoice'!G48 -> 0 | H51: ='Customs Invoice'!H48 -> #N/A | I51: ='Customs Invoice'!I48 -> 0 | J51: ='Customs Invoice'!J48 -> 0 | K51: =L51/G51 -> #DIV/0! | L51: ='Customs Invoice'!P48 -> 0
D52: =VLOOKUP(F52,Sheet2!$A$2:$D$31,4,0) -> #N/A | F52: =F51&1 -> 01
B53: ='Customs Invoice'!B49 -> 0 | C53: ='Customs Invoice'!C49 -> #N/A | D53: =VLOOKUP(F53,Sheet2!$A$2:$D$31,4,0) -> #N/A | E53: ='Customs Invoice'!E49 -> #N/A | F53: ='Customs Invoice'!F49 -> 0 | G53: ='Customs Invoice'!G49 -> 0 | H53: ='Customs Invoice'!H49 -> #N/A | I53: ='Customs Invoice'!I49 -> 0 | J53: ='Customs Invoice'!J49 -> 0 | K53: =L53/G53 -> #DIV/0! | L53: ='Customs Invoice'!P49 -> 0
D54: =VLOOKUP(F54,Sheet2!$A$2:$D$31,4,0) -> #N/A | F54: =F53&1 -> 01
B55: ='Customs Invoice'!B50 -> 0 | C55: ='Customs Invoice'!C50 -> #N/A | D55: =VLOOKUP(F55,Sheet2!$A$2:$D$31,4,0) -> #N/A | E55: ='Customs Invoice'!E50 -> #N/A | F55: ='Customs Invoice'!F50 -> 0 | G55: ='Customs Invoice'!G50 -> 0 | H55: ='Customs Invoice'!H50 -> #N/A | I55: ='Customs Invoice'!I50 -> 0 | J55: ='Customs Invoice'!J50 -> 0 | K55: =L55/G55 -> #DIV/0! | L55: ='Customs Invoice'!P50 -> 0
D56: =VLOOKUP(F56,Sheet2!$A$2:$D$31,4,0) -> #N/A | F56: =F55&1 -> 01
B57: ='Customs Invoice'!B51 -> 0 | C57: ='Customs Invoice'!C51 -> #N/A | D57: =VLOOKUP(F57,Sheet2!$A$2:$D$31,4,0) -> #N/A | E57: ='Customs Invoice'!E51 -> #N/A | F57: ='Customs Invoice'!F51 -> 0 | G57: ='Customs Invoice'!G51 -> 0 | H57: ='Customs Invoice'!H51 -> #N/A | I57: ='Customs Invoice'!I51 -> 0 | J57: ='Customs Invoice'!J51 -> 0 | K57: =L57/G57 -> #DIV/0! | L57: ='Customs Invoice'!P51 -> 0
D58: =VLOOKUP(F58,Sheet2!$A$2:$D$31,4,0) -> #N/A | F58: =F57&1 -> 01
B59: ='Customs Invoice'!B52 -> 0 | C59: ='Customs Invoice'!C52 -> #N/A | D59: =VLOOKUP(F59,Sheet2!$A$2:$D$31,4,0) -> #N/A | E59: ='Customs Invoice'!E52 -> #N/A | F59: ='Customs Invoice'!F52 -> 0 | G59: ='Customs Invoice'!G52 -> 0 | H59: ='Customs Invoice'!H52 -> #N/A | I59: ='Customs Invoice'!I52 -> 0 | J59: ='Customs Invoice'!J52 -> 0 | K59: =L59/G59 -> #DIV/0! | L59: ='Customs Invoice'!P52 -> 0
D60: =VLOOKUP(F60,Sheet2!$A$2:$D$31,4,0) -> #N/A | F60: =F59&1 -> 01
B61: ='Customs Invoice'!B53 -> 0 | C61: ='Customs Invoice'!C53 -> #N/A | D61: =VLOOKUP(F61,Sheet2!$A$2:$D$31,4,0) -> #N/A | E61: ='Customs Invoice'!E53 -> #N/A | F61: ='Customs Invoice'!F53 -> 0 | G61: ='Customs Invoice'!G53 -> 0 | H61: ='Customs Invoice'!H53 -> #N/A | I61: ='Customs Invoice'!I53 -> 0 | J61: ='Customs Invoice'!J53 -> 0 | K61: =L61/G61 -> #DIV/0! | L61: ='Customs Invoice'!P53 -> 0
D62: =VLOOKUP(F62,Sheet2!$A$2:$D$31,4,0) -> #N/A | F62: =F61&1 -> 01
B63: ='Customs Invoice'!B54 -> 0 | C63: ='Customs Invoice'!C54 -> #N/A | D63: =VLOOKUP(F63,Sheet2!$A$2:$D$31,4,0) -> #N/A | E63: ='Customs Invoice'!E54 -> #N/A | F63: ='Customs Invoice'!F54 -> 0 | G63: ='Customs Invoice'!G54 -> 0 | H63: ='Customs Invoice'!H54 -> #N/A | I63: ='Customs Invoice'!I54 -> 0 | J63: ='Customs Invoice'!J54 -> 0 | K63: =L63/G63 -> #DIV/0! | L63: ='Customs Invoice'!P54 -> 0
D64: =VLOOKUP(F64,Sheet2!$A$2:$D$31,4,0) -> #N/A | F64: =F63&1 -> 01
B65: TOTAL | G65: =SUM(G45:G64) -> 0 | I65: =SUM(I45:I64) -> 0 | J65: =SUM(J45:J64) -> 0 | L65: =SUM(L45:L64) -> 0
B67: BOX 3 = GOLD JEWELRY
B68: No | C68: Manufacturer ID code | D68: USA HTS code | E68: Item description | F68: ID | G68: QTY (Pcs, pairs) | I68: N.Weight | J68: G.Weight | K68: Unit value | L68: Total value
B69: ='Customs Invoice'!B69 -> 0 | C69: ='Customs Invoice'!C69 -> #N/A | D69: =VLOOKUP(F69,Sheet2!$A$2:$D$31,4,0) -> #N/A | E69: ='Customs Invoice'!E69 -> #N/A | F69: ='Customs Invoice'!F69 -> 0 | G69: ='Customs Invoice'!G69 -> 0 | H69: ='Customs Invoice'!H69 -> #N/A | I69: ='Customs Invoice'!I69 -> 0 | J69: ='Customs Invoice'!J69 -> 0 | K69: =L69/G69 -> #DIV/0! | L69: ='Customs Invoice'!P69 -> 0
D70: =VLOOKUP(F70,Sheet2!$A$2:$D$31,4,0) -> #N/A | F70: =F69&1 -> 01
B71: ='Customs Invoice'!B70 -> 0 | C71: ='Customs Invoice'!C70 -> #N/A | D71: =VLOOKUP(F71,Sheet2!$A$2:$D$31,4,0) -> #N/A | E71: ='Customs Invoice'!E70 -> #N/A | F71: ='Customs Invoice'!F70 -> 0 | G71: ='Customs Invoice'!G70 -> 0 | H71: ='Customs Invoice'!H70 -> #N/A | I71: ='Customs Invoice'!I70 -> 0 | J71: ='Customs Invoice'!J70 -> 0 | K71: =L71/G71 -> #DIV/0! | L71: ='Customs Invoice'!P70 -> 0
D72: =VLOOKUP(F72,Sheet2!$A$2:$D$31,4,0) -> #N/A | F72: =F71&1 -> 01
B73: ='Customs Invoice'!B71 -> 0 | C73: ='Customs Invoice'!C71 -> #N/A | D73: =VLOOKUP(F73,Sheet2!$A$2:$D$31,4,0) -> #N/A | E73: ='Customs Invoice'!E71 -> #N/A | F73: ='Customs Invoice'!F71 -> 0 | G73: ='Customs Invoice'!G71 -> 0 | H73: ='Customs Invoice'!H71 -> #N/A | I73: ='Customs Invoice'!I71 -> 0 | J73: ='Customs Invoice'!J71 -> 0 | K73: =L73/G73 -> #DIV/0! | L73: ='Customs Invoice'!P71 -> 0
D74: =VLOOKUP(F74,Sheet2!$A$2:$D$31,4,0) -> #N/A | F74: =F73&1 -> 01
B75: ='Customs Invoice'!B72 -> 0 | C75: ='Customs Invoice'!C72 -> #N/A | D75: =VLOOKUP(F75,Sheet2!$A$2:$D$31,4,0) -> #N/A | E75: ='Customs Invoice'!E72 -> #N/A | F75: ='Customs Invoice'!F72 -> 0 | G75: ='Customs Invoice'!G72 -> 0 | H75: ='Customs Invoice'!H72 -> #N/A | I75: ='Customs Invoice'!I72 -> 0 | J75: ='Customs Invoice'!J72 -> 0 | K75: =L75/G75 -> #DIV/0! | L75: ='Customs Invoice'!P72 -> 0
D76: =VLOOKUP(F76,Sheet2!$A$2:$D$31,4,0) -> #N/A | F76: =F75&1 -> 01
B77: ='Customs Invoice'!B73 -> 0 | C77: ='Customs Invoice'!C73 -> #N/A | D77: =VLOOKUP(F77,Sheet2!$A$2:$D$31,4,0) -> #N/A | E77: ='Customs Invoice'!E73 -> #N/A | F77: ='Customs Invoice'!F73 -> 0 | G77: ='Customs Invoice'!G73 -> 0 | H77: ='Customs Invoice'!H73 -> #N/A | I77: ='Customs Invoice'!I73 -> 0 | J77: ='Customs Invoice'!J73 -> 0 | K77: =L77/G77 -> #DIV/0! | L77: ='Customs Invoice'!P73 -> 0
D78: =VLOOKUP(F78,Sheet2!$A$2:$D$31,4,0) -> #N/A | F78: =F77&1 -> 01
B79: ='Customs Invoice'!B74 -> 0 | C79: ='Customs Invoice'!C74 -> #N/A | D79: =VLOOKUP(F79,Sheet2!$A$2:$D$31,4,0) -> #N/A | E79: ='Customs Invoice'!E74 -> #N/A | F79: ='Customs Invoice'!F74 -> 0 | G79: ='Customs Invoice'!G74 -> 0 | H79: ='Customs Invoice'!H74 -> #N/A | I79: ='Customs Invoice'!I74 -> 0 | J79: ='Customs Invoice'!J74 -> 0 | K79: =L79/G79 -> #DIV/0! | L79: ='Customs Invoice'!P74 -> 0
D80: =VLOOKUP(F80,Sheet2!$A$2:$D$31,4,0) -> #N/A | F80: =F79&1 -> 01
B81: ='Customs Invoice'!B75 -> 0 | C81: ='Customs Invoice'!C75 -> #N/A | D81: =VLOOKUP(F81,Sheet2!$A$2:$D$31,4,0) -> #N/A | E81: ='Customs Invoice'!E75 -> #N/A | F81: ='Customs Invoice'!F75 -> 0 | G81: ='Customs Invoice'!G75 -> 0 | H81: ='Customs Invoice'!H75 -> #N/A | I81: ='Customs Invoice'!I75 -> 0 | J81: ='Customs Invoice'!J75 -> 0 | K81: =L81/G81 -> #DIV/0! | L81: ='Customs Invoice'!P75 -> 0
D82: =VLOOKUP(F82,Sheet2!$A$2:$D$31,4,0) -> #N/A | F82: =F81&1 -> 01
B83: ='Customs Invoice'!B76 -> 0 | C83: ='Customs Invoice'!C76 -> #N/A | D83: =VLOOKUP(F83,Sheet2!$A$2:$D$31,4,0) -> #N/A | E83: ='Customs Invoice'!E76 -> #N/A | F83: ='Customs Invoice'!F76 -> 0 | G83: ='Customs Invoice'!G76 -> 0 | H83: ='Customs Invoice'!H76 -> #N/A | I83: ='Customs Invoice'!I76 -> 0 | J83: ='Customs Invoice'!J76 -> 0 | K83: =L83/G83 -> #DIV/0! | L83: ='Customs Invoice'!P76 -> 0
D84: =VLOOKUP(F84,Sheet2!$A$2:$D$31,4,0) -> #N/A | F84: =F83&1 -> 01
B85: ='Customs Invoice'!B77 -> 0 | C85: ='Customs Invoice'!C77 -> #N/A | D85: =VLOOKUP(F85,Sheet2!$A$2:$D$31,4,0) -> #N/A | E85: ='Customs Invoice'!E77 -> #N/A | F85: ='Customs Invoice'!F77 -> 0 | G85: ='Customs Invoice'!G77 -> 0 | H85: ='Customs Invoice'!H77 -> #N/A | I85: ='Customs Invoice'!I77 -> 0 | J85: ='Customs Invoice'!J77 -> 0 | K85: =L85/G85 -> #DIV/0! | L85: ='Customs Invoice'!P77 -> 0
D86: =VLOOKUP(F86,Sheet2!$A$2:$D$31,4,0) -> #N/A | F86: =F85&1 -> 01
B87: ='Customs Invoice'!B78 -> 0 | C87: ='Customs Invoice'!C78 -> #N/A | D87: =VLOOKUP(F87,Sheet2!$A$2:$D$31,4,0) -> #N/A | E87: ='Customs Invoice'!E78 -> #N/A | F87: ='Customs Invoice'!F78 -> 0 | G87: ='Customs Invoice'!G78 -> 0 | H87: ='Customs Invoice'!H78 -> #N/A | I87: ='Customs Invoice'!I78 -> 0 | J87: ='Customs Invoice'!J78 -> 0 | K87: =L87/G87 -> #DIV/0! | L87: ='Customs Invoice'!P78 -> 0
D88: =VLOOKUP(F88,Sheet2!$A$2:$D$31,4,0) -> #N/A | F88: =F87&1 -> 01
B89: TOTAL | G89: =SUM(G69:G88) -> 0 | I89: =SUM(I69:I88) -> 0 | J89: =SUM(J69:J88) -> 0 | L89: =SUM(L69:L88) -> 0
B91: BOX 4 = GOLD JEWELRY
B92: No | C92: Manufacturer ID code | D92: USA HTS code | E92: Item description | F92: ID | G92: QTY (Pcs, pairs) | I92: N.Weight | J92: G.Weight | K92: Unit value | L92: Total value
B93: ='Customs Invoice'!B93 -> 0 | C93: ='Customs Invoice'!C93 -> #N/A | D93: =VLOOKUP(F93,Sheet2!$A$2:$D$31,4,0) -> #N/A | E93: ='Customs Invoice'!E93 -> #N/A | F93: ='Customs Invoice'!F93 -> 0 | G93: ='Customs Invoice'!G93 -> 0 | H93: ='Customs Invoice'!H93 -> #N/A | I93: ='Customs Invoice'!I93 -> 0 | J93: ='Customs Invoice'!J93 -> 0 | K93: =L93/G93 -> #DIV/0! | L93: ='Customs Invoice'!P93 -> 0
D94: =VLOOKUP(F94,Sheet2!$A$2:$D$31,4,0) -> #N/A | F94: =F93&1 -> 01
B95: ='Customs Invoice'!B94 -> 0 | C95: ='Customs Invoice'!C94 -> #N/A | D95: =VLOOKUP(F95,Sheet2!$A$2:$D$31,4,0) -> #N/A | E95: ='Customs Invoice'!E94 -> #N/A | F95: ='Customs Invoice'!F94 -> 0 | G95: ='Customs Invoice'!G94 -> 0 | H95: ='Customs Invoice'!H94 -> #N/A | I95: ='Customs Invoice'!I94 -> 0 | J95: ='Customs Invoice'!J94 -> 0 | K95: =L95/G95 -> #DIV/0! | L95: ='Customs Invoice'!P94 -> 0
D96: =VLOOKUP(F96,Sheet2!$A$2:$D$31,4,0) -> #N/A | F96: =F95&1 -> 01
B97: ='Customs Invoice'!B95 -> 0 | C97: ='Customs Invoice'!C95 -> #N/A | D97: =VLOOKUP(F97,Sheet2!$A$2:$D$31,4,0) -> #N/A | E97: ='Customs Invoice'!E95 -> #N/A | F97: ='Customs Invoice'!F95 -> 0 | G97: ='Customs Invoice'!G95 -> 0 | H97: ='Customs Invoice'!H95 -> #N/A | I97: ='Customs Invoice'!I95 -> 0 | J97: ='Customs Invoice'!J95 -> 0 | K97: =L97/G97 -> #DIV/0! | L97: ='Customs Invoice'!P95 -> 0
D98: =VLOOKUP(F98,Sheet2!$A$2:$D$31,4,0) -> #N/A | F98: =F97&1 -> 01
B99: ='Customs Invoice'!B96 -> 0 | C99: ='Customs Invoice'!C96 -> #N/A | D99: =VLOOKUP(F99,Sheet2!$A$2:$D$31,4,0) -> #N/A | E99: ='Customs Invoice'!E96 -> #N/A | F99: ='Customs Invoice'!F96 -> 0 | G99: ='Customs Invoice'!G96 -> 0 | H99: ='Customs Invoice'!H96 -> #N/A | I99: ='Customs Invoice'!I96 -> 0 | J99: ='Customs Invoice'!J96 -> 0 | K99: =L99/G99 -> #DIV/0! | L99: ='Customs Invoice'!P96 -> 0
D100: =VLOOKUP(F100,Sheet2!$A$2:$D$31,4,0) -> #N/A | F100: =F99&1 -> 01
B101: ='Customs Invoice'!B97 -> 0 | C101: ='Customs Invoice'!C97 -> #N/A | D101: =VLOOKUP(F101,Sheet2!$A$2:$D$31,4,0) -> #N/A | E101: ='Customs Invoice'!E97 -> #N/A | F101: ='Customs Invoice'!F97 -> 0 | G101: ='Customs Invoice'!G97 -> 0 | H101: ='Customs Invoice'!H97 -> #N/A | I101: ='Customs Invoice'!I97 -> 0 | J101: ='Customs Invoice'!J97 -> 0 | K101: =L101/G101 -> #DIV/0! | L101: ='Customs Invoice'!P97 -> 0
D102: =VLOOKUP(F102,Sheet2!$A$2:$D$31,4,0) -> #N/A | F102: =F101&1 -> 01
B103: ='Customs Invoice'!B98 -> 0 | C103: ='Customs Invoice'!C98 -> #N/A | D103: =VLOOKUP(F103,Sheet2!$A$2:$D$31,4,0) -> #N/A | E103: ='Customs Invoice'!E98 -> #N/A | F103: ='Customs Invoice'!F98 -> 0 | G103: ='Customs Invoice'!G98 -> 0 | H103: ='Customs Invoice'!H98 -> #N/A | I103: ='Customs Invoice'!I98 -> 0 | J103: ='Customs Invoice'!J98 -> 0 | K103: =L103/G103 -> #DIV/0! | L103: ='Customs Invoice'!P98 -> 0
...

Sheet US Customs Invoice LABOR
A1: PT. VERONIQUE INDONESIA
A2: Jl. Raya Purwonegoro Rt. 007/003, Purwonegoro, Banjarnegara, Jawa Tengah, Zip Code : 53472, INDONESIA
A3: INVOICE
A4: Seller: | B4: PT. VERONIQUE INDONESIA | I4: Invoice No. & Date : | J4: ='Customs Invoice'!K4 -> 0 | K4: ='Customs Invoice'!L4 -> 0
B5: Jl. Raya Purwonegoro Rt. 007/003 Purwonegoro Banjarnegara | I5: L/C No. & Date) :
B6: Jawa Tengah Zip Code : 53472 INDONESIA | I6: ='Customs Invoice'!I6 -> BILL TO : | J6: ='Customs Invoice'!K6 -> 0 | L6: NEW MERCHANDISE
B7: NPWP : 0315202689-529000 | J7: ='Customs Invoice'!K7 -> 0
B8: Tel : 62-286-598-8594 Fax : 62-286-598-8650 | J8: ='Customs Invoice'!K8 -> 0
A9: Consignee: | B9: ='Customs Invoice'!B9 -> 0 | J9: ='Customs Invoice'!K9 -> 0
B10: ='Customs Invoice'!B10 -> 0 | J10: ='Customs Invoice'!K10 -> 0
B11: ='Customs Invoice'!B11 -> 0 | J11: ='Customs Invoice'!K11 -> 0
B12: ='Customs Invoice'!B12 -> 0 | I12: "GSP eligible Article"
B13: ='Customs Invoice'!B13 -> 0 | I13: Other References: | J13: Country of Origin : | K13: INDONESIA
B14: ='Customs Invoice'!B14 -> 0 | J14: B/L No. :
A15: Departure Date: | B15: ='Customs Invoice'!B15 -> 0 | D15: COUNTRY OF ORIGIN: INDONESIA | J15: A/C No. :
A16: Vessel/Flight : | B16: ='Customs Invoice'!B16 -> 0 | D16: From : INDONESIA | J16: C/T No. : | K16: ='Customs Invoice'!L16 -> 1
A17: ='Customs Invoice'!A17 -> To : | I17: Terms of Payment: | J17: 30 Day's Net
B18: =CONCATENATE("PT Veronique to US_",LEFT('Customs Invoice'!K4,13)," Customs Invoice_New Merchandise") -> PT Veronique to US_ Customs Invoice_New Merchandise
B19: BOX 1 = GOLD JEWELRY
B20: No | C20: Manufacturer ID code | D20: USA HTS code | E20: Item description | F20: ID | G20: QTY (Pcs, pairs) | I20: N.Weight | J20: G.Weight | K20: Manufacturing Value
B21: ='Customs Invoice'!B21 -> 1 | C21: ='Customs Invoice'!C21 -> #N/A | D21: =VLOOKUP(F21,Sheet2!$A$2:$D$31,4,0) -> #N/A | E21: ='Customs Invoice'!E21 -> #N/A | F21: ='Customs Invoice'!F21 -> 0 | G21: ='Customs Invoice'!G21 -> 0 | H21: ='Customs Invoice'!H21 -> #N/A | I21: ='Customs Invoice'!I21 -> 0 | J21: ='Customs Invoice'!J21 -> #DIV/0! | K21: ='Customs Invoice'!M21 -> 0
D22: =VLOOKUP(F22,Sheet2!$A$2:$D$31,4,0) -> #N/A | F22: =F21&1 -> 01
B23: ='Customs Invoice'!B22 -> 2 | C23: ='Customs Invoice'!C22 -> #N/A | D23: =VLOOKUP(F23,Sheet2!$A$2:$D$31,4,0) -> #N/A | E23: ='Customs Invoice'!E22 -> #N/A | F23: ='Customs Invoice'!F22 -> 0 | G23: ='Customs Invoice'!G22 -> 0 | H23: ='Customs Invoice'!H22 -> #N/A | I23: ='Customs Invoice'!I22 -> 0 | J23: ='Customs Invoice'!J22 -> 0 | K23: ='Customs Invoice'!M22 -> 0
D24: =VLOOKUP(F24,Sheet2!$A$2:$D$31,4,0) -> #N/A | F24: =F23&1 -> 01
B25: ='Customs Invoice'!B23 -> 3 | C25: ='Customs Invoice'!C23 -> #N/A | D25: =VLOOKUP(F25,Sheet2!$A$2:$D$31,4,0) -> #N/A | E25: ='Customs Invoice'!E23 -> #N/A | F25: ='Customs Invoice'!F23 -> 0 | G25: ='Customs Invoice'!G23 -> 0 | H25: ='Customs Invoice'!H23 -> #N/A | I25: ='Customs Invoice'!I23 -> 0 | J25: ='Customs Invoice'!J23 -> 0 | K25: ='Customs Invoice'!M23 -> 0
D26: =VLOOKUP(F26,Sheet2!$A$2:$D$31,4,0) -> #N/A | F26: =F25&1 -> 01
B27: ='Customs Invoice'!B24 -> 4 | C27: ='Customs Invoice'!C24 -> #N/A | D27: =VLOOKUP(F27,Sheet2!$A$2:$D$31,4,0) -> #N/A | E27: ='Customs Invoice'!E24 -> #N/A | F27: ='Customs Invoice'!F24 -> 0 | G27: ='Customs Invoice'!G24 -> 0 | H27: ='Customs Invoice'!H24 -> #N/A | I27: ='Customs Invoice'!I24 -> 0 | J27: ='Customs Invoice'!J24 -> 0 | K27: ='Customs Invoice'!M24 -> 0
D28: =VLOOKUP(F28,Sheet2!$A$2:$D$31,4,0) -> #N/A | F28: =F27&1 -> 01
B29: ='Customs Invoice'!B25 -> 5 | C29: ='Customs Invoice'!C25 -> #N/A | D29: =VLOOKUP(F29,Sheet2!$A$2:$D$31,4,0) -> #N/A | E29: ='Customs Invoice'!E25 -> #N/A | F29: ='Customs Invoice'!F25 -> 0 | G29: ='Customs Invoice'!G25 -> 0 | H29: ='Customs Invoice'!H25 -> #N/A | I29: ='Customs Invoice'!I25 -> 0 | J29: ='Customs Invoice'!J25 -> 0 | K29: ='Customs Invoice'!M25 -> 0
D30: =VLOOKUP(F30,Sheet2!$A$2:$D$31,4,0) -> #N/A | F30: =F29&1 -> 01
B31: ='Customs Invoice'!B26 -> 6 | C31: ='Customs Invoice'!C26 -> #N/A | D31: =VLOOKUP(F31,Sheet2!$A$2:$D$31,4,0) -> #N/A | E31: ='Customs Invoice'!E26 -> #N/A | F31: ='Customs Invoice'!F26 -> 0 | G31: ='Customs Invoice'!G26 -> 0 | H31: ='Customs Invoice'!H26 -> #N/A | I31: ='Customs Invoice'!I26 -> 0 | J31: ='Customs Invoice'!J26 -> 0 | K31: ='Customs Invoice'!M26 -> 0
D32: =VLOOKUP(F32,Sheet2!$A$2:$D$31,4,0) -> #N/A | F32: =F31&1 -> 01
B33: ='Customs Invoice'!B27 -> 7 | C33: ='Customs Invoice'!C27 -> #N/A | D33: =VLOOKUP(F33,Sheet2!$A$2:$D$31,4,0) -> #N/A | E33: ='Customs Invoice'!E27 -> #N/A | F33: ='Customs Invoice'!F27 -> 0 | G33: ='Customs Invoice'!G27 -> 0 | H33: ='Customs Invoice'!H27 -> #N/A | I33: ='Customs Invoice'!I27 -> 0 | J33: ='Customs Invoice'!J27 -> 0 | K33: ='Customs Invoice'!M27 -> 0
D34: =VLOOKUP(F34,Sheet2!$A$2:$D$31,4,0) -> #N/A | F34: =F33&1 -> 01
B35: ='Customs Invoice'!B28 -> 8 | C35: ='Customs Invoice'!C28 -> #N/A | D35: =VLOOKUP(F35,Sheet2!$A$2:$D$31,4,0) -> #N/A | E35: ='Customs Invoice'!E28 -> #N/A | F35: ='Customs Invoice'!F28 -> 0 | G35: ='Customs Invoice'!G28 -> 0 | H35: ='Customs Invoice'!H28 -> #N/A | I35: ='Customs Invoice'!I28 -> 0 | J35: ='Customs Invoice'!J28 -> 0 | K35: ='Customs Invoice'!M28 -> 0
D36: =VLOOKUP(F36,Sheet2!$A$2:$D$31,4,0) -> #N/A | F36: =F35&1 -> 01
B37: ='Customs Invoice'!B29 -> 9 | C37: ='Customs Invoice'!C29 -> #N/A | D37: =VLOOKUP(F37,Sheet2!$A$2:$D$31,4,0) -> #N/A | E37: ='Customs Invoice'!E29 -> #N/A | F37: ='Customs Invoice'!F29 -> 0 | G37: ='Customs Invoice'!G29 -> 0 | H37: ='Customs Invoice'!H29 -> #N/A | I37: ='Customs Invoice'!I29 -> 0 | J37: ='Customs Invoice'!J29 -> 0 | K37: ='Customs Invoice'!M29 -> 0
D38: =VLOOKUP(F38,Sheet2!$A$2:$D$31,4,0) -> #N/A | F38: =F37&1 -> 01
B39: ='Customs Invoice'!B30 -> 10 | C39: ='Customs Invoice'!C30 -> #N/A | D39: =VLOOKUP(F39,Sheet2!$A$2:$D$31,4,0) -> #N/A | E39: ='Customs Invoice'!E30 -> #N/A | F39: ='Customs Invoice'!F30 -> - | G39: ='Customs Invoice'!G30 -> 0 | H39: ='Customs Invoice'!H30 -> #N/A | I39: ='Customs Invoice'!I30 -> 0 | J39: ='Customs Invoice'!J30 -> 0 | K39: ='Customs Invoice'!M30 -> 0
D40: =VLOOKUP(F40,Sheet2!$A$2:$D$31,4,0) -> #N/A | F40: =F39&1 -> -1
B41: TOTAL | G41: =SUM(G21:G40) -> 0 | I41: =SUM(I21:I40) -> 0 | J41: =SUM(J21:J40) -> #DIV/0! | K41: =SUM(K21:K40) -> 0
B43: BOX 2 = GOLD JEWELRY
B44: No | C44: Manufacturer ID code | D44: USA HTS code | E44: Item description | F44: ID | G44: QTY (Pcs, pairs) | I44: N.Weight | J44: G.Weight | K44: Unit value | L44: Total value
B45: ='Customs Invoice'!B45 -> 0 | C45: ='Customs Invoice'!C45 -> #N/A | D45: =VLOOKUP(F45,Sheet2!$A$2:$D$31,4,0) -> #N/A | E45: ='Customs Invoice'!E45 -> #N/A | F45: ='Customs Invoice'!F45 -> 0 | G45: ='Customs Invoice'!G45 -> 0 | H45: ='Customs Invoice'!H45 -> #N/A | I45: ='Customs Invoice'!I45 -> 0 | J45: ='Customs Invoice'!J45 -> 0 | K45: =L45/G45 -> #DIV/0! | L45: ='Customs Invoice'!P45 -> 0
D46: =VLOOKUP(F46,Sheet2!$A$2:$D$31,4,0) -> #N/A | F46: =F45&1 -> 01
B47: ='Customs Invoice'!B46 -> 0 | C47: ='Customs Invoice'!C46 -> #N/A | D47: =VLOOKUP(F47,Sheet2!$A$2:$D$31,4,0) -> #N/A | E47: ='Customs Invoice'!E46 -> #N/A | F47: ='Customs Invoice'!F46 -> 0 | G47: ='Customs Invoice'!G46 -> 0 | H47: ='Customs Invoice'!H46 -> #N/A | I47: ='Customs Invoice'!I46 -> 0 | J47: ='Customs Invoice'!J46 -> 0 | K47: =L47/G47 -> #DIV/0! | L47: ='Customs Invoice'!P46 -> 0
D48: =VLOOKUP(F48,Sheet2!$A$2:$D$31,4,0) -> #N/A | F48: =F47&1 -> 01
B49: ='Customs Invoice'!B47 -> 0 | C49: ='Customs Invoice'!C47 -> #N/A | D49: =VLOOKUP(F49,Sheet2!$A$2:$D$31,4,0) -> #N/A | E49: ='Customs Invoice'!E47 -> #N/A | F49: ='Customs Invoice'!F47 -> 0 | G49: ='Customs Invoice'!G47 -> 0 | H49: ='Customs Invoice'!H47 -> #N/A | I49: ='Customs Invoice'!I47 -> 0 | J49: ='Customs Invoice'!J47 -> 0 | K49: =L49/G49 -> #DIV/0! | L49: ='Customs Invoice'!P47 -> 0
D50: =VLOOKUP(F50,Sheet2!$A$2:$D$31,4,0) -> #N/A | F50: =F49&1 -> 01
B51: ='Customs Invoice'!B48 -> 0 | C51: ='Customs Invoice'!C48 -> #N/A | D51: =VLOOKUP(F51,Sheet2!$A$2:$D$31,4,0) -> #N/A | E51: ='Customs Invoice'!E48 -> #N/A | F51: ='Customs Invoice'!F48 -> 0 | G51: ='Customs Invoice'!G48 -> 0 | H51: ='Customs Invoice'!H48 -> #N/A | I51: ='Customs Invoice'!I48 -> 0 | J51: ='Customs Invoice'!J48 -> 0 | K51: =L51/G51 -> #DIV/0! | L51: ='Customs Invoice'!P48 -> 0
D52: =VLOOKUP(F52,Sheet2!$A$2:$D$31,4,0) -> #N/A | F52: =F51&1 -> 01
B53: ='Customs Invoice'!B49 -> 0 | C53: ='Customs Invoice'!C49 -> #N/A | D53: =VLOOKUP(F53,Sheet2!$A$2:$D$31,4,0) -> #N/A | E53: ='Customs Invoice'!E49 -> #N/A | F53: ='Customs Invoice'!F49 -> 0 | G53: ='Customs Invoice'!G49 -> 0 | H53: ='Customs Invoice'!H49 -> #N/A | I53: ='Customs Invoice'!I49 -> 0 | J53: ='Customs Invoice'!J49 -> 0 | K53: =L53/G53 -> #DIV/0! | L53: ='Customs Invoice'!P49 -> 0
D54: =VLOOKUP(F54,Sheet2!$A$2:$D$31,4,0) -> #N/A | F54: =F53&1 -> 01
B55: ='Customs Invoice'!B50 -> 0 | C55: ='Customs Invoice'!C50 -> #N/A | D55: =VLOOKUP(F55,Sheet2!$A$2:$D$31,4,0) -> #N/A | E55: ='Customs Invoice'!E50 -> #N/A | F55: ='Customs Invoice'!F50 -> 0 | G55: ='Customs Invoice'!G50 -> 0 | H55: ='Customs Invoice'!H50 -> #N/A | I55: ='Customs Invoice'!I50 -> 0 | J55: ='Customs Invoice'!J50 -> 0 | K55: =L55/G55 -> #DIV/0! | L55: ='Customs Invoice'!P50 -> 0
D56: =VLOOKUP(F56,Sheet2!$A$2:$D$31,4,0) -> #N/A | F56: =F55&1 -> 01
B57: ='Customs Invoice'!B51 -> 0 | C57: ='Customs Invoice'!C51 -> #N/A | D57: =VLOOKUP(F57,Sheet2!$A$2:$D$31,4,0) -> #N/A | E57: ='Customs Invoice'!E51 -> #N/A | F57: ='Customs Invoice'!F51 -> 0 | G57: ='Customs Invoice'!G51 -> 0 | H57: ='Customs Invoice'!H51 -> #N/A | I57: ='Customs Invoice'!I51 -> 0 | J57: ='Customs Invoice'!J51 -> 0 | K57: =L57/G57 -> #DIV/0! | L57: ='Customs Invoice'!P51 -> 0
D58: =VLOOKUP(F58,Sheet2!$A$2:$D$31,4,0) -> #N/A | F58: =F57&1 -> 01
B59: ='Customs Invoice'!B52 -> 0 | C59: ='Customs Invoice'!C52 -> #N/A | D59: =VLOOKUP(F59,Sheet2!$A$2:$D$31,4,0) -> #N/A | E59: ='Customs Invoice'!E52 -> #N/A | F59: ='Customs Invoice'!F52 -> 0 | G59: ='Customs Invoice'!G52 -> 0 | H59: ='Customs Invoice'!H52 -> #N/A | I59: ='Customs Invoice'!I52 -> 0 | J59: ='Customs Invoice'!J52 -> 0 | K59: =L59/G59 -> #DIV/0! | L59: ='Customs Invoice'!P52 -> 0
D60: =VLOOKUP(F60,Sheet2!$A$2:$D$31,4,0) -> #N/A | F60: =F59&1 -> 01
B61: ='Customs Invoice'!B53 -> 0 | C61: ='Customs Invoice'!C53 -> #N/A | D61: =VLOOKUP(F61,Sheet2!$A$2:$D$31,4,0) -> #N/A | E61: ='Customs Invoice'!E53 -> #N/A | F61: ='Customs Invoice'!F53 -> 0 | G61: ='Customs Invoice'!G53 -> 0 | H61: ='Customs Invoice'!H53 -> #N/A | I61: ='Customs Invoice'!I53 -> 0 | J61: ='Customs Invoice'!J53 -> 0 | K61: =L61/G61 -> #DIV/0! | L61: ='Customs Invoice'!P53 -> 0
D62: =VLOOKUP(F62,Sheet2!$A$2:$D$31,4,0) -> #N/A | F62: =F61&1 -> 01
B63: ='Customs Invoice'!B54 -> 0 | C63: ='Customs Invoice'!C54 -> #N/A | D63: =VLOOKUP(F63,Sheet2!$A$2:$D$31,4,0) -> #N/A | E63: ='Customs Invoice'!E54 -> #N/A | F63: ='Customs Invoice'!F54 -> 0 | G63: ='Customs Invoice'!G54 -> 0 | H63: ='Customs Invoice'!H54 -> #N/A | I63: ='Customs Invoice'!I54 -> 0 | J63: ='Customs Invoice'!J54 -> 0 | K63: =L63/G63 -> #DIV/0! | L63: ='Customs Invoice'!P54 -> 0
D64: =VLOOKUP(F64,Sheet2!$A$2:$D$31,4,0) -> #N/A | F64: =F63&1 -> 01
B65: TOTAL | G65: =SUM(G45:G64) -> 0 | I65: =SUM(I45:I64) -> 0 | J65: =SUM(J45:J64) -> 0 | L65: =SUM(L45:L64) -> 0
B67: BOX 3 = GOLD JEWELRY
B68: No | C68: Manufacturer ID code | D68: USA HTS code | E68: Item description | F68: ID | G68: QTY (Pcs, pairs) | I68: N.Weight | J68: G.Weight | K68: Unit value | L68: Total value
B69: ='Customs Invoice'!B69 -> 0 | C69: ='Customs Invoice'!C69 -> #N/A | D69: =VLOOKUP(F69,Sheet2!$A$2:$D$31,4,0) -> #N/A | E69: ='Customs Invoice'!E69 -> #N/A | F69: ='Customs Invoice'!F69 -> 0 | G69: ='Customs Invoice'!G69 -> 0 | H69: ='Customs Invoice'!H69 -> #N/A | I69: ='Customs Invoice'!I69 -> 0 | J69: ='Customs Invoice'!J69 -> 0 | K69: =L69/G69 -> #DIV/0! | L69: ='Customs Invoice'!P69 -> 0
D70: =VLOOKUP(F70,Sheet2!$A$2:$D$31,4,0) -> #N/A | F70: =F69&1 -> 01
B71: ='Customs Invoice'!B70 -> 0 | C71: ='Customs Invoice'!C70 -> #N/A | D71: =VLOOKUP(F71,Sheet2!$A$2:$D$31,4,0) -> #N/A | E71: ='Customs Invoice'!E70 -> #N/A | F71: ='Customs Invoice'!F70 -> 0 | G71: ='Customs Invoice'!G70 -> 0 | H71: ='Customs Invoice'!H70 -> #N/A | I71: ='Customs Invoice'!I70 -> 0 | J71: ='Customs Invoice'!J70 -> 0 | K71: =L71/G71 -> #DIV/0! | L71: ='Customs Invoice'!P70 -> 0
D72: =VLOOKUP(F72,Sheet2!$A$2:$D$31,4,0) -> #N/A | F72: =F71&1 -> 01
B73: ='Customs Invoice'!B71 -> 0 | C73: ='Customs Invoice'!C71 -> #N/A | D73: =VLOOKUP(F73,Sheet2!$A$2:$D$31,4,0) -> #N/A | E73: ='Customs Invoice'!E71 -> #N/A | F73: ='Customs Invoice'!F71 -> 0 | G73: ='Customs Invoice'!G71 -> 0 | H73: ='Customs Invoice'!H71 -> #N/A | I73: ='Customs Invoice'!I71 -> 0 | J73: ='Customs Invoice'!J71 -> 0 | K73: =L73/G73 -> #DIV/0! | L73: ='Customs Invoice'!P71 -> 0
D74: =VLOOKUP(F74,Sheet2!$A$2:$D$31,4,0) -> #N/A | F74: =F73&1 -> 01
B75: ='Customs Invoice'!B72 -> 0 | C75: ='Customs Invoice'!C72 -> #N/A | D75: =VLOOKUP(F75,Sheet2!$A$2:$D$31,4,0) -> #N/A | E75: ='Customs Invoice'!E72 -> #N/A | F75: ='Customs Invoice'!F72 -> 0 | G75: ='Customs Invoice'!G72 -> 0 | H75: ='Customs Invoice'!H72 -> #N/A | I75: ='Customs Invoice'!I72 -> 0 | J75: ='Customs Invoice'!J72 -> 0 | K75: =L75/G75 -> #DIV/0! | L75: ='Customs Invoice'!P72 -> 0
D76: =VLOOKUP(F76,Sheet2!$A$2:$D$31,4,0) -> #N/A | F76: =F75&1 -> 01
B77: ='Customs Invoice'!B73 -> 0 | C77: ='Customs Invoice'!C73 -> #N/A | D77: =VLOOKUP(F77,Sheet2!$A$2:$D$31,4,0) -> #N/A | E77: ='Customs Invoice'!E73 -> #N/A | F77: ='Customs Invoice'!F73 -> 0 | G77: ='Customs Invoice'!G73 -> 0 | H77: ='Customs Invoice'!H73 -> #N/A | I77: ='Customs Invoice'!I73 -> 0 | J77: ='Customs Invoice'!J73 -> 0 | K77: =L77/G77 -> #DIV/0! | L77: ='Customs Invoice'!P73 -> 0
D78: =VLOOKUP(F78,Sheet2!$A$2:$D$31,4,0) -> #N/A | F78: =F77&1 -> 01
B79: ='Customs Invoice'!B74 -> 0 | C79: ='Customs Invoice'!C74 -> #N/A | D79: =VLOOKUP(F79,Sheet2!$A$2:$D$31,4,0) -> #N/A | E79: ='Customs Invoice'!E74 -> #N/A | F79: ='Customs Invoice'!F74 -> 0 | G79: ='Customs Invoice'!G74 -> 0 | H79: ='Customs Invoice'!H74 -> #N/A | I79: ='Customs Invoice'!I74 -> 0 | J79: ='Customs Invoice'!J74 -> 0 | K79: =L79/G79 -> #DIV/0! | L79: ='Customs Invoice'!P74 -> 0
D80: =VLOOKUP(F80,Sheet2!$A$2:$D$31,4,0) -> #N/A | F80: =F79&1 -> 01
B81: ='Customs Invoice'!B75 -> 0 | C81: ='Customs Invoice'!C75 -> #N/A | D81: =VLOOKUP(F81,Sheet2!$A$2:$D$31,4,0) -> #N/A | E81: ='Customs Invoice'!E75 -> #N/A | F81: ='Customs Invoice'!F75 -> 0 | G81: ='Customs Invoice'!G75 -> 0 | H81: ='Customs Invoice'!H75 -> #N/A | I81: ='Customs Invoice'!I75 -> 0 | J81: ='Customs Invoice'!J75 -> 0 | K81: =L81/G81 -> #DIV/0! | L81: ='Customs Invoice'!P75 -> 0
D82: =VLOOKUP(F82,Sheet2!$A$2:$D$31,4,0) -> #N/A | F82: =F81&1 -> 01
B83: ='Customs Invoice'!B76 -> 0 | C83: ='Customs Invoice'!C76 -> #N/A | D83: =VLOOKUP(F83,Sheet2!$A$2:$D$31,4,0) -> #N/A | E83: ='Customs Invoice'!E76 -> #N/A | F83: ='Customs Invoice'!F76 -> 0 | G83: ='Customs Invoice'!G76 -> 0 | H83: ='Customs Invoice'!H76 -> #N/A | I83: ='Customs Invoice'!I76 -> 0 | J83: ='Customs Invoice'!J76 -> 0 | K83: =L83/G83 -> #DIV/0! | L83: ='Customs Invoice'!P76 -> 0
D84: =VLOOKUP(F84,Sheet2!$A$2:$D$31,4,0) -> #N/A | F84: =F83&1 -> 01
B85: ='Customs Invoice'!B77 -> 0 | C85: ='Customs Invoice'!C77 -> #N/A | D85: =VLOOKUP(F85,Sheet2!$A$2:$D$31,4,0) -> #N/A | E85: ='Customs Invoice'!E77 -> #N/A | F85: ='Customs Invoice'!F77 -> 0 | G85: ='Customs Invoice'!G77 -> 0 | H85: ='Customs Invoice'!H77 -> #N/A | I85: ='Customs Invoice'!I77 -> 0 | J85: ='Customs Invoice'!J77 -> 0 | K85: =L85/G85 -> #DIV/0! | L85: ='Customs Invoice'!P77 -> 0
D86: =VLOOKUP(F86,Sheet2!$A$2:$D$31,4,0) -> #N/A | F86: =F85&1 -> 01
B87: ='Customs Invoice'!B78 -> 0 | C87: ='Customs Invoice'!C78 -> #N/A | D87: =VLOOKUP(F87,Sheet2!$A$2:$D$31,4,0) -> #N/A | E87: ='Customs Invoice'!E78 -> #N/A | F87: ='Customs Invoice'!F78 -> 0 | G87: ='Customs Invoice'!G78 -> 0 | H87: ='Customs Invoice'!H78 -> #N/A | I87: ='Customs Invoice'!I78 -> 0 | J87: ='Customs Invoice'!J78 -> 0 | K87: =L87/G87 -> #DIV/0! | L87: ='Customs Invoice'!P78 -> 0
D88: =VLOOKUP(F88,Sheet2!$A$2:$D$31,4,0) -> #N/A | F88: =F87&1 -> 01
B89: TOTAL | G89: =SUM(G69:G88) -> 0 | I89: =SUM(I69:I88) -> 0 | J89: =SUM(J69:J88) -> 0 | L89: =SUM(L69:L88) -> 0
B91: BOX 4 = GOLD JEWELRY
B92: No | C92: Manufacturer ID code | D92: USA HTS code | E92: Item description | F92: ID | G92: QTY (Pcs, pairs) | I92: N.Weight | J92: G.Weight | K92: Unit value | L92: Total value
B93: ='Customs Invoice'!B93 -> 0 | C93: ='Customs Invoice'!C93 -> #N/A | D93: =VLOOKUP(F93,Sheet2!$A$2:$D$31,4,0) -> #N/A | E93: ='Customs Invoice'!E93 -> #N/A | F93: ='Customs Invoice'!F93 -> 0 | G93: ='Customs Invoice'!G93 -> 0 | H93: ='Customs Invoice'!H93 -> #N/A | I93: ='Customs Invoice'!I93 -> 0 | J93: ='Customs Invoice'!J93 -> 0 | K93: =L93/G93 -> #DIV/0! | L93: ='Customs Invoice'!P93 -> 0
D94: =VLOOKUP(F94,Sheet2!$A$2:$D$31,4,0) -> #N/A | F94: =F93&1 -> 01
B95: ='Customs Invoice'!B94 -> 0 | C95: ='Customs Invoice'!C94 -> #N/A | D95: =VLOOKUP(F95,Sheet2!$A$2:$D$31,4,0) -> #N/A | E95: ='Customs Invoice'!E94 -> #N/A | F95: ='Customs Invoice'!F94 -> 0 | G95: ='Customs Invoice'!G94 -> 0 | H95: ='Customs Invoice'!H94 -> #N/A | I95: ='Customs Invoice'!I94 -> 0 | J95: ='Customs Invoice'!J94 -> 0 | K95: =L95/G95 -> #DIV/0! | L95: ='Customs Invoice'!P94 -> 0
D96: =VLOOKUP(F96,Sheet2!$A$2:$D$31,4,0) -> #N/A | F96: =F95&1 -> 01
B97: ='Customs Invoice'!B95 -> 0 | C97: ='Customs Invoice'!C95 -> #N/A | D97: =VLOOKUP(F97,Sheet2!$A$2:$D$31,4,0) -> #N/A | E97: ='Customs Invoice'!E95 -> #N/A | F97: ='Customs Invoice'!F95 -> 0 | G97: ='Customs Invoice'!G95 -> 0 | H97: ='Customs Invoice'!H95 -> #N/A | I97: ='Customs Invoice'!I95 -> 0 | J97: ='Customs Invoice'!J95 -> 0 | K97: =L97/G97 -> #DIV/0! | L97: ='Customs Invoice'!P95 -> 0
D98: =VLOOKUP(F98,Sheet2!$A$2:$D$31,4,0) -> #N/A | F98: =F97&1 -> 01
B99: ='Customs Invoice'!B96 -> 0 | C99: ='Customs Invoice'!C96 -> #N/A | D99: =VLOOKUP(F99,Sheet2!$A$2:$D$31,4,0) -> #N/A | E99: ='Customs Invoice'!E96 -> #N/A | F99: ='Customs Invoice'!F96 -> 0 | G99: ='Customs Invoice'!G96 -> 0 | H99: ='Customs Invoice'!H96 -> #N/A | I99: ='Customs Invoice'!I96 -> 0 | J99: ='Customs Invoice'!J96 -> 0 | K99: =L99/G99 -> #DIV/0! | L99: ='Customs Invoice'!P96 -> 0
D100: =VLOOKUP(F100,Sheet2!$A$2:$D$31,4,0) -> #N/A | F100: =F99&1 -> 01
B101: ='Customs Invoice'!B97 -> 0 | C101: ='Customs Invoice'!C97 -> #N/A | D101: =VLOOKUP(F101,Sheet2!$A$2:$D$31,4,0) -> #N/A | E101: ='Customs Invoice'!E97 -> #N/A | F101: ='Customs Invoice'!F97 -> 0 | G101: ='Customs Invoice'!G97 -> 0 | H101: ='Customs Invoice'!H97 -> #N/A | I101: ='Customs Invoice'!I97 -> 0 | J101: ='Customs Invoice'!J97 -> 0 | K101: =L101/G101 -> #DIV/0! | L101: ='Customs Invoice'!P97 -> 0
D102: =VLOOKUP(F102,Sheet2!$A$2:$D$31,4,0) -> #N/A | F102: =F101&1 -> 01
B103: ='Customs Invoice'!B98 -> 0 | C103: ='Customs Invoice'!C98 -> #N/A | D103: =VLOOKUP(F103,Sheet2!$A$2:$D$31,4,0) -> #N/A | E103: ='Customs Invoice'!E98 -> #N/A | F103: ='Customs Invoice'!F98 -> 0 | G103: ='Customs Invoice'!G98 -> 0 | H103: ='Customs Invoice'!H98 -> #N/A | I103: ='Customs Invoice'!I98 -> 0 | J103: ='Customs Invoice'!J98 -> 0 | K103: =L103/G103 -> #DIV/0! | L103: ='Customs Invoice'!P98 -> 0
...

Sheet Customs Invoice NON MAKLON
A1: PT. VERONIQUE INDONESIA
A2: Jl. Raya Purwonegoro Rt. 007/003, Purwonegoro, Banjarnegara, Jawa Tengah, Zip Code : 53472, INDONESIA
A3: INVOICE
A4: Seller: | B4: PT. VERONIQUE INDONESIA | I4: Invoice No. & Date : | K4: ='Customs Invoice'!K4 -> 0 | L4: ='Customs Invoice'!L4 -> 0
B5: Jl. Raya Purwonegoro Rt. 007/003 Purwonegoro Banjarnegara | I5: L/C No. & Date) :
B6: Jawa Tengah Zip Code : 53472 INDONESIA | I6: BILL TO : | K6: ='Customs Invoice'!K6 -> 0
B7: NPWP : 0315202689-529000 | K7: ='Customs Invoice'!K7 -> 0
B8: Tel : 62-286-598-8594 Fax : 62-286-598-8650 | K8: ='Customs Invoice'!K8 -> 0
A9: Consignee: | B9: ='Customs Invoice'!B9 -> 0 | K9: ='Customs Invoice'!K9 -> 0
B10: ='Customs Invoice'!B10 -> 0 | K10: NEW MERCHANDISE
B11: ='Customs Invoice'!B11 -> 0
B12: ='Customs Invoice'!B12 -> 0 | I12: "GSP eligible Article"
B13: ='Customs Invoice'!B13 -> 0 | I13: Other References: | K13: Country of Origin : | L13: INDONESIA
B14: ='Customs Invoice'!B14 -> 0 | K14: B/L No. :
A15: Departure Date: | B15: ='Customs Invoice'!B15 -> 0 | D15: COUNTRY OF ORIGIN: INDONESIA | K15: A/C No. :
A16: Vessel/Flight : | B16: ='Customs Invoice'!B16 -> 0 | D16: From : INDONESIA | K16: C/T No. : | L16: 1
A17: To : | B17: ='Customs Invoice'!B17 -> 0 | I17: Terms of Payment: | K17: 30 Day's Net
B19: BOX 1 = GOLD JEWELRY
B20: No | C20: ID Code | D20: USA harmonized code | E20: Item | F20: ID | G20: Qty/Pcs,Pair | I20: N.Weight | J20: G.Weight | K20: Unit Value | L20: Total Value | M20: Manufacturing Cost (nilai maklon) | N20: Dia Value | O20: Gold Value | P20: Manufacturing + Dia + Gold for US | R20: Total Value | S20: N.Weight
B21: 1 | C21: =CONCATENATE("FGG-",MID(E21,1,3),MID(E21,10,1),"-ASU") -> #N/A | D21: ='Customs Invoice'!D21 -> #N/A | E21: ='Customs Invoice'!E21 -> #N/A | F21: ='Customs Invoice'!F21 -> 0 | G21: ='Customs Invoice'!G21 -> 0 | H21: ='Customs Invoice'!H21 -> #N/A | I21: ='Customs Invoice'!I21 -> 0 | J21: ='Customs Invoice'!J21 -> #DIV/0! | K21: =L21/G21 -> #DIV/0! | L21: ='Customs Invoice'!L21 -> 0 | R21: =L21 -> 0 | S21: =I21 -> 0
B22: 2 | C22: =CONCATENATE("FGG-",MID(E22,1,3),MID(E22,10,1),"-ASU") -> #N/A | D22: ='Customs Invoice'!D22 -> #N/A | E22: ='Customs Invoice'!E22 -> #N/A | F22: ='Customs Invoice'!F22 -> 0 | G22: ='Customs Invoice'!G22 -> 0 | H22: ='Customs Invoice'!H22 -> #N/A | I22: ='Customs Invoice'!I22 -> 0 | J22: ='Customs Invoice'!J22 -> 0 | K22: =L22/G22 -> #DIV/0! | L22: ='Customs Invoice'!L22 -> 0 | R22: =L22 -> 0 | S22: =I22 -> 0
B23: 3 | C23: =CONCATENATE("FGG-",MID(E23,1,3),MID(E23,10,1),"-ASU") -> #N/A | D23: ='Customs Invoice'!D23 -> #N/A | E23: ='Customs Invoice'!E23 -> #N/A | F23: ='Customs Invoice'!F23 -> 0 | G23: ='Customs Invoice'!G23 -> 0 | H23: ='Customs Invoice'!H23 -> #N/A | I23: ='Customs Invoice'!I23 -> 0 | J23: ='Customs Invoice'!J23 -> 0 | K23: =L23/G23 -> #DIV/0! | L23: ='Customs Invoice'!L23 -> 0 | R23: =L23 -> 0 | S23: =I23 -> 0
B24: 4 | C24: =CONCATENATE("FGG-",MID(E24,1,3),MID(E24,10,1),"-ASU") -> #N/A | D24: ='Customs Invoice'!D24 -> #N/A | E24: ='Customs Invoice'!E24 -> #N/A | F24: ='Customs Invoice'!F24 -> 0 | G24: ='Customs Invoice'!G24 -> 0 | H24: ='Customs Invoice'!H24 -> #N/A | I24: ='Customs Invoice'!I24 -> 0 | J24: ='Customs Invoice'!J24 -> 0 | K24: =L24/G24 -> #DIV/0! | L24: ='Customs Invoice'!L24 -> 0 | R24: =L24 -> 0 | S24: =I24 -> 0
B25: 5 | C25: =CONCATENATE("FGG-",MID(E25,1,3),MID(E25,10,1),"-ASU") -> #N/A | D25: ='Customs Invoice'!D25 -> #N/A | E25: ='Customs Invoice'!E25 -> #N/A | F25: ='Customs Invoice'!F25 -> 0 | G25: ='Customs Invoice'!G25 -> 0 | H25: ='Customs Invoice'!H25 -> #N/A | I25: ='Customs Invoice'!I25 -> 0 | J25: ='Customs Invoice'!J25 -> 0 | K25: =L25/G25 -> #DIV/0! | L25: ='Customs Invoice'!L25 -> 0 | R25: =L25 -> 0 | S25: =I25 -> 0
B26: 6 | C26: =CONCATENATE("FGG-",MID(E26,1,3),MID(E26,10,1),"-ASU") -> #N/A | D26: ='Customs Invoice'!D26 -> #N/A | E26: ='Customs Invoice'!E26 -> #N/A | F26: ='Customs Invoice'!F26 -> 0 | G26: ='Customs Invoice'!G26 -> 0 | H26: ='Customs Invoice'!H26 -> #N/A | I26: ='Customs Invoice'!I26 -> 0 | J26: ='Customs Invoice'!J26 -> 0 | K26: =L26/G26 -> #DIV/0! | L26: ='Customs Invoice'!L26 -> 0 | R26: =L26 -> 0 | S26: =I26 -> 0
B27: 7 | C27: =CONCATENATE("FGG-",MID(E27,1,3),MID(E27,10,1),"-ASU") -> #N/A | D27: ='Customs Invoice'!D27 -> #N/A | E27: ='Customs Invoice'!E27 -> #N/A | F27: ='Customs Invoice'!F27 -> 0 | G27: ='Customs Invoice'!G27 -> 0 | H27: ='Customs Invoice'!H27 -> #N/A | I27: ='Customs Invoice'!I27 -> 0 | J27: ='Customs Invoice'!J27 -> 0 | K27: =L27/G27 -> #DIV/0! | L27: ='Customs Invoice'!L27 -> 0 | R27: =L27 -> 0 | S27: =I27 -> 0
B28: 8 | C28: =CONCATENATE("FGG-",MID(E28,1,3),MID(E28,10,1),"-ASU") -> #N/A | D28: ='Customs Invoice'!D28 -> #N/A | E28: ='Customs Invoice'!E28 -> #N/A | F28: ='Customs Invoice'!F28 -> 0 | G28: ='Customs Invoice'!G28 -> 0 | H28: ='Customs Invoice'!H28 -> #N/A | I28: ='Customs Invoice'!I28 -> 0 | J28: ='Customs Invoice'!J28 -> 0 | K28: =L28/G28 -> #DIV/0! | L28: ='Customs Invoice'!L28 -> 0 | R28: =L28 -> 0 | S28: =I28 -> 0
B29: 9 | C29: =CONCATENATE("FGG-",MID(E29,1,3),MID(E29,10,1),"-ASU") -> #N/A | D29: ='Customs Invoice'!D29 -> #N/A | E29: ='Customs Invoice'!E29 -> #N/A | F29: ='Customs Invoice'!F29 -> 0 | G29: ='Customs Invoice'!G29 -> 0 | H29: ='Customs Invoice'!H29 -> #N/A | I29: ='Customs Invoice'!I29 -> 0 | J29: ='Customs Invoice'!J29 -> 0 | K29: =L29/G29 -> #DIV/0! | L29: ='Customs Invoice'!L29 -> 0 | R29: =L29 -> 0 | S29: =I29 -> 0
B30: 10 | C30: =CONCATENATE("FGG-",MID(E30,1,3),MID(E30,10,1),"-ASU") -> #N/A | D30: ='Customs Invoice'!D30 -> #N/A | E30: ='Customs Invoice'!E30 -> #N/A | F30: ='Customs Invoice'!F30 -> - | G30: ='Customs Invoice'!G30 -> 0 | H30: ='Customs Invoice'!H30 -> #N/A | I30: ='Customs Invoice'!I30 -> 0 | J30: ='Customs Invoice'!J30 -> 0 | K30: =L30/G30 -> #DIV/0! | L30: ='Customs Invoice'!L30 -> 0 | R30: =L30 -> 0 | S30: =I30 -> 0
B31: 11 | C31: =CONCATENATE("FGG-",MID(E31,1,3),MID(E31,10,1),"-ASU") -> #N/A | D31: ='Customs Invoice'!D31 -> #N/A | E31: ='Customs Invoice'!E31 -> #N/A | F31: ='Customs Invoice'!F31 -> - | G31: ='Customs Invoice'!G31 -> 0 | H31: ='Customs Invoice'!H31 -> #N/A | I31: ='Customs Invoice'!I31 -> 0 | J31: ='Customs Invoice'!J31 -> 0 | K31: =L31/G31 -> #DIV/0! | L31: ='Customs Invoice'!L31 -> 0 | R31: =L31 -> 0 | S31: =I31 -> 0
B32: 12 | C32: =CONCATENATE("FGG-",MID(E32,1,3),MID(E32,10,1),"-ASU") -> #N/A | D32: ='Customs Invoice'!D32 -> #N/A | E32: ='Customs Invoice'!E32 -> #N/A | F32: ='Customs Invoice'!F32 -> - | G32: ='Customs Invoice'!G32 -> 0 | H32: ='Customs Invoice'!H32 -> #N/A | I32: ='Customs Invoice'!I32 -> 0 | J32: ='Customs Invoice'!J32 -> 0 | K32: =L32/G32 -> #DIV/0! | L32: ='Customs Invoice'!L32 -> 0 | R32: =L32 -> 0 | S32: =I32 -> 0
... B40: 20 | C40: =CONCATENATE("FGG-",MID(E40,1,3),MID(E40,10,1),"-ASU") -> #N/A | D40: ='Customs Invoice'!D40 -> #N/A | E40: ='Customs Invoice'!E40 -> #N/A | F40: ='Customs Invoice'!F40 -> - | G40: ='Customs Invoice'!G40 -> 0 | H40: ='Customs Invoice'!H40 -> #N/A | I40: ='Customs Invoice'!I40 -> 0 | J40: ='Customs Invoice'!J40 -> 0 | K40: =L40/G40 -> #DIV/0! | L40: ='Customs Invoice'!L40 -> 0 | R40: =L40 -> 0 | S40: =I40 -> 0
E41: TOTAL | G41: =SUM(G21:G40) -> 0 | I41: =SUM(I21:I40) -> 0 | J41: =SUM(J21:J40) -> #DIV/0! | L41: =SUM(L21:L40) -> 0 | M41: =SUM(M21:M40) -> 0 | N41: =SUM(N21:N40) -> 0 | O41: =SUM(O21:O40) -> 0 | P41: =SUM(P21:P40) -> 0
B43: BOX 2 = GOLD JEWELRY
B44: No | C44: ID Code | D44: USA harmonized code | E44: Item | F44: ID | G44: Qty/Pcs,Pair | I44: N.Weight | J44: G.Weight | K44: Unit Value (material & manufacturing cost) | L44: Total Value (material & manufacturing cost) | M44: Manufacturing Cost (nilai maklon) | P44: Manufacturing + Dia + Gold for US
C45: =CONCATENATE("MFGG","-",MID(E45,1,3),MID(E45,10,1),"-","IDD") -> #N/A | D45: =VLOOKUP(F45,Sheet2!$A$2:$D$31,4,0) -> #N/A | E45: =VLOOKUP(F45,Sheet2!$A$2:$D$31,2,0) -> #N/A | H45: =VLOOKUP(F45,Sheet2!$A$2:$D$31,3,0) -> #N/A | K45: =L45/G45 -> #DIV/0!
C46: =CONCATENATE("MFGG","-",MID(E46,1,3),MID(E46,10,1),"-","IDD") -> #N/A | D46: =VLOOKUP(F46,Sheet2!$A$2:$D$31,4,0) -> #N/A | E46: =VLOOKUP(F46,Sheet2!$A$2:$D$31,2,0) -> #N/A | H46: =VLOOKUP(F46,Sheet2!$A$2:$D$31,3,0) -> #N/A | K46: =L46/G46 -> #DIV/0!
C47: =CONCATENATE("MFGG","-",MID(E47,1,3),MID(E47,10,1),"-","IDD") -> #N/A | D47: =VLOOKUP(F47,Sheet2!$A$2:$D$31,4,0) -> #N/A | E47: =VLOOKUP(F47,Sheet2!$A$2:$D$31,2,0) -> #N/A | H47: =VLOOKUP(F47,Sheet2!$A$2:$D$31,3,0) -> #N/A | K47: =L47/G47 -> #DIV/0!
C48: =CONCATENATE("MFGG","-",MID(E48,1,3),MID(E48,10,1),"-","IDD") -> #N/A | D48: =VLOOKUP(F48,Sheet2!$A$2:$D$31,4,0) -> #N/A | E48: =VLOOKUP(F48,Sheet2!$A$2:$D$31,2,0) -> #N/A | H48: =VLOOKUP(F48,Sheet2!$A$2:$D$31,3,0) -> #N/A | K48: =L48/G48 -> #DIV/0!
C49: =CONCATENATE("MFGG","-",MID(E49,1,3),MID(E49,10,1),"-","IDD") -> #N/A | D49: =VLOOKUP(F49,Sheet2!$A$2:$D$31,4,0) -> #N/A | E49: =VLOOKUP(F49,Sheet2!$A$2:$D$31,2,0) -> #N/A | H49: =VLOOKUP(F49,Sheet2!$A$2:$D$31,3,0) -> #N/A | K49: =L49/G49 -> #DIV/0!
C50: =CONCATENATE("MFGG","-",MID(E50,1,3),MID(E50,10,1),"-","IDD") -> #N/A | D50: =VLOOKUP(F50,Sheet2!$A$2:$D$31,4,0) -> #N/A | E50: =VLOOKUP(F50,Sheet2!$A$2:$D$31,2,0) -> #N/A | H50: =VLOOKUP(F50,Sheet2!$A$2:$D$31,3,0) -> #N/A | K50: =L50/G50 -> #DIV/0!
C51: =CONCATENATE("MFGG","-",MID(E51,1,3),MID(E51,10,1),"-","IDD") -> #N/A | D51: =VLOOKUP(F51,Sheet2!$A$2:$D$31,4,0) -> #N/A | E51: =VLOOKUP(F51,Sheet2!$A$2:$D$31,2,0) -> #N/A | H51: =VLOOKUP(F51,Sheet2!$A$2:$D$31,3,0) -> #N/A | K51: =L51/G51 -> #DIV/0!
C52: =CONCATENATE("MFGG","-",MID(E52,1,3),MID(E52,10,1),"-","IDD") -> #N/A | D52: =VLOOKUP(F52,Sheet2!$A$2:$D$31,4,0) -> #N/A | E52: =VLOOKUP(F52,Sheet2!$A$2:$D$31,2,0) -> #N/A | H52: =VLOOKUP(F52,Sheet2!$A$2:$D$31,3,0) -> #N/A | K52: =L52/G52 -> #DIV/0!
C53: =CONCATENATE("MFGG","-",MID(E53,1,3),MID(E53,10,1),"-","IDD") -> #N/A | D53: =VLOOKUP(F53,Sheet2!$A$2:$D$31,4,0) -> #N/A | E53: =VLOOKUP(F53,Sheet2!$A$2:$D$31,2,0) -> #N/A | H53: =VLOOKUP(F53,Sheet2!$A$2:$D$31,3,0) -> #N/A | K53: =L53/G53 -> #DIV/0!
C54: =CONCATENATE("MFGG","-",MID(E54,1,3),MID(E54,10,1),"-","IDD") -> #N/A | D54: =VLOOKUP(F54,Sheet2!$A$2:$D$31,4,0) -> #N/A | E54: =VLOOKUP(F54,Sheet2!$A$2:$D$31,2,0) -> #N/A | H54: =VLOOKUP(F54,Sheet2!$A$2:$D$31,3,0) -> #N/A | K54: =L54/G54 -> #DIV/0!
C55: =CONCATENATE("MFGG","-",MID(E55,1,3),MID(E55,10,1),"-","IDD") -> #N/A | D55: =VLOOKUP(F55,Sheet2!$A$2:$D$31,4,0) -> #N/A | E55: =VLOOKUP(F55,Sheet2!$A$2:$D$31,2,0) -> #N/A | H55: =VLOOKUP(F55,Sheet2!$A$2:$D$31,3,0) -> #N/A | K55: =L55/G55 -> #DIV/0!
C56: =CONCATENATE("MFGG","-",MID(E56,1,3),MID(E56,10,1),"-","IDD") -> #N/A | D56: =VLOOKUP(F56,Sheet2!$A$2:$D$31,4,0) -> #N/A | E56: =VLOOKUP(F56,Sheet2!$A$2:$D$31,2,0) -> #N/A | H56: =VLOOKUP(F56,Sheet2!$A$2:$D$31,3,0) -> #N/A | K56: =L56/G56 -> #DIV/0!
... C64: =CONCATENATE("MFGG","-",MID(E64,1,3),MID(E64,10,1),"-","IDD") -> #N/A | D64: =VLOOKUP(F64,Sheet2!$A$2:$D$31,4,0) -> #N/A | E64: =VLOOKUP(F64,Sheet2!$A$2:$D$31,2,0) -> #N/A | H64: =VLOOKUP(F64,Sheet2!$A$2:$D$31,3,0) -> #N/A | K64: =L64/G64 -> #DIV/0!
E65: TOTAL | G65: =SUM(G45:G64) -> 0 | I65: =SUM(I45:I64) -> 0 | J65: =SUM(J45:J64) -> 0 | L65: =SUM(L45:L64) -> 0 | M65: =SUM(M45:M64) -> 0 | P65: =SUM(P45:P64) -> 0
B67: BOX 3 = GOLD JEWELRY
B68: No | C68: ID Code | D68: USA harmonized code | E68: Item | F68: ID | G68: Qty/Pcs,Pair | I68: N.Weight | J68: G.Weight | K68: Unit Value (material & manufacturing cost) | L68: Total Value (material & manufacturing cost) | M68: Manufacturing Cost (nilai maklon) | P68: Manufacturing + Dia + Gold for US
C69: =CONCATENATE("MFGG","-",MID(E69,1,3),MID(E69,10,1),"-","IDD") -> #N/A | D69: =VLOOKUP(F69,Sheet2!$A$2:$D$31,4,0) -> #N/A | E69: =VLOOKUP(F69,Sheet2!$A$2:$D$31,2,0) -> #N/A | H69: =VLOOKUP(F69,Sheet2!$A$2:$D$31,3,0) -> #N/A | K69: =L69/G69 -> #DIV/0!
C70: =CONCATENATE("MFGG","-",MID(E70,1,3),MID(E70,10,1),"-","IDD") -> #N/A | D70: =VLOOKUP(F70,Sheet2!$A$2:$D$31,4,0) -> #N/A | E70: =VLOOKUP(F70,Sheet2!$A$2:$D$31,2,0) -> #N/A | H70: =VLOOKUP(F70,Sheet2!$A$2:$D$31,3,0) -> #N/A | K70: =L70/G70 -> #DIV/0!
C71: =CONCATENATE("MFGG","-",MID(E71,1,3),MID(E71,10,1),"-","IDD") -> #N/A | D71: =VLOOKUP(F71,Sheet2!$A$2:$D$31,4,0) -> #N/A | E71: =VLOOKUP(F71,Sheet2!$A$2:$D$31,2,0) -> #N/A | H71: =VLOOKUP(F71,Sheet2!$A$2:$D$31,3,0) -> #N/A | K71: =L71/G71 -> #DIV/0!
C72: =CONCATENATE("MFGG","-",MID(E72,1,3),MID(E72,10,1),"-","IDD") -> #N/A | D72: =VLOOKUP(F72,Sheet2!$A$2:$D$31,4,0) -> #N/A | E72: =VLOOKUP(F72,Sheet2!$A$2:$D$31,2,0) -> #N/A | H72: =VLOOKUP(F72,Sheet2!$A$2:$D$31,3,0) -> #N/A | K72: =L72/G72 -> #DIV/0!
C73: =CONCATENATE("MFGG","-",MID(E73,1,3),MID(E73,10,1),"-","IDD") -> #N/A | D73: =VLOOKUP(F73,Sheet2!$A$2:$D$31,4,0) -> #N/A | E73: =VLOOKUP(F73,Sheet2!$A$2:$D$31,2,0) -> #N/A | H73: =VLOOKUP(F73,Sheet2!$A$2:$D$31,3,0) -> #N/A | K73: =L73/G73 -> #DIV/0!
C74: =CONCATENATE("MFGG","-",MID(E74,1,3),MID(E74,10,1),"-","IDD") -> #N/A | D74: =VLOOKUP(F74,Sheet2!$A$2:$D$31,4,0) -> #N/A | E74: =VLOOKUP(F74,Sheet2!$A$2:$D$31,2,0) -> #N/A | H74: =VLOOKUP(F74,Sheet2!$A$2:$D$31,3,0) -> #N/A | K74: =L74/G74 -> #DIV/0!
C75: =CONCATENATE("MFGG","-",MID(E75,1,3),MID(E75,10,1),"-","IDD") -> #N/A | D75: =VLOOKUP(F75,Sheet2!$A$2:$D$31,4,0) -> #N/A | E75: =VLOOKUP(F75,Sheet2!$A$2:$D$31,2,0) -> #N/A | H75: =VLOOKUP(F75,Sheet2!$A$2:$D$31,3,0) -> #N/A | K75: =L75/G75 -> #DIV/0!
C76: =CONCATENATE("MFGG","-",MID(E76,1,3),MID(E76,10,1),"-","IDD") -> #N/A | D76: =VLOOKUP(F76,Sheet2!$A$2:$D$31,4,0) -> #N/A | E76: =VLOOKUP(F76,Sheet2!$A$2:$D$31,2,0) -> #N/A | H76: =VLOOKUP(F76,Sheet2!$A$2:$D$31,3,0) -> #N/A | K76: =L76/G76 -> #DIV/0!
C77: =CONCATENATE("MFGG","-",MID(E77,1,3),MID(E77,10,1),"-","IDD") -> #N/A | D77: =VLOOKUP(F77,Sheet2!$A$2:$D$31,4,0) -> #N/A | E77: =VLOOKUP(F77,Sheet2!$A$2:$D$31,2,0) -> #N/A | H77: =VLOOKUP(F77,Sheet2!$A$2:$D$31,3,0) -> #N/A | K77: =L77/G77 -> #DIV/0!
C78: =CONCATENATE("MFGG","-",MID(E78,1,3),MID(E78,10,1),"-","IDD") -> #N/A | D78: =VLOOKUP(F78,Sheet2!$A$2:$D$31,4,0) -> #N/A | E78: =VLOOKUP(F78,Sheet2!$A$2:$D$31,2,0) -> #N/A | H78: =VLOOKUP(F78,Sheet2!$A$2:$D$31,3,0) -> #N/A | K78: =L78/G78 -> #DIV/0!
C79: =CONCATENATE("MFGG","-",MID(E79,1,3),MID(E79,10,1),"-","IDD") -> #N/A | D79: =VLOOKUP(F79,Sheet2!$A$2:$D$31,4,0) -> #N/A | E79: =VLOOKUP(F79,Sheet2!$A$2:$D$31,2,0) -> #N/A | H79: =VLOOKUP(F79,Sheet2!$A$2:$D$31,3,0) -> #N/A | K79: =L79/G79 -> #DIV/0!
C80: =CONCATENATE("MFGG","-",MID(E80,1,3),MID(E80,10,1),"-","IDD") -> #N/A | D80: =VLOOKUP(F80,Sheet2!$A$2:$D$31,4,0) -> #N/A | E80: =VLOOKUP(F80,Sheet2!$A$2:$D$31,2,0) -> #N/A | H80: =VLOOKUP(F80,Sheet2!$A$2:$D$31,3,0) -> #N/A | K80: =L80/G80 -> #DIV/0!
... C88: =CONCATENATE("MFGG","-",MID(E88,1,3),MID(E88,10,1),"-","IDD") -> #N/A | D88: =VLOOKUP(F88,Sheet2!$A$2:$D$31,4,0) -> #N/A | E88: =VLOOKUP(F88,Sheet2!$A$2:$D$31,2,0) -> #N/A | H88: =VLOOKUP(F88,Sheet2!$A$2:$D$31,3,0) -> #N/A | K88: =L88/G88 -> #DIV/0!
E89: TOTAL | G89: =SUM(G69:G88) -> 0 | I89: =SUM(I69:I88) -> 0 | J89: =SUM(J69:J88) -> 0 | L89: =SUM(L69:L88) -> 0 | M89: =SUM(M69:M88) -> 0 | P89: =SUM(P69:P88) -> 0
B91: BOX 4 = GOLD JEWELRY
B92: No | C92: ID Code | D92: USA harmonized code | E92: Item | F92: ID | G92: Qty/Pcs,Pair | I92: N.Weight | J92: G.Weight | K92: Unit Value (material & manufacturing cost) | L92: Total Value (material & manufacturing cost) | M92: Manufacturing Cost (nilai maklon) | P92: Manufacturing + Dia + Gold for US
C93: =CONCATENATE("MFGG","-",MID(E93,1,3),MID(E93,10,1),"-","IDD") -> #N/A | D93: =VLOOKUP(F93,Sheet2!$A$2:$D$31,4,0) -> #N/A | E93: =VLOOKUP(F93,Sheet2!$A$2:$D$31,2,0) -> #N/A | H93: =VLOOKUP(F93,Sheet2!$A$2:$D$31,3,0) -> #N/A | K93: =L93/G93 -> #DIV/0!
C94: =CONCATENATE("MFGG","-",MID(E94,1,3),MID(E94,10,1),"-","IDD") -> #N/A | D94: =VLOOKUP(F94,Sheet2!$A$2:$D$31,4,0) -> #N/A | E94: =VLOOKUP(F94,Sheet2!$A$2:$D$31,2,0) -> #N/A | H94: =VLOOKUP(F94,Sheet2!$A$2:$D$31,3,0) -> #N/A | K94: =L94/G94 -> #DIV/0!
C95: =CONCATENATE("MFGG","-",MID(E95,1,3),MID(E95,10,1),"-","IDD") -> #N/A | D95: =VLOOKUP(F95,Sheet2!$A$2:$D$31,4,0) -> #N/A | E95: =VLOOKUP(F95,Sheet2!$A$2:$D$31,2,0) -> #N/A | H95: =VLOOKUP(F95,Sheet2!$A$2:$D$31,3,0) -> #N/A | K95: =L95/G95 -> #DIV/0!
C96: =CONCATENATE("MFGG","-",MID(E96,1,3),MID(E96,10,1),"-","IDD") -> #N/A | D96: =VLOOKUP(F96,Sheet2!$A$2:$D$31,4,0) -> #N/A | E96: =VLOOKUP(F96,Sheet2!$A$2:$D$31,2,0) -> #N/A | H96: =VLOOKUP(F96,Sheet2!$A$2:$D$31,3,0) -> #N/A | K96: =L96/G96 -> #DIV/0!
C97: =CONCATENATE("MFGG","-",MID(E97,1,3),MID(E97,10,1),"-","IDD") -> #N/A | D97: =VLOOKUP(F97,Sheet2!$A$2:$D$31,4,0) -> #N/A | E97: =VLOOKUP(F97,Sheet2!$A$2:$D$31,2,0) -> #N/A | H97: =VLOOKUP(F97,Sheet2!$A$2:$D$31,3,0) -> #N/A | K97: =L97/G97 -> #DIV/0!
C98: =CONCATENATE("MFGG","-",MID(E98,1,3),MID(E98,10,1),"-","IDD") -> #N/A | D98: =VLOOKUP(F98,Sheet2!$A$2:$D$31,4,0) -> #N/A | E98: =VLOOKUP(F98,Sheet2!$A$2:$D$31,2,0) -> #N/A | H98: =VLOOKUP(F98,Sheet2!$A$2:$D$31,3,0) -> #N/A | K98: =L98/G98 -> #DIV/0!
C99: =CONCATENATE("MFGG","-",MID(E99,1,3),MID(E99,10,1),"-","IDD") -> #N/A | D99: =VLOOKUP(F99,Sheet2!$A$2:$D$31,4,0) -> #N/A | E99: =VLOOKUP(F99,Sheet2!$A$2:$D$31,2,0) -> #N/A | H99: =VLOOKUP(F99,Sheet2!$A$2:$D$31,3,0) -> #N/A | K99: =L99/G99 -> #DIV/0!
C100: =CONCATENATE("MFGG","-",MID(E100,1,3),MID(E100,10,1),"-","IDD") -> #N/A | D100: =VLOOKUP(F100,Sheet2!$A$2:$D$31,4,0) -> #N/A | E100: =VLOOKUP(F100,Sheet2!$A$2:$D$31,2,0) -> #N/A | H100: =VLOOKUP(F100,Sheet2!$A$2:$D$31,3,0) -> #N/A | K100: =L100/G100 -> #DIV/0!
C101: =CONCATENATE("MFGG","-",MID(E101,1,3),MID(E101,10,1),"-","IDD") -> #N/A | D101: =VLOOKUP(F101,Sheet2!$A$2:$D$31,4,0) -> #N/A | E101: =VLOOKUP(F101,Sheet2!$A$2:$D$31,2,0) -> #N/A | H101: =VLOOKUP(F101,Sheet2!$A$2:$D$31,3,0) -> #N/A | K101: =L101/G101 -> #DIV/0!
C102: =CONCATENATE("MFGG","-",MID(E102,1,3),MID(E102,10,1),"-","IDD") -> #N/A | D102: =VLOOKUP(F102,Sheet2!$A$2:$D$31,4,0) -> #N/A | E102: =VLOOKUP(F102,Sheet2!$A$2:$D$31,2,0) -> #N/A | H102: =VLOOKUP(F102,Sheet2!$A$2:$D$31,3,0) -> #N/A | K102: =L102/G102 -> #DIV/0!
C103: =CONCATENATE("MFGG","-",MID(E103,1,3),MID(E103,10,1),"-","IDD") -> #N/A | D103: =VLOOKUP(F103,Sheet2!$A$2:$D$31,4,0) -> #N/A | E103: =VLOOKUP(F103,Sheet2!$A$2:$D$31,2,0) -> #N/A | H103: =VLOOKUP(F103,Sheet2!$A$2:$D$31,3,0) -> #N/A | K103: =L103/G103 -> #DIV/0!
C104: =CONCATENATE("MFGG","-",MID(E104,1,3),MID(E104,10,1),"-","IDD") -> #N/A | D104: =VLOOKUP(F104,Sheet2!$A$2:$D$31,4,0) -> #N/A | E104: =VLOOKUP(F104,Sheet2!$A$2:$D$31,2,0) -> #N/A | H104: =VLOOKUP(F104,Sheet2!$A$2:$D$31,3,0) -> #N/A | K104: =L104/G104 -> #DIV/0!
... C112: =CONCATENATE("MFGG","-",MID(E112,1,3),MID(E112,10,1),"-","IDD") -> #N/A | D112: =VLOOKUP(F112,Sheet2!$A$2:$D$31,4,0) -> #N/A | E112: =VLOOKUP(F112,Sheet2!$A$2:$D$31,2,0) -> #N/A | H112: =VLOOKUP(F112,Sheet2!$A$2:$D$31,3,0) -> #N/A | K112: =L112/G112 -> #DIV/0!
E113: TOTAL | G113: =SUM(G93:G112) -> 0 | I113: =SUM(I93:I112) -> 0 | J113: =SUM(J93:J112) -> 0 | L113: =SUM(L93:L112) -> 0 | M113: =SUM(M93:M112) -> 0 | P113: =SUM(P93:P112) -> 0
B115: BOX 5 = GOLD JEWELRY
B116: No | C116: ID Code | D116: USA harmonized code | E116: Item | F116: ID | G116: Qty/Pcs,Pair | I116: N.Weight | J116: G.Weight | K116: Unit Value (material & manufacturing cost) | L116: Total Value (material & manufacturing cost) | M116: Manufacturing Cost (nilai maklon) | P116: Manufacturing + Dia + Gold for US
C117: =CONCATENATE("MFGG","-",MID(E117,1,3),MID(E117,10,1),"-","IDD") -> #N/A | D117: =VLOOKUP(F117,Sheet2!$A$2:$D$31,4,0) -> #N/A | E117: =VLOOKUP(F117,Sheet2!$A$2:$D$31,2,0) -> #N/A | H117: =VLOOKUP(F117,Sheet2!$A$2:$D$31,3,0) -> #N/A | K117: =L117/G117 -> #DIV/0!
C118: =CONCATENATE("MFGG","-",MID(E118,1,3),MID(E118,10,1),"-","IDD") -> #N/A | D118: =VLOOKUP(F118,Sheet2!$A$2:$D$31,4,0) -> #N/A | E118: =VLOOKUP(F118,Sheet2!$A$2:$D$31,2,0) -> #N/A | H118: =VLOOKUP(F118,Sheet2!$A$2:$D$31,3,0) -> #N/A | K118: =L118/G118 -> #DIV/0!
C119: =CONCATENATE("MFGG","-",MID(E119,1,3),MID(E119,10,1),"-","IDD") -> #N/A | D119: =VLOOKUP(F119,Sheet2!$A$2:$D$31,4,0) -> #N/A | E119: =VLOOKUP(F119,Sheet2!$A$2:$D$31,2,0) -> #N/A | H119: =VLOOKUP(F119,Sheet2!$A$2:$D$31,3,0) -> #N/A | K119: =L119/G119 -> #DIV/0!
C120: =CONCATENATE("MFGG","-",MID(E120,1,3),MID(E120,10,1),"-","IDD") -> #N/A | D120: =VLOOKUP(F120,Sheet2!$A$2:$D$31,4,0) -> #N/A | E120: =VLOOKUP(F120,Sheet2!$A$2:$D$31,2,0) -> #N/A | H120: =VLOOKUP(F120,Sheet2!$A$2:$D$31,3,0) -> #N/A | K120: =L120/G120 -> #DIV/0!
C121: =CONCATENATE("MFGG","-",MID(E121,1,3),MID(E121,10,1),"-","IDD") -> #N/A | D121: =VLOOKUP(F121,Sheet2!$A$2:$D$31,4,0) -> #N/A | E121: =VLOOKUP(F121,Sheet2!$A$2:$D$31,2,0) -> #N/A | H121: =VLOOKUP(F121,Sheet2!$A$2:$D$31,3,0) -> #N/A | K121: =L121/G121 -> #DIV/0!
C122: =CONCATENATE("MFGG","-",MID(E122,1,3),MID(E122,10,1),"-","IDD") -> #N/A | D122: =VLOOKUP(F122,Sheet2!$A$2:$D$31,4,0) -> #N/A | E122: =VLOOKUP(F122,Sheet2!$A$2:$D$31,2,0) -> #N/A | H122: =VLOOKUP(F122,Sheet2!$A$2:$D$31,3,0) -> #N/A | K122: =L122/G122 -> #DIV/0!
C123: =CONCATENATE("MFGG","-",MID(E123,1,3),MID(E123,10,1),"-","IDD") -> #N/A | D123: =VLOOKUP(F123,Sheet2!$A$2:$D$31,4,0) -> #N/A | E123: =VLOOKUP(F123,Sheet2!$A$2:$D$31,2,0) -> #N/A | H123: =VLOOKUP(F123,Sheet2!$A$2:$D$31,3,0) -> #N/A | K123: =L123/G123 -> #DIV/0!
C124: =CONCATENATE("MFGG","-",MID(E124,1,3),MID(E124,10,1),"-","IDD") -> #N/A | D124: =VLOOKUP(F124,Sheet2!$A$2:$D$31,4,0) -> #N/A | E124: =VLOOKUP(F124,Sheet2!$A$2:$D$31,2,0) -> #N/A | H124: =VLOOKUP(F124,Sheet2!$A$2:$D$31,3,0) -> #N/A | K124: =L124/G124 -> #DIV/0!
C125: =CONCATENATE("MFGG","-",MID(E125,1,3),MID(E125,10,1),"-","IDD") -> #N/A | D125: =VLOOKUP(F125,Sheet2!$A$2:$D$31,4,0) -> #N/A | E125: =VLOOKUP(F125,Sheet2!$A$2:$D$31,2,0) -> #N/A | H125: =VLOOKUP(F125,Sheet2!$A$2:$D$31,3,0) -> #N/A | K125: =L125/G125 -> #DIV/0!
C126: =CONCATENATE("MFGG","-",MID(E126,1,3),MID(E126,10,1),"-","IDD") -> #N/A | D126: =VLOOKUP(F126,Sheet2!$A$2:$D$31,4,0) -> #N/A | E126: =VLOOKUP(F126,Sheet2!$A$2:$D$31,2,0) -> #N/A | H126: =VLOOKUP(F126,Sheet2!$A$2:$D$31,3,0) -> #N/A | K126: =L126/G126 -> #DIV/0!
C127: =CONCATENATE("MFGG","-",MID(E127,1,3),MID(E127,10,1),"-","IDD") -> #N/A | D127: =VLOOKUP(F127,Sheet2!$A$2:$D$31,4,0) -> #N/A | E127: =VLOOKUP(F127,Sheet2!$A$2:$D$31,2,0) -> #N/A | H127: =VLOOKUP(F127,Sheet2!$A$2:$D$31,3,0) -> #N/A | K127: =L127/G127 -> #DIV/0!
C128: =CONCATENATE("MFGG","-",MID(E128,1,3),MID(E128,10,1),"-","IDD") -> #N/A | D128: =VLOOKUP(F128,Sheet2!$A$2:$D$31,4,0) -> #N/A | E128: =VLOOKUP(F128,Sheet2!$A$2:$D$31,2,0) -> #N/A | H128: =VLOOKUP(F128,Sheet2!$A$2:$D$31,3,0) -> #N/A | K128: =L128/G128 -> #DIV/0!
... C136: =CONCATENATE("MFGG","-",MID(E136,1,3),MID(E136,10,1),"-","IDD") -> #N/A | D136: =VLOOKUP(F136,Sheet2!$A$2:$D$31,4,0) -> #N/A | E136: =VLOOKUP(F136,Sheet2!$A$2:$D$31,2,0) -> #N/A | H136: =VLOOKUP(F136,Sheet2!$A$2:$D$31,3,0) -> #N/A | K136: =L136/G136 -> #DIV/0!
E137: TOTAL | G137: =SUM(G117:G136) -> 0 | I137: =SUM(I117:I136) -> 0 | J137: =SUM(J117:J136) -> 0 | L137: =SUM(L117:L136) -> 0 | M137: =SUM(M117:M136) -> 0 | P137: =SUM(P117:P136) -> 0
B139: BOX 6 = GOLD JEWELRY
B140: No | C140: ID Code | D140: USA harmonized code | E140: Item | F140: ID | G140: Qty/Pcs,Pair | I140: N.Weight | J140: G.Weight | K140: Unit Value (material & manufacturing cost) | L140: Total Value (material & manufacturing cost) | M140: Manufacturing Cost (nilai maklon) | P140: Manufacturing + Dia + Gold for US
C141: =CONCATENATE("MFGG","-",MID(E141,1,3),MID(E141,10,1),"-","IDD") -> #N/A | D141: =VLOOKUP(F141,Sheet2!$A$2:$D$31,4,0) -> #N/A | E141: =VLOOKUP(F141,Sheet2!$A$2:$D$31,2,0) -> #N/A | H141: =VLOOKUP(F141,Sheet2!$A$2:$D$31,3,0) -> #N/A | K141: =L141/G141 -> #DIV/0!
...

Sheet Int. Customs Invoice
A1: PT. VERONIQUE INDONESIA
A2: Jl. Raya Purwonegoro Rt. 007/003, Purwonegoro, Banjarnegara, Jawa Tengah, Zip Code : 53472, INDONESIA
A3: CUSTOMS INVOICE
A4: Seller: | B4: PT. VERONIQUE INDONESIA | H4: Invoice No. & Date : | J4: ='Customs Invoice'!K4 -> 0
B5: Jl. Raya Purwonegoro Rt. 007/003 Purwonegoro Banjarnegara | H5: L/C No. & Date) :
B6: Jawa Tengah Zip Code : 53472, INDONESIA | H6: ='Customs Invoice'!I6 -> BILL TO : | J6: ='Customs Invoice'!K6 -> 0
B7: Tel: 62-286-598-8594 Fax: 62-286-598-8650 | J7: ='Customs Invoice'!K7 -> 0
B8: NPWP :0315202689529000 | J8: ='Customs Invoice'!K8 -> 0
A9: Consignee: | B9: ='Customs Invoice'!B9 -> 0 | J9: ='Customs Invoice'!K9 -> 0
B10: ='Customs Invoice'!B10 -> 0 | J10: ='Customs Invoice'!K10 -> 0
B11: ='Customs Invoice'!B11 -> 0 | J11: ='Customs Invoice'!K11 -> 0
B12: ='Customs Invoice'!B12 -> 0
B13: ='Customs Invoice'!B13 -> 0 | H13: Other References: | J13: Country of Origin : INDONESIA
B14: ='Customs Invoice'!B14 -> 0 | J14: B/L No. :
A15: Departure Date: | B15: ='Customs Invoice'!B15 -> 0 | C15: Incoterm: FCA | D15: COUNTRY OF ORIGIN: INDONESIA | J15: A/C No. :
A16: Vessel/Flight: | B16: ='Customs Invoice'!B16 -> 0 | D16: From : INDONESIA | J16: C/T No. : 1
A17: ='Customs Invoice'!A17 -> To : | H17: Terms of Payment: | J17: 30 Day's Net
B18: =CONCATENATE("PT Veronique to International Customers_",LEFT('Customs Invoice'!K4,13)," Customs Invoice_New Merchandise") -> PT Veronique to International Customers_ Customs Invoice_New Merchandise
B19: BOX 1 = GOLD JEWELRY
B20: Origin | C20: Item description | D20: Entry Line | E20: Gross weight | F20: Net weight | G20: Sequence | H20: Manufacturing ID code | I20: Quantity | K20: Total value (gold value + stone value + manufacturing value) | L20: Value of return of customer's stones | M20: Applicable manufacturing value
B21: Indonesia | C21: ='Customs Invoice'!E21 -> #N/A | D21: 1 | E21: ='Customs Invoice'!J21 -> #DIV/0! | F21: ='Customs Invoice'!I21 -> 0 | G21: A | H21: ='Customs Invoice'!C21 -> #N/A | I21: ='Customs Invoice'!G21 -> 0 | J21: ='Customs Invoice'!H21 -> #N/A | K21: ='Customs Invoice'!P21 -> 0 | L21: ='Customs Invoice'!N21 -> 0 | M21: ='Customs Invoice'!M21 -> 0
C22: ='Customs Invoice'!E22 -> #N/A | D22: 2 | E22: ='Customs Invoice'!J22 -> 0 | F22: ='Customs Invoice'!I22 -> 0 | G22: A | H22: ='Customs Invoice'!C22 -> #N/A | I22: ='Customs Invoice'!G22 -> 0 | J22: ='Customs Invoice'!H22 -> #N/A | K22: ='Customs Invoice'!P22 -> 0 | L22: ='Customs Invoice'!N22 -> 0 | M22: ='Customs Invoice'!M22 -> 0
C23: ='Customs Invoice'!E23 -> #N/A | D23: 3 | E23: ='Customs Invoice'!J23 -> 0 | F23: ='Customs Invoice'!I23 -> 0 | G23: A | H23: ='Customs Invoice'!C23 -> #N/A | I23: ='Customs Invoice'!G23 -> 0 | J23: ='Customs Invoice'!H23 -> #N/A | K23: ='Customs Invoice'!P23 -> 0 | L23: ='Customs Invoice'!N23 -> 0 | M23: ='Customs Invoice'!M23 -> 0
C24: ='Customs Invoice'!E24 -> #N/A | D24: 4 | E24: ='Customs Invoice'!J24 -> 0 | F24: ='Customs Invoice'!I24 -> 0 | G24: A | H24: ='Customs Invoice'!C24 -> #N/A | I24: ='Customs Invoice'!G24 -> 0 | J24: ='Customs Invoice'!H24 -> #N/A | K24: ='Customs Invoice'!P24 -> 0 | L24: ='Customs Invoice'!N24 -> 0 | M24: ='Customs Invoice'!M24 -> 0
C25: ='Customs Invoice'!E25 -> #N/A | D25: 5 | E25: ='Customs Invoice'!J25 -> 0 | F25: ='Customs Invoice'!I25 -> 0 | G25: A | H25: ='Customs Invoice'!C25 -> #N/A | I25: ='Customs Invoice'!G25 -> 0 | J25: ='Customs Invoice'!H25 -> #N/A | K25: ='Customs Invoice'!P25 -> 0 | L25: ='Customs Invoice'!N25 -> 0 | M25: ='Customs Invoice'!M25 -> 0
C26: ='Customs Invoice'!E26 -> #N/A | D26: 6 | E26: ='Customs Invoice'!J26 -> 0 | F26: ='Customs Invoice'!I26 -> 0 | G26: A | H26: ='Customs Invoice'!C26 -> #N/A | I26: ='Customs Invoice'!G26 -> 0 | J26: ='Customs Invoice'!H26 -> #N/A | K26: ='Customs Invoice'!P26 -> 0 | L26: ='Customs Invoice'!N26 -> 0 | M26: ='Customs Invoice'!M26 -> 0
C27: ='Customs Invoice'!E27 -> #N/A | D27: 7 | E27: ='Customs Invoice'!J27 -> 0 | F27: ='Customs Invoice'!I27 -> 0 | G27: A | H27: ='Customs Invoice'!C27 -> #N/A | I27: ='Customs Invoice'!G27 -> 0 | J27: ='Customs Invoice'!H27 -> #N/A | K27: ='Customs Invoice'!P27 -> 0 | L27: ='Customs Invoice'!N27 -> 0 | M27: ='Customs Invoice'!M27 -> 0
C28: ='Customs Invoice'!E28 -> #N/A | D28: 8 | E28: ='Customs Invoice'!J28 -> 0 | F28: ='Customs Invoice'!I28 -> 0 | G28: A | H28: ='Customs Invoice'!C28 -> #N/A | I28: ='Customs Invoice'!G28 -> 0 | J28: ='Customs Invoice'!H28 -> #N/A | K28: ='Customs Invoice'!P28 -> 0 | L28: ='Customs Invoice'!N28 -> 0 | M28: ='Customs Invoice'!M28 -> 0
C29: ='Customs Invoice'!E29 -> #N/A | D29: 9 | E29: ='Customs Invoice'!J29 -> 0 | F29: ='Customs Invoice'!I29 -> 0 | G29: A | H29: ='Customs Invoice'!C29 -> #N/A | I29: ='Customs Invoice'!G29 -> 0 | J29: ='Customs Invoice'!H29 -> #N/A | K29: ='Customs Invoice'!P29 -> 0 | L29: ='Customs Invoice'!N29 -> 0 | M29: ='Customs Invoice'!M29 -> 0
C30: ='Customs Invoice'!E30 -> #N/A | D30: 10 | E30: ='Customs Invoice'!J30 -> 0 | F30: ='Customs Invoice'!I30 -> 0 | G30: A | H30: ='Customs Invoice'!C30 -> #N/A | I30: ='Customs Invoice'!G30 -> 0 | J30: ='Customs Invoice'!H30 -> #N/A | K30: ='Customs Invoice'!P30 -> 0 | L30: ='Customs Invoice'!N30 -> 0 | M30: ='Customs Invoice'!M30 -> 0
E31: =SUM(E21:E30) -> #DIV/0! | F31: =SUM(F21:F30) -> 0 | I31: =SUM(I21:I30) -> 0 | K31: =SUM(K21:K30) -> 0 | L31: =SUM(L21:L30) -> 0 | M31: =SUM(M21:M30) -> 0
F33: Manufacturing ID code | G33: Gross weight | H33: Net weight | I33: Total QTY | K33: Total value (gold value + stone value + manufacturing value) | L33: Value of return of customer's stones | M33: Applicable manufacturing value
E34: =C21 -> #N/A | F34: =H21 -> #N/A | G34: =E21 -> #DIV/0! | H34: =F21 -> 0 | I34: =I21 -> 0 | J34: =J21 -> #N/A | K34: =K21 -> 0 | L34: =L21 -> 0 | M34: =M21 -> 0
E35: =C22 -> #N/A | F35: =H22 -> #N/A | G35: =E22 -> 0 | H35: =F22 -> 0 | I35: =I22 -> 0 | J35: =J22 -> #N/A | K35: =K22 -> 0 | L35: =L22 -> 0 | M35: =M22 -> 0
E36: =C23 -> #N/A | F36: =H23 -> #N/A | G36: =E23 -> 0 | H36: =F23 -> 0 | I36: =I23 -> 0 | J36: =J23 -> #N/A | K36: =K23 -> 0 | L36: =L23 -> 0 | M36: =M23 -> 0
E37: =C24 -> #N/A | F37: =H24 -> #N/A | G37: =E24 -> 0 | H37: =F24 -> 0 | I37: =I24 -> 0 | J37: =J24 -> #N/A | K37: =K24 -> 0 | L37: =L24 -> 0 | M37: =M24 -> 0
E38: =C25 -> #N/A | F38: =H25 -> #N/A | G38: =E25 -> 0 | H38: =F25 -> 0 | I38: =I25 -> 0 | J38: =J25 -> #N/A | K38: =K25 -> 0 | L38: =L25 -> 0 | M38: =M25 -> 0
E39: =C26 -> #N/A | F39: =H26 -> #N/A | G39: =E26 -> 0 | H39: =F26 -> 0 | I39: =I26 -> 0 | J39: =J26 -> #N/A | K39: =K26 -> 0 | L39: =L26 -> 0 | M39: =M26 -> 0
E40: =C27 -> #N/A | F40: =H27 -> #N/A | G40: =E27 -> 0 | H40: =F27 -> 0 | I40: =I27 -> 0 | J40: =J27 -> #N/A | K40: =K27 -> 0 | L40: =L27 -> 0 | M40: =M27 -> 0
E41: =C28 -> #N/A | F41: =H28 -> #N/A | G41: =E28 -> 0 | H41: =F28 -> 0 | I41: =I28 -> 0 | J41: =J28 -> #N/A | K41: =K28 -> 0 | L41: =L28 -> 0 | M41: =M28 -> 0
E42: =C29 -> #N/A | F42: =H29 -> #N/A | G42: =E29 -> 0 | H42: =F29 -> 0 | I42: =I29 -> 0 | J42: =J29 -> #N/A | K42: =K29 -> 0 | L42: =L29 -> 0 | M42: =M29 -> 0
E43: =C30 -> #N/A | F43: =H30 -> #N/A | G43: =E30 -> 0 | H43: =F30 -> 0 | I43: =I30 -> 0 | J43: =J28 -> #N/A | K43: =K28 -> 0 | L43: =L28 -> 0 | M43: =M30 -> 0
G44: =SUM(G34:G43) -> #DIV/0! | H44: =SUM(H34:H43) -> 0 | I44: =SUM(I34:I43) -> 0 | K44: =SUM(K34:K43) -> 0 | L44: =SUM(L34:L43) -> 0 | M44: =SUM(M34:M43) -> 0
L45: Handling charge | M45: 0
L46: Document fee | M46: 30
M47: =SUM(M44:M46) -> 30
H50: PRESIDENT J.E. PARK

Sheet Sheet2
A1: ID | B1: NAMA | C1: UNIT | D1: HS CODE
A2: 14KB | B2: 14K Gold Bracelet | C2: Pcs | D2: 7113.19.5091 | F2: Pcs
A3: 14KB1 | B3: 14K Gold Bracelet | C3: Pcs | D3: 9903.03.01 | F3: Pcs
A4: 14KE | B4: 14K Gold Earring | C4: Pairs | D4: 7113.19.5091 | F4: Pairs
A5: 14KE1 | B5: 14K Gold Earring | C5: Pairs | D5: 9903.03.01 | F5: Pairs
A6: 14KN | B6: 14K Gold Necklace | C6: Pcs | D6: 7113.19.2900 | F6: Pcs
A7: 14KN1 | B7: 14K Gold Necklace | C7: Pcs | D7: 9903.03.01 | F7: Pcs
A8: 14KP | B8: 14K Gold Pendant | C8: Pcs | D8: 7113.19.5091 | F8: Pcs
A9: 14KP1 | B9: 14K Gold Pendant | C9: Pcs | D9: 9903.03.01 | F9: Pcs
A10: 14KR | B10: 14K Gold Ring | C10: Pcs | D10: 7113.19.5091 | F10: Pcs
A11: 14KR1 | B11: 14K Gold Ring | C11: Pcs | D11: 9903.03.01 | F11: Pcs
A12: 18KB | B12: 18K Gold Bracelet | C12: Pcs | D12: 7113.19.5091 | F12: Pcs
A13: 18KB1 | B13: 18K Gold Bracelet | C13: Pcs | D13: 9903.03.01 | F13: Pcs
... A21: 18KR1 | B21: 18K Gold Ring | C21: Pcs | D21: 9903.03.01 | F21: Pcs

Sheet Sheet3
A1: ID | B1: NAMA | C1: UNIT | D1: HS CODE
A2: 10KB | B2: 10K Gold Bracelet | C2: Pcs | D2: 7113.19.5091
A3: 10KE | B3: 10K Gold Earring | C3: Pairs | D3: 7113.19.5091
A4: 10KN | B4: 10K Gold Necklace | C4: Pcs | D4: 7113.19.2900
A5: 10KN KING | B5: 10K Gold Necklace | C5: Pcs | D5: 7113.19.2100
A6: 10KP | B6: 10K Gold Pendant | C6: Pcs | D6: 7113.19.5091
A7: 10KR | B7: 10K Gold Ring | C7: Pcs | D7: 7113.19.5091
A8: 14KB | B8: 14K Gold Bracelet | C8: Pcs | D8: 7113.19.5091
A9: 14KE | B9: 14K Gold Earring | C9: Pairs | D9: 7113.19.5091
A10: 14KN | B10: 14K Gold Necklace | C10: Pcs | D10: 7113.19.2900
A11: 14KP | B11: 14K Gold Pendant | C11: Pcs | D11: 7113.19.5091
A12: 14KR | B12: 14K Gold Ring | C12: Pcs | D12: 7113.19.5091
... A31: 18KN KING | B31: 18K Gold Necklace | C31: Pcs | D31: 7113.19.2100
